Workbook
Name impfibra: implantacao!$A:$V
Name servicossistemas: servicos!$D$8:$D$163
Name Print_Area: 'orcamento-2026'!$A$1:$R$78
Name municipios: regiao!$A$6:$A$150
Name indiceclientesimp: implantacao!$B:$B
Name mesorregioes: regiao!$L$168:$L$173

Sheet orcamento-2026
B1: EMPRESA DE TECNOLOGIA DA INFORMAÇÃO E COMUNICAÇÃO DO ESTADO DO PARÁ
A3: Emissão: | B3: =TODAY() -> 46232 | H3: Orçamento nº | K3: 057/2026
A4: DADOS DO CLIENTE | P4: OCULTAR | X4: Contatos
A5: Cliente: | B5: =VLOOKUP(N5,clientes!A:B,2,0) -> Tribunal de Contas do Estado | N5: TCE | X5: =IFERROR(__xludf.DUMMYFUNCTION("IFERROR(FILTER(contatos!D:D, contatos!$C:$C = $N$5), ""..."")"),"Thyago Souza de Andrade") -> Thyago Souza de Andrade
A6: CNPJ: | B6: =VLOOKUP(N5,clientes!A:H,4,0) | X6: =IFERROR(__xludf.DUMMYFUNCTION("""COMPUTED_VALUE"""),"Mônica Regina Câmara") -> Mônica Regina Câmara
A7: Endereço: | B7: =CONCATENATE(VLOOKUP($N$5,clientes!A:M,8,0)," , ",VLOOKUP($N$5,clientes!A:M,9,0)," , ",VLOOKUP($N$5,clientes!A:L,11,0)," , ",VLOOKUP($N$5,clientes!A:M,12,0)) -> Tv. Quintino Bocaiúva, 1585 , Nazaré , Belém , PA
A8: Nome: | B8: Thyago Souza de Andrade
A9: Cargo: | B9: {=IFERROR(XLOOKUP($B$8, contatos!$D:$D, contatos!E:E), " ")}
A10: Setor: | B10: {=IFERROR(XLOOKUP($B$8, contatos!$D:$D, contatos!F:F), " ")} -> Coordenadoria de Infraestrutura e Segurança - Secretaria de Tecnologia da Informação
A11: E-mail: | B11: {=IFERROR(TEXTJOIN(" ", TRUE, XLOOKUP($B$8, contatos!$D:$D, contatos!I:I), XLOOKUP($B$8, contatos!$D:$D, contatos!J:J)), " ")} -> thyago.andrade@tcepa.tc.br
A12: Telefone | B12: {=IFERROR(TEXTJOIN(" ", TRUE, XLOOKUP($B$8, contatos!$D:$D, contatos!G:G), XLOOKUP($B$8, contatos!$D:$D, contatos!H:H)), " ")} -> (91) 3210-0530
A14: 5.1 - INSTALAÇÃO | O14: OCULTAR
A15: Item | B15: Município | C15: Região | D15: Nome | E15: Código | F15: Serviço | G15: Tipo | H15: Status | I15: Incluir | J15: Qtd | K15: Grandeza | L15: Custo | M15: Ocultar | N15: Total | O15: Ativação | P15: Configuração | Q15: Desp Adm | R15: Com/Sem | S15: Reaparelhamento | T15: Impostos | U15: Coluna 1 | V15: Coluna 2 | W15: Coluna 3 | X15: Coluna 4
A16: =ROW()-ROW(tabelaimplantacao_3[[#HEADERS],[Item]]) -> 1 | B16: PARAGOMINAS | C16: =ifna(VLOOKUP(B16,regiao[[#ALL],[MUNICÍPIO]:[REGIAO_INTEGRACAO]],5,0),"") -> SUDESTE | D16: SINE | E16: {=XLOOKUP(F16&G16,servicos!F:F,servicos!C:C)} -> 5300 | F16: Implantação de infraestrutura de | G16: FIBRA | H16: Previsto | I16: FALSE | J16: 1 | K16: {=XLOOKUP(F16&G16,servicos!$F:$F,servicos!I:I,"Não encontrado",0,1)} -> Configuração, Cabeamento, Equipamento | L16: 0 | N16: =IF(O15<>0,tabelaimplantacao_3[Custo]+tabelaimplantacao_3[Ativação]+tabelaimplantacao_3[Configuração]+tabelaimplantacao_3[Desp Adm]+tabelaimplantacao_3[Reaparelhamento]+tabelaimplantacao_3[Impostos],0) -> 885.41606 | O16: =IF(tabelaimplantacao_3[Tipo]="Fibra",pconfig!$G$7,pconfig!$G$7) -> 285.71 | P16: =IF(tabelaimplantacao_3[Tipo]="Radio",pconfig!$G$9,pconfig!$G$8) -> 316.45 | Q16: =(tabelaimplantacao_3[Custo]+tabelaimplantacao_3[Ativação]+tabelaimplantacao_3[Configuração])*pconfig!$G$2 -> 60.216 | R16: TRUE | S16: =IF(R16<>FALSE,(tabelaimplantacao_3[Custo]+tabelaimplantacao_3[Ativação]+tabelaimplantacao_3[Configuração])*pconfig!$G$3,0) -> 120.432 | T16: =(tabelaimplantacao_3[Custo]+tabelaimplantacao_3[Ativação]+tabelaimplantacao_3[Configuração])*pconfig!$G$4 -> 102.60806
A17: =ROW()-ROW(tabelaimplantacao_3[[#HEADERS],[Item]]) -> 2 | B17: ANANINDEUA | C17: =ifna(VLOOKUP(B17,regiao[[#ALL],[MUNICÍPIO]:[REGIAO_INTEGRACAO]],5,0),"") -> METROPOLITANA | D17: SINE | E17: {=XLOOKUP(F17&G17,servicos!F:F,servicos!C:C)} -> 5300 | F17: Implantação de infraestrutura de | G17: FIBRA | H17: Previsto | I17: FALSE | J17: 1 | K17: {=XLOOKUP(F17&G17,servicos!$F:$F,servicos!I:I,"Não encontrado",0,1)} -> Configuração, Cabeamento, Equipamento | L17: 0 | N17: =IF(O16<>0,tabelaimplantacao_3[Custo]+tabelaimplantacao_3[Ativação]+tabelaimplantacao_3[Configuração]+tabelaimplantacao_3[Desp Adm]+tabelaimplantacao_3[Reaparelhamento]+tabelaimplantacao_3[Impostos],0) -> 885.41606 | O17: =IF(tabelaimplantacao_3[Tipo]="Fibra",pconfig!$G$7,pconfig!$G$7) -> 285.71 | P17: =IF(tabelaimplantacao_3[Tipo]="Radio",pconfig!$G$9,pconfig!$G$8) -> 316.45 | Q17: =(tabelaimplantacao_3[Custo]+tabelaimplantacao_3[Ativação]+tabelaimplantacao_3[Configuração])*pconfig!$G$2 -> 60.216 | R17: TRUE | S17: =IF(R17<>FALSE,(tabelaimplantacao_3[Custo]+tabelaimplantacao_3[Ativação]+tabelaimplantacao_3[Configuração])*pconfig!$G$3,0) -> 120.432 | T17: =(tabelaimplantacao_3[Custo]+tabelaimplantacao_3[Ativação]+tabelaimplantacao_3[Configuração])*pconfig!$G$4 -> 102.60806
A18: TOTAL IMPLANTAÇÃO | N18: =SUMIF(tabelaimplantacao_3[[#ALL],[Incluir]],TRUE,tabelaimplantacao_3[[#ALL],[Total]]) -> 0
A20: 5.2 - SERVIÇOS DE TELECOM - LINK DE DADOS | P20: OCULTAR
A21: Item | B21: Município | C21: Região | D21: Unidade | E21: Código | F21: Serviço | G21: Tipo | H21: Status | I21: Incluir | J21: Qtd | K21: Grandeza | L21: Tabela-ano | M21: Ocultar | N21: Mensal | O21: Total Mensal c/ Reajuste | P21: Unitário | Q21: Preço Manutenção | R21: Total | S21: Mensal 2021 | T21: Mensal 2022 | U21: Mensal 2023 | V21: Mensal 2024 | W21: Mensal 2025 | X21: Mensal 2026 | Y21: 2026-reg
A22: =ROW()-ROW(tabelatelecom_3[[#HEADERS],[Item]]) -> 1 | B22: BELEM | C22: =ifna(VLOOKUP(B22,regiao[[#ALL],[MUNICÍPIO]:[REGIAO_INTEGRACAO]],5,0),"") -> METROPOLITANA | D22: CIIC | E22: {=XLOOKUP(F22&G22,servicos!F:F,servicos!C:C)} -> 5279 | F22: Link de Dados | G22: FIBRA | H22: Ativo | I22: TRUE | J22: 1 | K22: {=XLOOKUP($F22&G22,servicos!$F:$F,servicos!I:I,"Não encontrado",0,1)} -> Mbps | L22: 2025 | N22: =IFS(L22=2021,ROUND(R22,2),L22=2022,ROUND(R22*(1+pconfig!$B$2),2),L22=2023,ROUND(T22*(1+pconfig!$B$3),2),L22=2024,ROUND(U22*(1+pconfig!$B$4),2),L22=2025, ROUND(V22*(1+pconfig!$B$5),2),L22=2026, ROUND(W22*(1+pconfig!$B$6),2),L22="regiaointegracao",Y22*J22) -> 275.91 | O22: =N22*(1+'historico-reajuste'!$C$2)*(1+'historico-reajuste'!$C$3) -> 275.91 | P22: {=XLOOKUP(B22&G22,linkdados!E:E,linkdados!L:L)*J22} -> 23.980363 | Q22: {=XLOOKUP(B22&G22,linkdados!E:E,linkdados!N:N,"")} -> 178.8142 | R22: =IFERROR(__xludf.DUMMYFUNCTION("IF(F22=""Link de Dados"", IFS(J22<=pconfig!$B$12,P22*pconfig!$C$12,J22<=pconfig!$B$13,P22*pconfig!$C$13,J22<=pconfig!$B$14,P22*pconfig!$C$14,J22<=pconfig!$B$15,P22*pconfig!$C$15,J22<=pconfig!$B$16,P22*pconfig!$C$16,J22<=pconfig!$B$17,P22*pconfig!$C$17,J22"&"<=pconfig!$B$18,P22*pconfig!$C$18,J22<=pconfig!$B$19,P22*pconfig!$C$19,J22<=pconfig!$B$20,P22*pconfig!$C$20,J22<=pconfig!$B$21,P22*pconfig!$C$21)+Q22,IF(H22=""Mensal"",FILTER(servicos!O:O,servicos!F:F=F22&G22)*J22,P22))"),202.79456193353474) -> 202.79456 | S22: =IF(F22="Link de Dados",R22,0) -> 202.79456 | T22: =IF(F22="Link de Dados",S22*(1+pconfig!$B$2),S22) -> 238.87171 | U22: =IF(F22="Link de Dados",T22*(1+pconfig!$B$3),T22) -> 254.92389 | V22: =U22*(1+pconfig!$B$4) -> 258.97718 | W22: =V22*(1+pconfig!$B$5) -> 275.91429 | X22: =W22*(1+pconfig!$B$6) -> 284.96428 | Y22: {=XLOOKUP(B22,regiao!A:A,regiao!H:H,0,1)} -> 69.86
A23: =ROW()-ROW(tabelatelecom_3[[#HEADERS],[Item]]) -> 2 | B23: SANTAREM | C23: =ifna(VLOOKUP(B23,regiao[[#ALL],[MUNICÍPIO]:[REGIAO_INTEGRACAO]],5,0),"") -> BAIXO AMAZONAS | D23: ABRIGO LAR DA PROVIDENCIA | E23: {=XLOOKUP(F23&G23,servicos!F:F,servicos!C:C)} -> 5279 | F23: Link de Dados | G23: FIBRA | H23: Ativo | I23: TRUE | J23: 1 | K23: {=XLOOKUP($F23&G23,servicos!$F:$F,servicos!I:I,"Não encontrado",0,1)} -> Mbps | L23: 2022 | N23: =IFS(L23=2021,ROUND(R23,2),L23=2022,ROUND(R23*(1+pconfig!$B$2),2),L23=2023,ROUND(T23*(1+pconfig!$B$3),2),L23=2024,ROUND(U23*(1+pconfig!$B$4),2),L23=2025, ROUND(V23*(1+pconfig!$B$5),2),L23=2026, ROUND(W23*(1+pconfig!$B$6),2),L23="regiaointegracao",Y23*J23) -> 331.28 | O23: =N23*(1+'historico-reajuste'!$C$2)*(1+'historico-reajuste'!$C$3) -> 331.28 | P23: {=XLOOKUP(B23&G23,linkdados!E:E,linkdados!L:L)*J23} -> 29.550604 | Q23: {=XLOOKUP(B23&G23,linkdados!E:E,linkdados!N:N,"")} -> 251.6994 | R23: =IFERROR(__xludf.DUMMYFUNCTION("IF(F23=""Link de Dados"", IFS(J23<=pconfig!$B$12,P23*pconfig!$C$12,J23<=pconfig!$B$13,P23*pconfig!$C$13,J23<=pconfig!$B$14,P23*pconfig!$C$14,J23<=pconfig!$B$15,P23*pconfig!$C$15,J23<=pconfig!$B$16,P23*pconfig!$C$16,J23<=pconfig!$B$17,P23*pconfig!$C$17,J23"&"<=pconfig!$B$18,P23*pconfig!$C$18,J23<=pconfig!$B$19,P23*pconfig!$C$19,J23<=pconfig!$B$20,P23*pconfig!$C$20,J23<=pconfig!$B$21,P23*pconfig!$C$21)+Q23,IF(H23=""Mensal"",FILTER(servicos!O:O,servicos!F:F=F23&G23)*J23,P23))"),281.25000000000006) -> 281.25 | S23: =IF(F23="Link de Dados",R23,0) -> 281.25 | T23: =IF(F23="Link de Dados",S23*(1+pconfig!$B$2),S23) -> 331.28438 | U23: =IF(F23="Link de Dados",T23*(1+pconfig!$B$3),T23) -> 353.54669 | V23: =U23*(1+pconfig!$B$4) -> 359.16808 | W23: =V23*(1+pconfig!$B$5) -> 382.65767 | X23: =W23*(1+pconfig!$B$6) -> 395.20884 | Y23: {=XLOOKUP(B23,regiao!A:A,regiao!H:H,0,1)} -> 72.86
A24: =ROW()-ROW(tabelatelecom_3[[#HEADERS],[Item]]) -> 3 | B24: SANTAREM | C24: =ifna(VLOOKUP(B24,regiao[[#ALL],[MUNICÍPIO]:[REGIAO_INTEGRACAO]],5,0),"") -> BAIXO AMAZONAS | D24: ABRIGO SOCORRO GABRIEL | E24: {=XLOOKUP(F24&G24,servicos!F:F,servicos!C:C)} -> 5279 | F24: Link de Dados | G24: FIBRA | H24: Ativo | I24: TRUE | J24: 1 | K24: {=XLOOKUP($F24&G24,servicos!$F:$F,servicos!I:I,"Não encontrado",0,1)} -> Mbps | L24: 2022 | N24: =IFS(L24=2021,ROUND(R24,2),L24=2022,ROUND(R24*(1+pconfig!$B$2),2),L24=2023,ROUND(T24*(1+pconfig!$B$3),2),L24=2024,ROUND(U24*(1+pconfig!$B$4),2),L24=2025, ROUND(V24*(1+pconfig!$B$5),2),L24=2026, ROUND(W24*(1+pconfig!$B$6),2),L24="regiaointegracao",Y24*J24) -> 331.28 | O24: =N24*(1+'historico-reajuste'!$C$2)*(1+'historico-reajuste'!$C$3) -> 331.28 | P24: {=XLOOKUP(B24&G24,linkdados!E:E,linkdados!L:L)*J24} -> 29.550604 | Q24: {=XLOOKUP(B24&G24,linkdados!E:E,linkdados!N:N,"")} -> 251.6994 | R24: =IFERROR(__xludf.DUMMYFUNCTION("IF(F24=""Link de Dados"", IFS(J24<=pconfig!$B$12,P24*pconfig!$C$12,J24<=pconfig!$B$13,P24*pconfig!$C$13,J24<=pconfig!$B$14,P24*pconfig!$C$14,J24<=pconfig!$B$15,P24*pconfig!$C$15,J24<=pconfig!$B$16,P24*pconfig!$C$16,J24<=pconfig!$B$17,P24*pconfig!$C$17,J24"&"<=pconfig!$B$18,P24*pconfig!$C$18,J24<=pconfig!$B$19,P24*pconfig!$C$19,J24<=pconfig!$B$20,P24*pconfig!$C$20,J24<=pconfig!$B$21,P24*pconfig!$C$21)+Q24,IF(H24=""Mensal"",FILTER(servicos!O:O,servicos!F:F=F24&G24)*J24,P24))"),281.25000000000006) -> 281.25 | S24: =IF(F24="Link de Dados",R24,0) -> 281.25 | T24: =IF(F24="Link de Dados",S24*(1+pconfig!$B$2),S24) -> 331.28438 | U24: =IF(F24="Link de Dados",T24*(1+pconfig!$B$3),T24) -> 353.54669 | V24: =U24*(1+pconfig!$B$4) -> 359.16808 | W24: =V24*(1+pconfig!$B$5) -> 382.65767 | X24: =W24*(1+pconfig!$B$6) -> 395.20884 | Y24: {=XLOOKUP(B24,regiao!A:A,regiao!H:H,0,1)} -> 72.86
A25: =ROW()-ROW(tabelatelecom_3[[#HEADERS],[Item]]) -> 4 | B25: BELEM | C25: =ifna(VLOOKUP(B25,regiao[[#ALL],[MUNICÍPIO]:[REGIAO_INTEGRACAO]],5,0),"") -> METROPOLITANA | D25: PADRE EUTÍQUIO | E25: {=XLOOKUP(F25&G25,servicos!F:F,servicos!C:C)} -> 5279 | F25: Link de Dados | G25: FIBRA | H25: Ativo | I25: TRUE | J25: 1 | K25: {=XLOOKUP($F25&G25,servicos!$F:$F,servicos!I:I,"Não encontrado",0,1)} -> Mbps | L25: 2022 | N25: =IFS(L25=2021,ROUND(R25,2),L25=2022,ROUND(R25*(1+pconfig!$B$2),2),L25=2023,ROUND(T25*(1+pconfig!$B$3),2),L25=2024,ROUND(U25*(1+pconfig!$B$4),2),L25=2025, ROUND(V25*(1+pconfig!$B$5),2),L25=2026, ROUND(W25*(1+pconfig!$B$6),2),L25="regiaointegracao",Y25*J25) -> 238.87 | O25: =N25*(1+'historico-reajuste'!$C$2)*(1+'historico-reajuste'!$C$3) -> 238.87 | P25: {=XLOOKUP(B25&G25,linkdados!E:E,linkdados!L:L)*J25} -> 23.980363 | Q25: {=XLOOKUP(B25&G25,linkdados!E:E,linkdados!N:N,"")} -> 178.8142 | R25: =IFERROR(__xludf.DUMMYFUNCTION("IF(F25=""Link de Dados"", IFS(J25<=pconfig!$B$12,P25*pconfig!$C$12,J25<=pconfig!$B$13,P25*pconfig!$C$13,J25<=pconfig!$B$14,P25*pconfig!$C$14,J25<=pconfig!$B$15,P25*pconfig!$C$15,J25<=pconfig!$B$16,P25*pconfig!$C$16,J25<=pconfig!$B$17,P25*pconfig!$C$17,J25"&"<=pconfig!$B$18,P25*pconfig!$C$18,J25<=pconfig!$B$19,P25*pconfig!$C$19,J25<=pconfig!$B$20,P25*pconfig!$C$20,J25<=pconfig!$B$21,P25*pconfig!$C$21)+Q25,IF(H25=""Mensal"",FILTER(servicos!O:O,servicos!F:F=F25&G25)*J25,P25))"),202.79456193353474) -> 202.79456 | S25: =IF(F25="Link de Dados",R25,0) -> 202.79456 | T25: =IF(F25="Link de Dados",S25*(1+pconfig!$B$2),S25) -> 238.87171 | U25: =IF(F25="Link de Dados",T25*(1+pconfig!$B$3),T25) -> 254.92389 | V25: =U25*(1+pconfig!$B$4) -> 258.97718 | W25: =V25*(1+pconfig!$B$5) -> 275.91429 | X25: =W25*(1+pconfig!$B$6) -> 284.96428 | Y25: {=XLOOKUP(B25,regiao!A:A,regiao!H:H,0,1)} -> 69.86
A26: =ROW()-ROW(tabelatelecom_3[[#HEADERS],[Item]]) -> 5 | B26: BELEM | C26: =ifna(VLOOKUP(B26,regiao[[#ALL],[MUNICÍPIO]:[REGIAO_INTEGRACAO]],5,0),"") -> METROPOLITANA | D26: SEDE | E26: {=XLOOKUP(F26&G26,servicos!F:F,servicos!C:C)} -> 5279 | F26: Link de Dados | G26: FIBRA | H26: Ativo | I26: TRUE | J26: 1 | K26: {=XLOOKUP($F26&G26,servicos!$F:$F,servicos!I:I,"Não encontrado",0,1)} -> Mbps | L26: 2022 | N26: =IFS(L26=2021,ROUND(R26,2),L26=2022,ROUND(R26*(1+pconfig!$B$2),2),L26=2023,ROUND(T26*(1+pconfig!$B$3),2),L26=2024,ROUND(U26*(1+pconfig!$B$4),2),L26=2025, ROUND(V26*(1+pconfig!$B$5),2),L26=2026, ROUND(W26*(1+pconfig!$B$6),2),L26="regiaointegracao",Y26*J26) -> 238.87 | O26: =N26*(1+'historico-reajuste'!$C$2)*(1+'historico-reajuste'!$C$3) -> 238.87 | P26: {=XLOOKUP(B26&G26,linkdados!E:E,linkdados!L:L)*J26} -> 23.980363 | Q26: {=XLOOKUP(B26&G26,linkdados!E:E,linkdados!N:N,"")} -> 178.8142 | R26: =IFERROR(__xludf.DUMMYFUNCTION("IF(F26=""Link de Dados"", IFS(J26<=pconfig!$B$12,P26*pconfig!$C$12,J26<=pconfig!$B$13,P26*pconfig!$C$13,J26<=pconfig!$B$14,P26*pconfig!$C$14,J26<=pconfig!$B$15,P26*pconfig!$C$15,J26<=pconfig!$B$16,P26*pconfig!$C$16,J26<=pconfig!$B$17,P26*pconfig!$C$17,J26"&"<=pconfig!$B$18,P26*pconfig!$C$18,J26<=pconfig!$B$19,P26*pconfig!$C$19,J26<=pconfig!$B$20,P26*pconfig!$C$20,J26<=pconfig!$B$21,P26*pconfig!$C$21)+Q26,IF(H26=""Mensal"",FILTER(servicos!O:O,servicos!F:F=F26&G26)*J26,P26))"),202.79456193353474) -> 202.79456 | S26: =IF(F26="Link de Dados",R26,0) -> 202.79456 | T26: =IF(F26="Link de Dados",S26*(1+pconfig!$B$2),S26) -> 238.87171 | U26: =IF(F26="Link de Dados",T26*(1+pconfig!$B$3),T26) -> 254.92389 | V26: =U26*(1+pconfig!$B$4) -> 258.97718 | W26: =V26*(1+pconfig!$B$5) -> 275.91429 | X26: =W26*(1+pconfig!$B$6) -> 284.96428 | Y26: {=XLOOKUP(B26,regiao!A:A,regiao!H:H,0,1)} -> 69.86
A27: =ROW()-ROW(tabelatelecom_3[[#HEADERS],[Item]]) -> 6 | B27: ANANINDEUA | C27: =ifna(VLOOKUP(B27,regiao[[#ALL],[MUNICÍPIO]:[REGIAO_INTEGRACAO]],5,0),"") -> METROPOLITANA | D27: SINE | E27: {=XLOOKUP(F27&G27,servicos!F:F,servicos!C:C)} -> 5279 | F27: Link de Dados | G27: FIBRA | H27: Ativo | I27: TRUE | J27: 1 | K27: {=XLOOKUP($F27&G27,servicos!$F:$F,servicos!I:I,"Não encontrado",0,1)} -> Mbps | L27: 2022 | N27: =IFS(L27=2021,ROUND(R27,2),L27=2022,ROUND(R27*(1+pconfig!$B$2),2),L27=2023,ROUND(T27*(1+pconfig!$B$3),2),L27=2024,ROUND(U27*(1+pconfig!$B$4),2),L27=2025, ROUND(V27*(1+pconfig!$B$5),2),L27=2026, ROUND(W27*(1+pconfig!$B$6),2),L27="regiaointegracao",Y27*J27) -> 241.7 | O27: =N27*(1+'historico-reajuste'!$C$2)*(1+'historico-reajuste'!$C$3) -> 241.7 | P27: {=XLOOKUP(B27&G27,linkdados!E:E,linkdados!L:L)*J27} -> 26.378399 | Q27: {=XLOOKUP(B27&G27,linkdados!E:E,linkdados!N:N,"")} -> 178.8142 | R27: =IFERROR(__xludf.DUMMYFUNCTION("IF(F27=""Link de Dados"", IFS(J27<=pconfig!$B$12,P27*pconfig!$C$12,J27<=pconfig!$B$13,P27*pconfig!$C$13,J27<=pconfig!$B$14,P27*pconfig!$C$14,J27<=pconfig!$B$15,P27*pconfig!$C$15,J27<=pconfig!$B$16,P27*pconfig!$C$16,J27<=pconfig!$B$17,P27*pconfig!$C$17,J27"&"<=pconfig!$B$18,P27*pconfig!$C$18,J27<=pconfig!$B$19,P27*pconfig!$C$19,J27<=pconfig!$B$20,P27*pconfig!$C$20,J27<=pconfig!$B$21,P27*pconfig!$C$21)+Q27,IF(H27=""Mensal"",FILTER(servicos!O:O,servicos!F:F=F27&G27)*J27,P27))"),205.1925981873112) -> 205.1926 | S27: =IF(F27="Link de Dados",R27,0) -> 205.1926 | T27: =IF(F27="Link de Dados",S27*(1+pconfig!$B$2),S27) -> 241.69636 | U27: =IF(F27="Link de Dados",T27*(1+pconfig!$B$3),T27) -> 257.93836 | V27: =U27*(1+pconfig!$B$4) -> 262.03958 | W27: =V27*(1+pconfig!$B$5) -> 279.17697 | X27: =W27*(1+pconfig!$B$6) -> 288.33397 | Y27: {=XLOOKUP(B27,regiao!A:A,regiao!H:H,0,1)} -> 69.86
A28: =ROW()-ROW(tabelatelecom_3[[#HEADERS],[Item]]) -> 7 | B28: CASTANHAL | C28: =ifna(VLOOKUP(B28,regiao[[#ALL],[MUNICÍPIO]:[REGIAO_INTEGRACAO]],5,0),"") -> METROPOLITANA | D28: CRAS | E28: {=XLOOKUP(F28&G28,servicos!F:F,servicos!C:C)} -> 5279 | F28: Link de Dados | G28: FIBRA | H28: Ativo | I28: TRUE | J28: 1 | K28: {=XLOOKUP($F28&G28,servicos!$F:$F,servicos!I:I,"Não encontrado",0,1)} -> Mbps | L28: 2022 | N28: =IFS(L28=2021,ROUND(R28,2),L28=2022,ROUND(R28*(1+pconfig!$B$2),2),L28=2023,ROUND(T28*(1+pconfig!$B$3),2),L28=2024,ROUND(U28*(1+pconfig!$B$4),2),L28=2025, ROUND(V28*(1+pconfig!$B$5),2),L28=2026, ROUND(W28*(1+pconfig!$B$6),2),L28="regiaointegracao",Y28*J28) -> 188.36 | O28: =N28*(1+'historico-reajuste'!$C$2)*(1+'historico-reajuste'!$C$3) -> 188.36 | P28: {=XLOOKUP(B28&G28,linkdados!E:E,linkdados!L:L)*J28} -> 26.378399 | Q28: {=XLOOKUP(B28&G28,linkdados!E:E,linkdados!N:N,"")} -> 133.53474 | R28: =IFERROR(__xludf.DUMMYFUNCTION("IF(F28=""Link de Dados"", IFS(J28<=pconfig!$B$12,P28*pconfig!$C$12,J28<=pconfig!$B$13,P28*pconfig!$C$13,J28<=pconfig!$B$14,P28*pconfig!$C$14,J28<=pconfig!$B$15,P28*pconfig!$C$15,J28<=pconfig!$B$16,P28*pconfig!$C$16,J28<=pconfig!$B$17,P28*pconfig!$C$17,J28"&"<=pconfig!$B$18,P28*pconfig!$C$18,J28<=pconfig!$B$19,P28*pconfig!$C$19,J28<=pconfig!$B$20,P28*pconfig!$C$20,J28<=pconfig!$B$21,P28*pconfig!$C$21)+Q28,IF(H28=""Mensal"",FILTER(servicos!O:O,servicos!F:F=F28&G28)*J28,P28))"),159.9131419939577) -> 159.91314 | S28: =IF(F28="Link de Dados",R28,0) -> 159.91314 | T28: =IF(F28="Link de Dados",S28*(1+pconfig!$B$2),S28) -> 188.36169 | U28: =IF(F28="Link de Dados",T28*(1+pconfig!$B$3),T28) -> 201.0196 | V28: =U28*(1+pconfig!$B$4) -> 204.21581 | W28: =V28*(1+pconfig!$B$5) -> 217.57152 | X28: =W28*(1+pconfig!$B$6) -> 224.70787 | Y28: {=XLOOKUP(B28,regiao!A:A,regiao!H:H,0,1)} -> 77.04
A29: =ROW()-ROW(tabelatelecom_3[[#HEADERS],[Item]]) -> 8 | B29: PARAGOMINAS | C29: =ifna(VLOOKUP(B29,regiao[[#ALL],[MUNICÍPIO]:[REGIAO_INTEGRACAO]],5,0),"") -> SUDESTE | D29: SINE | E29: {=XLOOKUP(F29&G29,servicos!F:F,servicos!C:C)} -> 5279 | F29: Link de Dados | G29: FIBRA | H29: Ativo | I29: TRUE | J29: 1 | K29: {=XLOOKUP($F29&G29,servicos!$F:$F,servicos!I:I,"Não encontrado",0,1)} -> Mbps | L29: 2022 | N29: =IFS(L29=2021,ROUND(R29,2),L29=2022,ROUND(R29*(1+pconfig!$B$2),2),L29=2023,ROUND(T29*(1+pconfig!$B$3),2),L29=2024,ROUND(U29*(1+pconfig!$B$4),2),L29=2025, ROUND(V29*(1+pconfig!$B$5),2),L29=2026, ROUND(W29*(1+pconfig!$B$6),2),L29="regiaointegracao",Y29*J29) -> 175.8 | O29: =N29*(1+'historico-reajuste'!$C$2)*(1+'historico-reajuste'!$C$3) -> 175.8 | P29: {=XLOOKUP(B29&G29,linkdados!E:E,linkdados!L:L)*J29} -> 29.550604 | Q29: {=XLOOKUP(B29&G29,linkdados!E:E,linkdados!N:N,"")} -> 119.69411 | R29: =IFERROR(__xludf.DUMMYFUNCTION("IF(F29=""Link de Dados"", IFS(J29<=pconfig!$B$12,P29*pconfig!$C$12,J29<=pconfig!$B$13,P29*pconfig!$C$13,J29<=pconfig!$B$14,P29*pconfig!$C$14,J29<=pconfig!$B$15,P29*pconfig!$C$15,J29<=pconfig!$B$16,P29*pconfig!$C$16,J29<=pconfig!$B$17,P29*pconfig!$C$17,J29"&"<=pconfig!$B$18,P29*pconfig!$C$18,J29<=pconfig!$B$19,P29*pconfig!$C$19,J29<=pconfig!$B$20,P29*pconfig!$C$20,J29<=pconfig!$B$21,P29*pconfig!$C$21)+Q29,IF(H29=""Mensal"",FILTER(servicos!O:O,servicos!F:F=F29&G29)*J29,P29))"),149.24471299093656) -> 149.24471 | S29: =IF(F29="Link de Dados",R29,0) -> 149.24471 | T29: =IF(F29="Link de Dados",S29*(1+pconfig!$B$2),S29) -> 175.79535 | U29: =IF(F29="Link de Dados",T29*(1+pconfig!$B$3),T29) -> 187.60879 | V29: =U29*(1+pconfig!$B$4) -> 190.59177 | W29: =V29*(1+pconfig!$B$5) -> 203.05648 | X29: =W29*(1+pconfig!$B$6) -> 209.71673 | Y29: {=XLOOKUP(B29,regiao!A:A,regiao!H:H,0,1)} -> 65.28
A30: =ROW()-ROW(tabelatelecom_3[[#HEADERS],[Item]]) -> 9 | B30: TAILANDIA | C30: =ifna(VLOOKUP(B30,regiao[[#ALL],[MUNICÍPIO]:[REGIAO_INTEGRACAO]],5,0),"") -> NORDESTE | D30: SINE | E30: {=XLOOKUP(F30&G30,servicos!F:F,servicos!C:C)} -> 5262 | F30: Link de Dados | G30: RADIO | H30: Ativo | I30: TRUE | J30: 1 | K30: {=XLOOKUP($F30&G30,servicos!$F:$F,servicos!I:I,"Não encontrado",0,1)} -> Mbps | L30: 2022 | N30: =IFS(L30=2021,ROUND(R30,2),L30=2022,ROUND(R30*(1+pconfig!$B$2),2),L30=2023,ROUND(T30*(1+pconfig!$B$3),2),L30=2024,ROUND(U30*(1+pconfig!$B$4),2),L30=2025, ROUND(V30*(1+pconfig!$B$5),2),L30=2026, ROUND(W30*(1+pconfig!$B$6),2),L30="regiaointegracao",Y30*J30) -> 776.18 | O30: =N30*(1+'historico-reajuste'!$C$2)*(1+'historico-reajuste'!$C$3) -> 776.18 | P30: {=XLOOKUP(B30&G30,linkdados!E:E,linkdados!L:L)*J30} -> 29.550604 | Q30: {=XLOOKUP(B30&G30,linkdados!E:E,linkdados!N:N,"")} -> 629.40584 | R30: =IFERROR(__xludf.DUMMYFUNCTION("IF(F30=""Link de Dados"", IFS(J30<=pconfig!$B$12,P30*pconfig!$C$12,J30<=pconfig!$B$13,P30*pconfig!$C$13,J30<=pconfig!$B$14,P30*pconfig!$C$14,J30<=pconfig!$B$15,P30*pconfig!$C$15,J30<=pconfig!$B$16,P30*pconfig!$C$16,J30<=pconfig!$B$17,P30*pconfig!$C$17,J30"&"<=pconfig!$B$18,P30*pconfig!$C$18,J30<=pconfig!$B$19,P30*pconfig!$C$19,J30<=pconfig!$B$20,P30*pconfig!$C$20,J30<=pconfig!$B$21,P30*pconfig!$C$21)+Q30,IF(H30=""Mensal"",FILTER(servicos!O:O,servicos!F:F=F30&G30)*J30,P30))"),658.9564451158101) -> 658.95645 | S30: =IF(F30="Link de Dados",R30,0) -> 658.95645 | T30: =IF(F30="Link de Dados",S30*(1+pconfig!$B$2),S30) -> 776.1848 | U30: =IF(F30="Link de Dados",T30*(1+pconfig!$B$3),T30) -> 828.34442 | V30: =U30*(1+pconfig!$B$4) -> 841.51509 | W30: =V30*(1+pconfig!$B$5) -> 896.55018 | X30: =W30*(1+pconfig!$B$6) -> 925.95702 | Y30: {=XLOOKUP(B30,regiao!A:A,regiao!H:H,0,1)} -> 87.51
A31: TOTAL MENSAL | N31: =SUMIF(tabelatelecom_3[Incluir],TRUE,tabelatelecom_3[Mensal]) -> 2798.25 | O31: =SUMIF(tabelatelecom_3[Incluir],TRUE,tabelatelecom_3[Total Mensal c/ Reajuste]) -> 2798.25
A32: TOTAL ANUAL | N32: =N31*12 -> 33579 | O32: =O31*12 -> 33579
A35: 5.3 - SERVIÇOS DE INTERNET
A36: Item | B36: Município | C36: Região de Integração | D36: Unidade | E36: Código | F36: Serviço | G36: Tipo | H36: Status | I36: Incluir | J36: Qtd | K36: Grandeza | L36: Unitário | M36: Incluir reajuste | N36: Mensal | O36: Total Mensal c/ Reajuste
A37: =ROW()-ROW(tabelaInternet_4[[#HEADERS],[Item]]) -> 1 | B37: BELEM | C37: =ifna(VLOOKUP(B37,regiao[[#ALL],[MUNICÍPIO]:[REGIAO_INTEGRACAO]],5,0),"") -> METROPOLITANA | D37: SEDE | E37: {=XLOOKUP(F37&G37,servicos!F:F,servicos!C:C)} -> 3174 | F37: Internet | G37: FIBRA | H37: Ativo | I37: TRUE | J37: 300 | K37: {=XLOOKUP($F37&G37,servicos!$F:$F,servicos!I:I,"Não encontrado",0,1)} -> Mbps | L37: Tabela 2026 | M37: FALSE | N37: {=IFS(tabelaInternet_4[Unitário]="Tabela 2026",XLOOKUP(F37&G37,servicos!F:F,servicos!P:P)*tabelaInternet_4[Qtd],tabelaInternet_4[Unitário]="Contrato Cliente",XLOOKUP(F37&G37,servicos!F:F,servicos!N:N)*tabelaInternet_4[Qtd])} -> 6900 | O37: =IF(tabelaInternet_4[Incluir reajuste]=TRUE,tabelaInternet_4[Mensal]*(1+'historico-reajuste'!C3),tabelaInternet_4[Mensal]) -> 6900
A38: TOTAL MENSAL | N38: =SUMIF(tabelaInternet_4[[#DATA],[#TOTALS],[Incluir]],TRUE,tabelaInternet_4[Mensal]) -> 6900 | O38: =SUM(tabelaInternet_4[Total Mensal c/ Reajuste]) -> 6900
A39: TOTAL ANUAL | N39: =N38*12 -> 82800 | O39: =O38*12 -> 82800
A41: SERVIÇOS DE TI
A42: Item | B42: Município | C42: Região | D42: Unidade | E42: Código | F42: Serviço | G42: Grandeza | H42: Status | I42: Incluir | J42: Qtd | K42: Tabela | L42: Unitário | M42: Ocultar | N42: Mensal | O42: Total Mensal c/ Reajuste
A43: =ROW()-ROW(tabelati_3[[#HEADERS],[Item]]) -> 1 | B43: BELEM | C43: =ifna(VLOOKUP(B43,regiao[[#ALL],[MUNICÍPIO]:[REGIAO_INTEGRACAO]],5,0),"") -> METROPOLITANA | D43: Sede | E43: {=XLOOKUP(F43,servicos!D:D,servicos!C:C)} -> 5581 | F43: Business Intelligence Web - B.I. | G43: {=XLOOKUP(F43,servicos!D:D,servicos!I:I)} -> Licença de software | H43: Ativo | I43: TRUE | J43: 1 | K43: Contrato Cliente | L43: {=ifs(K43=2025,XLOOKUP(F43,servicos!D:D,servicos!O:O),K43=2026,XLOOKUP(F43,servicos!D:D,servicos!P:P),K43="Contrato Cliente",XLOOKUP(F43,servicos!D:D,servicos!N:N))} -> 790.9 | N43: =L43*J43 -> 790.9 | O43: =N43*(1+'historico-reajuste'!$C$3) -> 790.9
A44: =ROW()-ROW(tabelati_3[[#HEADERS],[Item]]) -> 2 | B44: BELEM | C44: =ifna(VLOOKUP(B44,regiao[[#ALL],[MUNICÍPIO]:[REGIAO_INTEGRACAO]],5,0),"") -> METROPOLITANA | D44: Sede | E44: {=XLOOKUP(F44,servicos!D:D,servicos!C:C)} -> 3429 | F44: Licença de Uso Sistema Globais (SIMAS/SIAFEM) | G44: {=XLOOKUP(F44,servicos!D:D,servicos!I:I)} -> Licença de software | H44: Ativo | I44: TRUE | J44: 20 | K44: Contrato Cliente | L44: {=ifs(K44=2025,XLOOKUP(F44,servicos!D:D,servicos!O:O),K44=2026,XLOOKUP(F44,servicos!D:D,servicos!P:P),K44="Contrato Cliente",XLOOKUP(F44,servicos!D:D,servicos!N:N))} -> 735.81 | N44: =L44*J44 -> 14716.2 | O44: =N44*(1+'historico-reajuste'!$C$3) -> 14716.2
A45: =ROW()-ROW(tabelati_3[[#HEADERS],[Item]]) -> 3 | B45: BELEM | C45: =ifna(VLOOKUP(B45,regiao[[#ALL],[MUNICÍPIO]:[REGIAO_INTEGRACAO]],5,0),"") -> METROPOLITANA | D45: Sede | E45: {=XLOOKUP(F45,servicos!D:D,servicos!C:C)} -> 3435 | F45: Licença de Uso Sistemas Específicos (ID CIVIL) | G45: {=XLOOKUP(F45,servicos!D:D,servicos!I:I)} -> Licença de software | H45: Ativo | I45: TRUE | J45: 1 | K45: Contrato Cliente | L45: {=ifs(K45=2025,XLOOKUP(F45,servicos!D:D,servicos!O:O),K45=2026,XLOOKUP(F45,servicos!D:D,servicos!P:P),K45="Contrato Cliente",XLOOKUP(F45,servicos!D:D,servicos!N:N))} -> 463.72 | N45: =L45*J45 -> 463.72 | O45: =N45*(1+'historico-reajuste'!$C$3) -> 463.72
A46: =ROW()-ROW(tabelati_3[[#HEADERS],[Item]]) -> 4 | B46: BELEM | C46: =ifna(VLOOKUP(B46,regiao[[#ALL],[MUNICÍPIO]:[REGIAO_INTEGRACAO]],5,0),"") -> METROPOLITANA | D46: Sede | E46: {=XLOOKUP(F46,servicos!D:D,servicos!C:C)} | F46: Licença de uso de sistema (SUAS) | G46: {=XLOOKUP(F46,servicos!D:D,servicos!I:I)} -> Licença de software | H46: Ativo | I46: TRUE | J46: 1 | K46: Contrato Cliente | L46: {=ifs(K46=2025,XLOOKUP(F46,servicos!D:D,servicos!O:O),K46=2026,XLOOKUP(F46,servicos!D:D,servicos!P:P),K46="Contrato Cliente",XLOOKUP(F46,servicos!D:D,servicos!N:N))} -> 2296.58 | N46: =L46*J46 -> 2296.58 | O46: =N46*(1+'historico-reajuste'!$C$3) -> 2296.58
A47: =ROW()-ROW(tabelati_3[[#HEADERS],[Item]]) -> 5 | B47: BELEM | C47: =ifna(VLOOKUP(B47,regiao[[#ALL],[MUNICÍPIO]:[REGIAO_INTEGRACAO]],5,0),"") -> METROPOLITANA | D47: Sede | E47: {=XLOOKUP(F47,servicos!D:D,servicos!C:C)} | F47: Licença de uso de sistema (COBEN) | G47: {=XLOOKUP(F47,servicos!D:D,servicos!I:I)} -> Licença de software | H47: Ativo | I47: TRUE | J47: 1 | K47: Contrato Cliente | L47: {=ifs(K47=2025,XLOOKUP(F47,servicos!D:D,servicos!O:O),K47=2026,XLOOKUP(F47,servicos!D:D,servicos!P:P),K47="Contrato Cliente",XLOOKUP(F47,servicos!D:D,servicos!N:N))} -> 2108.68 | N47: =L47*J47 -> 2108.68 | O47: =N47*(1+'historico-reajuste'!$C$3) -> 2108.68
A48: =ROW()-ROW(tabelati_3[[#HEADERS],[Item]]) -> 6 | B48: BELEM | C48: =ifna(VLOOKUP(B48,regiao[[#ALL],[MUNICÍPIO]:[REGIAO_INTEGRACAO]],5,0),"") -> METROPOLITANA | D48: Sede | E48: {=XLOOKUP(F48,servicos!D:D,servicos!C:C)} -> 5010 | F48: Hospedagem de Website (30Gb) | G48: {=XLOOKUP(F48,servicos!D:D,servicos!I:I)} -> GB | H48: Ativo | I48: TRUE | J48: 1 | K48: Contrato Cliente | L48: {=ifs(K48=2025,XLOOKUP(F48,servicos!D:D,servicos!O:O),K48=2026,XLOOKUP(F48,servicos!D:D,servicos!P:P),K48="Contrato Cliente",XLOOKUP(F48,servicos!D:D,servicos!N:N))} -> 76.13 | N48: =L48*J48 -> 76.13 | O48: =N48*(1+'historico-reajuste'!$C$3) -> 76.13
A49: =ROW()-ROW(tabelati_3[[#HEADERS],[Item]]) -> 7 | B49: BELEM | C49: =ifna(VLOOKUP(B49,regiao[[#ALL],[MUNICÍPIO]:[REGIAO_INTEGRACAO]],5,0),"") -> METROPOLITANA | D49: Sede | E49: {=XLOOKUP(F49,servicos!D:D,servicos!C:C)} -> 3011 | F49: Desenvolvimento de Website/Portal Padrão | G49: {=XLOOKUP(F49,servicos!D:D,servicos!I:I)} -> Hora | H49: Ativo | I49: TRUE | J49: 1 | K49: Contrato Cliente | L49: {=ifs(K49=2025,XLOOKUP(F49,servicos!D:D,servicos!O:O),K49=2026,XLOOKUP(F49,servicos!D:D,servicos!P:P),K49="Contrato Cliente",XLOOKUP(F49,servicos!D:D,servicos!N:N))} -> 521.95 | N49: =L49*J49 -> 521.95 | O49: =N49*(1+'historico-reajuste'!$C$3) -> 521.95
A50: =ROW()-ROW(tabelati_3[[#HEADERS],[Item]]) -> 8 | B50: BELEM | C50: =ifna(VLOOKUP(B50,regiao[[#ALL],[MUNICÍPIO]:[REGIAO_INTEGRACAO]],5,0),"") -> METROPOLITANA | D50: Sede | E50: {=XLOOKUP(F50,servicos!D:D,servicos!C:C)} -> 5530 | F50: Conta de Email (5Gb) 1 Cx | G50: {=XLOOKUP(F50,servicos!D:D,servicos!I:I)} -> GB | H50: Ativo | I50: TRUE | J50: 3 | K50: Contrato Cliente | L50: {=ifs(K50=2025,XLOOKUP(F50,servicos!D:D,servicos!O:O),K50=2026,XLOOKUP(F50,servicos!D:D,servicos!P:P),K50="Contrato Cliente",XLOOKUP(F50,servicos!D:D,servicos!N:N))} -> 8.61 | N50: =L50*J50 -> 25.83 | O50: =N50*(1+'historico-reajuste'!$C$3) -> 25.83
A51: TOTAL MENSAL | N51: =SUM(tabelati_3[[#DATA],[#TOTALS],[Mensal]]) -> 20999.99 | O51: =SUM(tabelati_3[Total Mensal c/ Reajuste]) -> 20999.99
A52: TOTAL ANUAL | N52: =N51*12 -> 251999.88 | O52: =O51*12 -> 251999.88
A54: SERVIÇOS SOB DEMANDA
A55: Item | B55: Município | C55: Região | D55: Unidade | E55: Serviço | F55: Tipo faturamento | G55: Utilização | H55: Status | I55: Incluir | J55: Qtd | K55: Ocultar | L55: unidade-faturamento | M55: Ocultar 2 | N55: Anual
A56: =ROW()-ROW(tabelademanda_4[[#HEADERS],[Item]]) -> 1 | B56: BELEM | C56: =ifna(VLOOKUP(B56,regiao[[#ALL],[MUNICÍPIO]:[REGIAO_INTEGRACAO]],5,0),"") -> METROPOLITANA | D56: Sede | E56: Serviço de TIC | F56: Sob demanda | G56: Novas implantações, Remanejamento | H56: Previsto | I56: FALSE | J56: 1 | L56: US | N56: 0
A57: TOTAL ANUAL | J57: =SUMIF(tabelademanda_4[Incluir],TRUE,tabelademanda_4[Anual]) -> 0
G59: 5.4 - RESUMO
G60: TOTAL (INSTALAÇÃO) | J60: =N18 -> 0
G61: TOTAL ANUAL - LINK DE DADOS | J61: =O32 -> 33579
G62: TOTAL ANUAL - INTERNET | J62: =O39 -> 82800
G63: TOTAL ANUAL - SERVIÇOS DE TI | J63: =O52 -> 251999.88
G64: SOB DEMANDA | J64: =J57 -> 0
G65: TOTAL GLOBAL | J65: =SUM(J60:J64) -> 368378.88
B67: Belém - PA, | E67: =B3 -> 46232 | J67: Validade | N67: 15 dias
B68: Local e Data | J68: Prazo de Execução (dias) | N68: Constante na proposta comercial
B70: Assinatura e Carimbo do funcionário PRODEPA
J71: Condições de Pagamento: | N71: via contrato
B72: Aceite do Cliente
A74: OBSERVAÇÕES
A75: 1 | B75: Valores de implantação compreendem serviço de lançamento de fibra, ativação e configuração de equipamentos e aquisição de ativos de rede (rack, switch gerenciável e DIO)
A76: 2 | B76: Os valores mensais de link de dados estão conforme tabela vigente e deverão ser incluídos no contrato do cliente através de termo aditivo.
A77: 3 | B77: Em caso de anuência com este orçameno pelo gestor do órgão, serão originadas as Propostas Técnica e Comercial, que serão parte integrante e indivisível do contrato.
A78: ELABORADO POR JULIANA LOBO

Sheet servicos
A1: Área | B1: Subárea | C1: Codigo | D1: Descrição | E1: Tipo | F1: Coluna 2 | G1: Lim inferior | H1: Lim Superior | I1: Grandeza | J1: Preço Pacote | K1: Tipo de faturamento | L1: Pagamento anual 2025 | M1: Pagamento anual 2026 | N1: Unitário Contrato Cliente | O1: Mensal 2025 | P1: Mensal 2026
A2: 1 - Comunicação de Dados | B2: TELECOM | C2: 5300 | D2: Implantação de infraestrutura de | E2: FIBRA | F2: =D2&E2 -> Implantação de infraestrutura deFIBRA | I2: Configuração, Cabeamento, Equipamento | K2: Pagamento único anual | L2: sob consulta | M2: =(if(L2="sob consulta","sob consulta", ROUND(L2*(1+pconfig!$B$6),2))) -> sob consulta | O2: 0 | P2: =(if(O2="sob consulta","sob consulta", ROUND(O2*(1+pconfig!$B$6),2))) -> 0
A3: 1 - Comunicação de Dados | B3: TELECOM | C3: 5291 | D3: Implantação de infraestrutura de | E3: RADIO | F3: =D3&E3 -> Implantação de infraestrutura deRADIO | I3: Configuração, Equipamento, Cabeamento | K3: Pagamento único anual | L3: sob consulta | M3: =(if(L3="sob consulta","sob consulta", ROUND(L3*(1+pconfig!$B$6),2))) -> sob consulta | O3: 0 | P3: =(if(O3="sob consulta","sob consulta", ROUND(O3*(1+pconfig!$B$6),2))) -> 0
A4: 1 - Comunicação de Dados | B4: TELECOM | C4: 5279 | D4: Link de Dados | E4: FIBRA | F4: =D4&E4 -> Link de DadosFIBRA | I4: Mbps | J4: sob consulta | K4: Mensal | L4: sob consulta | M4: =(if(L4="sob consulta","sob consulta", ROUND(L4*(1+pconfig!$B$6),2))) -> sob consulta | O4: 0 | P4: =(if(O4="sob consulta","sob consulta", ROUND(O4*(1+pconfig!$B$6),2))) -> 0
A5: 1 - Comunicação de Dados | B5: TELECOM | C5: 5262 | D5: Link de Dados | E5: RADIO | F5: =D5&E5 -> Link de DadosRADIO | I5: Mbps | J5: sob consulta | K5: Mensal | L5: sob consulta | M5: =(if(L5="sob consulta","sob consulta", ROUND(L5*(1+pconfig!$B$6),2))) -> sob consulta | O5: 0 | P5: =(if(O5="sob consulta","sob consulta", ROUND(O5*(1+pconfig!$B$6),2))) -> 0
A6: 1 - Comunicação de Dados | B6: Internet | C6: 3174 | D6: Internet | E6: FIBRA | F6: =D6&E6 -> InternetFIBRA | I6: Mbps | K6: Mensal | M6: =(if(L6="sob consulta","sob consulta", ROUND(L6*(1+pconfig!$B$6),2))) -> 0 | N6: 65.97 | O6: 23 | P6: 23
A7: 1 - Comunicação de Dados | B7: Internet | C7: 3174 | D7: Internet | E7: RADIO | F7: =D7&E7 -> InternetRADIO | I7: Mbps | K7: Mensal | M7: =(if(L7="sob consulta","sob consulta", ROUND(L7*(1+pconfig!$B$6),2))) -> 0 | N7: 65.97 | O7: 23 | P7: 23
A8: 2 - Data Center | B8: Hospedagem | D8: REGISTRO DE DOMÍNIO | F8: =D8&E8 -> REGISTRO DE DOMÍNIO | I8: Configuração | K8: Pagamento único anual | L8: 66.09 | M8: =(if(L8="sob consulta","sob consulta", ROUND(L8*(1+pconfig!$B$6),2))) -> 68.26 | O8: 0 | P8: =(if(O8="sob consulta","sob consulta", ROUND(O8*(1+pconfig!$B$6),2))) -> 0
A9: 2 - Data Center | B9: Hospedagem | D9: Locação de Espaço em Disco | F9: =D9&E9 -> Locação de Espaço em Disco | I9: GB | K9: Mensal | M9: =(if(L9="sob consulta","sob consulta", ROUND(L9*(1+pconfig!$B$6),2))) -> 0 | O9: 1.03 | P9: =(if(O9="sob consulta","sob consulta", ROUND(O9*(1+pconfig!$B$6),2))) -> 1.06
A10: 2 - Data Center | B10: Hospedagem | D10: Hospedagem de Servidor (colocation) - 1U | E10: 1U | F10: =D10&E10 -> Hospedagem de Servidor (colocation) - 1U1U | I10: U | K10: Mensal | M10: =(if(L10="sob consulta","sob consulta", ROUND(L10*(1+pconfig!$B$6),2))) -> 0 | O10: 712.35 | P10: =(if(O10="sob consulta","sob consulta", ROUND(O10*(1+pconfig!$B$6),2))) -> 735.72
A11: 2 - Data Center | B11: Hospedagem | D11: Hospedagem de Rack de Servidores - 22 U | E11: 22 U | F11: =D11&E11 -> Hospedagem de Rack de Servidores - 22 U22 U | I11: U | K11: Mensal | M11: =(if(L11="sob consulta","sob consulta", ROUND(L11*(1+pconfig!$B$6),2))) -> 0 | O11: 11371.59 | P11: =ROUND(O11*(1+pconfig!$B$6),2) -> 11744.58
A12: 2 - Data Center | B12: Hospedagem | D12: Hospedagem de Rack de Servidores (compartilhado) - 44U | E12: 44 U | F12: =D12&E12 -> Hospedagem de Rack de Servidores (compartilhado) - 44U44 U | I12: U | K12: Mensal | M12: =(if(L12="sob consulta","sob consulta", ROUND(L12*(1+pconfig!$B$6),2))) -> 0 | O12: 22743.2 | P12: =ROUND(O12*(1+pconfig!$B$6),2) -> 23489.18
A13: 2 - Data Center | B13: Hospedagem | D13: Hosped. de Rack de Servidores (exclusivo) - 44 U | E13: 44 U | F13: =D13&E13 -> Hosped. de Rack de Servidores (exclusivo) - 44 U44 U | I13: U | K13: Mensal | M13: =(if(L13="sob consulta","sob consulta", ROUND(L13*(1+pconfig!$B$6),2))) -> 0 | O13: 29566.16 | P13: =ROUND(O13*(1+pconfig!$B$6),2) -> 30535.93
A14: 2 - Data Center | B14: Hospedagem | D14: Hospedagem de Servidor Storage (colocation) | F14: =D14&E14 -> Hospedagem de Servidor Storage (colocation) | I14: Máquina | J14: sob consulta | K14: Mensal | L14: sob consulta | M14: =(if(L14="sob consulta","sob consulta", ROUND(L14*(1+pconfig!$B$6),2))) -> sob consulta | O14: 0 | P14: =ROUND(O14*(1+pconfig!$B$6),2) -> 0
A15: 3 - Data Center | B15: Hospedagem | D15: Hospedagem de Servidor Virtualizado | F15: =D15&E15 -> Hospedagem de Servidor Virtualizado | I15: Máquina | J15: sob consulta | K15: Mensal | L15: sob consulta | M15: =(if(L15="sob consulta","sob consulta", ROUND(L15*(1+pconfig!$B$6),2))) -> sob consulta | O15: 0 | P15: =ROUND(O15*(1+pconfig!$B$6),2) -> 0
A16: 4 - Data Center | B16: Hospedagem | C16: 5003 | D16: Hospedagem de Website (5Gb) | E16: =IFERROR(__xludf.DUMMYFUNCTION("CONCATENATE(REGEXEXTRACT(D16,""[\d]+""),""GB"")"),"5GB") -> 5GB | F16: =D16&E16 -> Hospedagem de Website (5Gb)5GB | G16: 1 | H16: 5 | I16: GB | K16: Mensal | M16: =(if(L16="sob consulta","sob consulta", ROUND(L16*(1+pconfig!$B$6),2))) -> 0 | O16: 33.73 | P16: =ROUND(O16*(1+pconfig!$B$6),2) -> 34.84
A17: 2 - Data Center | B17: Hospedagem | D17: Hospedagem de Website (10Gb) | E17: =IFERROR(__xludf.DUMMYFUNCTION("CONCATENATE(REGEXEXTRACT(D17,""[\d]+""),""GB"")"),"10GB") -> 10GB | F17: =D17&E17 -> Hospedagem de Website (10Gb)10GB | G17: 1 | H17: 10 | I17: GB | K17: Mensal | M17: =(if(L17="sob consulta","sob consulta", ROUND(L17*(1+pconfig!$B$6),2))) -> 0 | O17: 62.37 | P17: =ROUND(O17*(1+pconfig!$B$6),2) -> 64.42
A18: 2 - Data Center | B18: Hospedagem | C18: 5010 | D18: Hospedagem de Website (30Gb) | E18: =IFERROR(__xludf.DUMMYFUNCTION("CONCATENATE(REGEXEXTRACT(D18,""[\d]+""),""GB"")"),"30GB") -> 30GB | F18: =D18&E18 -> Hospedagem de Website (30Gb)30GB | G18: 1 | H18: 30 | I18: GB | K18: Mensal | M18: =(if(L18="sob consulta","sob consulta", ROUND(L18*(1+pconfig!$B$6),2))) -> 0 | N18: 76.13 | O18: 82.9 | P18: =ROUND(O18*(1+pconfig!$B$6),2) -> 85.62
A19: 2 - Data Center | B19: Hospedagem | D19: Hospedagem de Website (50Gb) | E19: =IFERROR(__xludf.DUMMYFUNCTION("CONCATENATE(REGEXEXTRACT(D19,""[\d]+""),""GB"")"),"50GB") -> 50GB | F19: =D19&E19 -> Hospedagem de Website (50Gb)50GB | G19: 1 | H19: 50 | I19: GB | K19: Mensal | M19: =(if(L19="sob consulta","sob consulta", ROUND(L19*(1+pconfig!$B$6),2))) -> 0 | O19: 103.46 | P19: =ROUND(O19*(1+pconfig!$B$6),2) -> 106.85
A20: 2 - Data Center | B20: Hospedagem | C20: 5026 | D20: Hospedagem de Website (100Gb) | E20: =IFERROR(__xludf.DUMMYFUNCTION("CONCATENATE(REGEXEXTRACT(D20,""[\d]+""),""GB"")"),"100GB") -> 100GB | F20: =D20&E20 -> Hospedagem de Website (100Gb)100GB | G20: 1 | H20: 100 | I20: GB | K20: Mensal | M20: =(if(L20="sob consulta","sob consulta", ROUND(L20*(1+pconfig!$B$6),2))) -> 0 | O20: 154.8 | P20: =ROUND(O20*(1+pconfig!$B$6),2) -> 159.88
A21: 2 - Data Center | B21: Hospedagem | C21: 5530 | D21: Conta de Email (1Gb) 1 Cx | E21: =IFERROR(__xludf.DUMMYFUNCTION("CONCATENATE(REGEXEXTRACT(D21,""[\d]+""),""GB"")"),"1GB") -> 1GB | F21: =D21&E21 -> Conta de Email (1Gb) 1 Cx1GB | G21: 1 | H21: 1 | I21: GB | J21: 6.24 | K21: Mensal | M21: =(if(L21="sob consulta","sob consulta", ROUND(L21*(1+pconfig!$B$6),2))) -> 0 | O21: =J21/H21 -> 6.24 | P21: =ROUND(O21*(1+pconfig!$B$6),2) -> 6.44
A22: 2 - Data Center | B22: Hospedagem | C22: 5530 | D22: Conta de Email (1Gb) 25 Cx | E22: =IFERROR(__xludf.DUMMYFUNCTION("CONCATENATE(REGEXEXTRACT(D22,""[\d]+""),""GB"")"),"1GB") -> 1GB | F22: =D22&E22 -> Conta de Email (1Gb) 25 Cx1GB | G22: 1 | H22: 25 | I22: GB | J22: 149.76 | K22: Mensal | M22: =(if(L22="sob consulta","sob consulta", ROUND(L22*(1+pconfig!$B$6),2))) -> 0 | O22: =J22/H22 -> 5.9904 | P22: =ROUND(O22*(1+pconfig!$B$6),2) -> 6.19
A23: 2 - Data Center | B23: Hospedagem | C23: 5530 | D23: Conta de Email (1Gb) 50 Cx | E23: =IFERROR(__xludf.DUMMYFUNCTION("CONCATENATE(REGEXEXTRACT(D23,""[\d]+""),""GB"")"),"1GB") -> 1GB | F23: =D23&E23 -> Conta de Email (1Gb) 50 Cx1GB | G23: 1 | H23: 50 | I23: GB | J23: 293.28 | K23: Mensal | M23: =(if(L23="sob consulta","sob consulta", ROUND(L23*(1+pconfig!$B$6),2))) -> 0 | O23: =J23/H23 -> 5.8656 | P23: =ROUND(O23*(1+pconfig!$B$6),2) -> 6.06
A24: 2 - Data Center | B24: Hospedagem | C24: 5530 | D24: Conta de Email (1Gb) 100 Cx | E24: =IFERROR(__xludf.DUMMYFUNCTION("CONCATENATE(REGEXEXTRACT(D24,""[\d]+""),""GB"")"),"1GB") -> 1GB | F24: =D24&E24 -> Conta de Email (1Gb) 100 Cx1GB | G24: 1 | H24: 100 | I24: GB | J24: 574.08 | K24: Mensal | M24: =(if(L24="sob consulta","sob consulta", ROUND(L24*(1+pconfig!$B$6),2))) -> 0 | O24: =J24/H24 -> 5.7408 | P24: =ROUND(O24*(1+pconfig!$B$6),2) -> 5.93
A25: 2 - Data Center | B25: Hospedagem | C25: 5530 | D25: Conta de Email (1Gb) 500 Cx NOVO | E25: =IFERROR(__xludf.DUMMYFUNCTION("CONCATENATE(REGEXEXTRACT(D25,""[\d]+""),""GB"")"),"1GB") -> 1GB | F25: =D25&E25 -> Conta de Email (1Gb) 500 Cx NOVO1GB | G25: 1 | H25: 500 | I25: GB | J25: 2842.06 | K25: Mensal | M25: =(if(L25="sob consulta","sob consulta", ROUND(L25*(1+pconfig!$B$6),2))) -> 0 | O25: =J25/H25 -> 5.68412 | P25: =ROUND(O25*(1+pconfig!$B$6),2) -> 5.87
A26: 2 - Data Center | B26: Hospedagem | C26: 5530 | D26: Conta de Email (1Gb) 1000 Cx NOVO | E26: =IFERROR(__xludf.DUMMYFUNCTION("CONCATENATE(REGEXEXTRACT(D26,""[\d]+""),""GB"")"),"1GB") -> 1GB | F26: =D26&E26 -> Conta de Email (1Gb) 1000 Cx NOVO1GB | G26: 1 | H26: 1000 | I26: GB | J26: 5615.92 | K26: Mensal | M26: =(if(L26="sob consulta","sob consulta", ROUND(L26*(1+pconfig!$B$6),2))) -> 0 | O26: =J26/H26 -> 5.61592 | P26: =ROUND(O26*(1+pconfig!$B$6),2) -> 5.8
A27: 2 - Data Center | B27: Hospedagem | C27: 5530 | D27: Conta de Email (2Gb) 1 Cx | E27: =IFERROR(__xludf.DUMMYFUNCTION("CONCATENATE(REGEXEXTRACT(D27,""[\d]+""),""GB"")"),"2GB") -> 2GB | F27: =D27&E27 -> Conta de Email (2Gb) 1 Cx2GB | G27: 1 | H27: 1 | I27: GB | J27: 7.18 | K27: Mensal | M27: =(if(L27="sob consulta","sob consulta", ROUND(L27*(1+pconfig!$B$6),2))) -> 0 | O27: =J27/H27 -> 7.18 | P27: =ROUND(O27*(1+pconfig!$B$6),2) -> 7.42
A28: 2 - Data Center | B28: Hospedagem | C28: 5530 | D28: Conta de Email (2Gb) 25 Cx | E28: =IFERROR(__xludf.DUMMYFUNCTION("CONCATENATE(REGEXEXTRACT(D28,""[\d]+""),""GB"")"),"2GB") -> 2GB | F28: =D28&E28 -> Conta de Email (2Gb) 25 Cx2GB | G28: 1 | H28: 25 | I28: GB | J28: 172.26 | K28: Mensal | M28: =(if(L28="sob consulta","sob consulta", ROUND(L28*(1+pconfig!$B$6),2))) -> 0 | O28: =J28/H28 -> 6.8904 | P28: =ROUND(O28*(1+pconfig!$B$6),2) -> 7.12
A29: 2 - Data Center | B29: Hospedagem | C29: 5530 | D29: Conta de Email (2Gb) 50 Cx | E29: =IFERROR(__xludf.DUMMYFUNCTION("CONCATENATE(REGEXEXTRACT(D29,""[\d]+""),""GB"")"),"2GB") -> 2GB | F29: =D29&E29 -> Conta de Email (2Gb) 50 Cx2GB | G29: 1 | H29: 50 | I29: GB | J29: 337.34 | K29: Mensal | M29: =(if(L29="sob consulta","sob consulta", ROUND(L29*(1+pconfig!$B$6),2))) -> 0 | O29: =J29/H29 -> 6.7468 | P29: =ROUND(O29*(1+pconfig!$B$6),2) -> 6.97
A30: 2 - Data Center | B30: Hospedagem | C30: 5530 | D30: Conta de Email (2Gb) 100 Cx | E30: =IFERROR(__xludf.DUMMYFUNCTION("CONCATENATE(REGEXEXTRACT(D30,""[\d]+""),""GB"")"),"2GB") -> 2GB | F30: =D30&E30 -> Conta de Email (2Gb) 100 Cx2GB | G30: 1 | H30: 100 | I30: GB | J30: 660.32 | K30: Mensal | M30: =(if(L30="sob consulta","sob consulta", ROUND(L30*(1+pconfig!$B$6),2))) -> 0 | O30: =J30/H30 -> 6.6032 | P30: =ROUND(O30*(1+pconfig!$B$6),2) -> 6.82
A31: 2 - Data Center | B31: Hospedagem | C31: 5530 | D31: Conta de Email (2Gb) 500 Cx NOVO | E31: =IFERROR(__xludf.DUMMYFUNCTION("CONCATENATE(REGEXEXTRACT(D31,""[\d]+""),""GB"")"),"2GB") -> 2GB | F31: =D31&E31 -> Conta de Email (2Gb) 500 Cx NOVO2GB | G31: 1 | H31: 500 | I31: GB | J31: 3006.9 | K31: Mensal | M31: =(if(L31="sob consulta","sob consulta", ROUND(L31*(1+pconfig!$B$6),2))) -> 0 | O31: =J31/H31 -> 6.0138 | P31: =ROUND(O31*(1+pconfig!$B$6),2) -> 6.21
A32: 2 - Data Center | B32: Hospedagem | C32: 5530 | D32: Conta de Email (2Gb) 1000 Cx NOVO | E32: =IFERROR(__xludf.DUMMYFUNCTION("CONCATENATE(REGEXEXTRACT(D32,""[\d]+""),""GB"")"),"2GB") -> 2GB | F32: =D32&E32 -> Conta de Email (2Gb) 1000 Cx NOVO2GB | G32: 1 | H32: 1000 | I32: GB | J32: 5888.76 | K32: Mensal | M32: =(if(L32="sob consulta","sob consulta", ROUND(L32*(1+pconfig!$B$6),2))) -> 0 | O32: =J32/H32 -> 5.88876 | P32: =ROUND(O32*(1+pconfig!$B$6),2) -> 6.08
A33: 2 - Data Center | B33: Hospedagem | C33: 5530 | D33: Conta de Email (5Gb) 1 Cx | E33: =IFERROR(__xludf.DUMMYFUNCTION("CONCATENATE(REGEXEXTRACT(D33,""[\d]+""),""GB"")"),"5GB") -> 5GB | F33: =D33&E33 -> Conta de Email (5Gb) 1 Cx5GB | G33: 1 | H33: 1 | I33: GB | J33: 8.61 | K33: Mensal | M33: =(if(L33="sob consulta","sob consulta", ROUND(L33*(1+pconfig!$B$6),2))) -> 0 | N33: 8.61 | O33: =J33/H33 -> 8.61 | P33: =ROUND(O33*(1+pconfig!$B$6),2) -> 8.89
A34: 2 - Data Center | B34: Hospedagem | C34: 5530 | D34: Conta de Email (5Gb) 25 Cx | E34: =IFERROR(__xludf.DUMMYFUNCTION("CONCATENATE(REGEXEXTRACT(D34,""[\d]+""),""GB"")"),"5GB") -> 5GB | F34: =D34&E34 -> Conta de Email (5Gb) 25 Cx5GB | G34: 1 | H34: 25 | I34: GB | J34: 206.64 | K34: Mensal | M34: =(if(L34="sob consulta","sob consulta", ROUND(L34*(1+pconfig!$B$6),2))) -> 0 | O34: =J34/H34 -> 8.2656 | P34: =ROUND(O34*(1+pconfig!$B$6),2) -> 8.54
A35: 2 - Data Center | B35: Hospedagem | C35: 5530 | D35: Conta de Email (5Gb) 50 Cx | E35: =IFERROR(__xludf.DUMMYFUNCTION("CONCATENATE(REGEXEXTRACT(D35,""[\d]+""),""GB"")"),"5GB") -> 5GB | F35: =D35&E35 -> Conta de Email (5Gb) 50 Cx5GB | G35: 1 | H35: 50 | I35: GB | J35: 404.68 | K35: Mensal | M35: =(if(L35="sob consulta","sob consulta", ROUND(L35*(1+pconfig!$B$6),2))) -> 0 | O35: =J35/H35 -> 8.0936 | P35: =ROUND(O35*(1+pconfig!$B$6),2) -> 8.36
A36: 2 - Data Center | B36: Hospedagem | C36: 5530 | D36: Conta de Email (5Gb) 100 Cx | E36: =IFERROR(__xludf.DUMMYFUNCTION("CONCATENATE(REGEXEXTRACT(D36,""[\d]+""),""GB"")"),"5GB") -> 5GB | F36: =D36&E36 -> Conta de Email (5Gb) 100 Cx5GB | G36: 1 | H36: 100 | I36: GB | J36: 792.14 | K36: Mensal | M36: =(if(L36="sob consulta","sob consulta", ROUND(L36*(1+pconfig!$B$6),2))) -> 0 | O36: =J36/H36 -> 7.9214 | P36: =ROUND(O36*(1+pconfig!$B$6),2) -> 8.18
A37: 2 - Data Center | B37: Hospedagem | C37: 5530 | D37: Conta de Email (5Gb) 500 Cx NOVO | E37: =IFERROR(__xludf.DUMMYFUNCTION("CONCATENATE(REGEXEXTRACT(D37,""[\d]+""),""GB"")"),"5GB") -> 5GB | F37: =D37&E37 -> Conta de Email (5Gb) 500 Cx NOVO5GB | G37: 1 | H37: 500 | I37: GB | J37: 3387.74 | K37: Mensal | M37: =(if(L37="sob consulta","sob consulta", ROUND(L37*(1+pconfig!$B$6),2))) -> 0 | O37: =J37/H37 -> 6.77548 | P37: =ROUND(O37*(1+pconfig!$B$6),2) -> 7
A38: 2 - Data Center | B38: Hospedagem | C38: 5530 | D38: Conta de Email (5Gb) 1000 Cx NOVO | E38: =IFERROR(__xludf.DUMMYFUNCTION("CONCATENATE(REGEXEXTRACT(D38,""[\d]+""),""GB"")"),"5GB") -> 5GB | F38: =D38&E38 -> Conta de Email (5Gb) 1000 Cx NOVO5GB | G38: 1 | H38: 1000 | I38: GB | J38: 6502.64 | K38: Mensal | M38: =(if(L38="sob consulta","sob consulta", ROUND(L38*(1+pconfig!$B$6),2))) -> 0 | O38: =J38/H38 -> 6.50264 | P38: =ROUND(O38*(1+pconfig!$B$6),2) -> 6.72
A39: 2 - Data Center | B39: Hospedagem | C39: 5530 | D39: Conta de Email (10Gb) 1 Cx | E39: =IFERROR(__xludf.DUMMYFUNCTION("CONCATENATE(REGEXEXTRACT(D39,""[\d]+""),""GB"")"),"10GB") -> 10GB | F39: =D39&E39 -> Conta de Email (10Gb) 1 Cx10GB | G39: 1 | H39: 1 | I39: GB | J39: 11.19 | K39: Mensal | M39: =(if(L39="sob consulta","sob consulta", ROUND(L39*(1+pconfig!$B$6),2))) -> 0 | O39: =J39/H39 -> 11.19 | P39: =ROUND(O39*(1+pconfig!$B$6),2) -> 11.56
A40: 2 - Data Center | B40: Hospedagem | C40: 5530 | D40: Conta de Email (10Gb) 25 Cx | E40: =IFERROR(__xludf.DUMMYFUNCTION("CONCATENATE(REGEXEXTRACT(D40,""[\d]+""),""GB"")"),"10GB") -> 10GB | F40: =D40&E40 -> Conta de Email (10Gb) 25 Cx10GB | G40: 1 | H40: 25 | I40: GB | J40: 268.67 | K40: Mensal | M40: =(if(L40="sob consulta","sob consulta", ROUND(L40*(1+pconfig!$B$6),2))) -> 0 | O40: =J40/H40 -> 10.7468 | P40: =ROUND(O40*(1+pconfig!$B$6),2) -> 11.1
A41: 2 - Data Center | B41: Hospedagem | C41: 5530 | D41: Conta de Email (10Gb) 50 Cx | E41: =IFERROR(__xludf.DUMMYFUNCTION("CONCATENATE(REGEXEXTRACT(D41,""[\d]+""),""GB"")"),"10GB") -> 10GB | F41: =D41&E41 -> Conta de Email (10Gb) 50 Cx10GB | G41: 1 | H41: 50 | I41: GB | J41: 526.15 | K41: Mensal | M41: =(if(L41="sob consulta","sob consulta", ROUND(L41*(1+pconfig!$B$6),2))) -> 0 | O41: =J41/H41 -> 10.523 | P41: =ROUND(O41*(1+pconfig!$B$6),2) -> 10.87
A42: 2 - Data Center | B42: Hospedagem | C42: 5530 | D42: Conta de Email (10Gb) 100 Cx | E42: =IFERROR(__xludf.DUMMYFUNCTION("CONCATENATE(REGEXEXTRACT(D42,""[\d]+""),""GB"")"),"10GB") -> 10GB | F42: =D42&E42 -> Conta de Email (10Gb) 100 Cx10GB | G42: 1 | H42: 100 | I42: GB | J42: 1029.9 | K42: Mensal | M42: =(if(L42="sob consulta","sob consulta", ROUND(L42*(1+pconfig!$B$6),2))) -> 0 | O42: =J42/H42 -> 10.299 | P42: =ROUND(O42*(1+pconfig!$B$6),2) -> 10.64
A43: 2 - Data Center | B43: Hospedagem | C43: 5530 | D43: Conta de Email (10Gb) 500 Cx NOVO | E43: =IFERROR(__xludf.DUMMYFUNCTION("CONCATENATE(REGEXEXTRACT(D43,""[\d]+""),""GB"")"),"10GB") -> 10GB | F43: =D43&E43 -> Conta de Email (10Gb) 500 Cx NOVO10GB | G43: 1 | H43: 500 | I43: GB | J43: 5087.29 | K43: Mensal | M43: =(if(L43="sob consulta","sob consulta", ROUND(L43*(1+pconfig!$B$6),2))) -> 0 | O43: =J43/H43 -> 10.17458 | P43: =ROUND(O43*(1+pconfig!$B$6),2) -> 10.51
A44: 2 - Data Center | B44: Hospedagem | C44: 5530 | D44: Conta de Email (10Gb) 1000 Cx NOVO | E44: =IFERROR(__xludf.DUMMYFUNCTION("CONCATENATE(REGEXEXTRACT(D44,""[\d]+""),""GB"")"),"10GB") -> 10GB | F44: =D44&E44 -> Conta de Email (10Gb) 1000 Cx NOVO10GB | G44: 1 | H44: 1000 | I44: GB | J44: 10072.27 | K44: Mensal | M44: =(if(L44="sob consulta","sob consulta", ROUND(L44*(1+pconfig!$B$6),2))) -> 0 | O44: =J44/H44 -> 10.07227 | P44: =ROUND(O44*(1+pconfig!$B$6),2) -> 10.4
A45: 2 - Data Center | B45: Hospedagem | C45: 5530 | D45: Conta de Email (15Gb) 1 Cx NOVO | E45: =IFERROR(__xludf.DUMMYFUNCTION("CONCATENATE(REGEXEXTRACT(D45,""[\d]+""),""GB"")"),"15GB") -> 15GB | F45: =D45&E45 -> Conta de Email (15Gb) 1 Cx NOVO15GB | G45: 1 | H45: 1 | I45: GB | J45: 14.54 | K45: Mensal | M45: =(if(L45="sob consulta","sob consulta", ROUND(L45*(1+pconfig!$B$6),2))) -> 0 | O45: =J45/H45 -> 14.54 | P45: =ROUND(O45*(1+pconfig!$B$6),2) -> 15.02
A46: 2 - Data Center | B46: Hospedagem | C46: 5530 | D46: Conta de Email (15Gb) 25 Cx NOVO | E46: =IFERROR(__xludf.DUMMYFUNCTION("CONCATENATE(REGEXEXTRACT(D46,""[\d]+""),""GB"")"),"15GB") -> 15GB | F46: =D46&E46 -> Conta de Email (15Gb) 25 Cx NOVO15GB | G46: 1 | H46: 25 | I46: GB | J46: 349.01 | K46: Mensal | M46: =(if(L46="sob consulta","sob consulta", ROUND(L46*(1+pconfig!$B$6),2))) -> 0 | O46: =J46/H46 -> 13.9604 | P46: =ROUND(O46*(1+pconfig!$B$6),2) -> 14.42
A47: 2 - Data Center | B47: Hospedagem | C47: 5530 | D47: Conta de Email (15Gb) 50 Cx NOVO | E47: =IFERROR(__xludf.DUMMYFUNCTION("CONCATENATE(REGEXEXTRACT(D47,""[\d]+""),""GB"")"),"15GB") -> 15GB | F47: =D47&E47 -> Conta de Email (15Gb) 50 Cx NOVO15GB | G47: 1 | H47: 50 | I47: GB | J47: 683.23 | K47: Mensal | M47: =(if(L47="sob consulta","sob consulta", ROUND(L47*(1+pconfig!$B$6),2))) -> 0 | O47: =J47/H47 -> 13.6646 | P47: =ROUND(O47*(1+pconfig!$B$6),2) -> 14.11
A48: 2 - Data Center | B48: Hospedagem | C48: 5530 | D48: Conta de Email (15Gb) 100 Cx NOVO | E48: =IFERROR(__xludf.DUMMYFUNCTION("CONCATENATE(REGEXEXTRACT(D48,""[\d]+""),""GB"")"),"15GB") -> 15GB | F48: =D48&E48 -> Conta de Email (15Gb) 100 Cx NOVO15GB | G48: 1 | H48: 100 | I48: GB | J48: 1338.04 | K48: Mensal | M48: =(if(L48="sob consulta","sob consulta", ROUND(L48*(1+pconfig!$B$6),2))) -> 0 | O48: =J48/H48 -> 13.3804 | P48: =ROUND(O48*(1+pconfig!$B$6),2) -> 13.82
A49: 2 - Data Center | B49: Hospedagem | C49: 5530 | D49: Conta de Email (15Gb) 500 Cx NOVO | E49: =IFERROR(__xludf.DUMMYFUNCTION("CONCATENATE(REGEXEXTRACT(D49,""[\d]+""),""GB"")"),"15GB") -> 15GB | F49: =D49&E49 -> Conta de Email (15Gb) 500 Cx NOVO15GB | G49: 1 | H49: 500 | I49: GB | J49: 6616.32 | K49: Mensal | M49: =(if(L49="sob consulta","sob consulta", ROUND(L49*(1+pconfig!$B$6),2))) -> 0 | O49: =J49/H49 -> 13.23264 | P49: =ROUND(O49*(1+pconfig!$B$6),2) -> 13.67
A50: 2 - Data Center | B50: Hospedagem | C50: 5530 | D50: Conta de Email (15Gb) 1000 Cx NOVO | E50: =IFERROR(__xludf.DUMMYFUNCTION("CONCATENATE(REGEXEXTRACT(D50,""[\d]+""),""GB"")"),"15GB") -> 15GB | F50: =D50&E50 -> Conta de Email (15Gb) 1000 Cx NOVO15GB | G50: 1 | H50: 1000 | I50: GB | J50: 13084.86 | K50: Mensal | M50: =(if(L50="sob consulta","sob consulta", ROUND(L50*(1+pconfig!$B$6),2))) -> 0 | O50: =J50/H50 -> 13.08486 | P50: =ROUND(O50*(1+pconfig!$B$6),2) -> 13.51
A51: 2 - Data Center | B51: Hospedagem | C51: 5530 | D51: Conta de Email (20Gb) 1 Cx NOVO | E51: =IFERROR(__xludf.DUMMYFUNCTION("CONCATENATE(REGEXEXTRACT(D51,""[\d]+""),""GB"")"),"20GB") -> 20GB | F51: =D51&E51 -> Conta de Email (20Gb) 1 Cx NOVO20GB | G51: 1 | H51: 1 | I51: GB | J51: 18.91 | K51: Mensal | M51: =(if(L51="sob consulta","sob consulta", ROUND(L51*(1+pconfig!$B$6),2))) -> 0 | O51: =J51/H51 -> 18.91 | P51: =ROUND(O51*(1+pconfig!$B$6),2) -> 19.53
A52: 2 - Data Center | B52: Hospedagem | C52: 5530 | D52: Conta de Email (20Gb) 25 Cx NOVO | E52: =IFERROR(__xludf.DUMMYFUNCTION("CONCATENATE(REGEXEXTRACT(D52,""[\d]+""),""GB"")"),"20GB") -> 20GB | F52: =D52&E52 -> Conta de Email (20Gb) 25 Cx NOVO20GB | G52: 1 | H52: 25 | I52: GB | J52: 453.59 | K52: Mensal | M52: =(if(L52="sob consulta","sob consulta", ROUND(L52*(1+pconfig!$B$6),2))) -> 0 | O52: =J52/H52 -> 18.1436 | P52: =ROUND(O52*(1+pconfig!$B$6),2) -> 18.74
A53: 2 - Data Center | B53: Hospedagem | C53: 5530 | D53: Conta de Email (20Gb) 50 Cx NOVO | E53: =IFERROR(__xludf.DUMMYFUNCTION("CONCATENATE(REGEXEXTRACT(D53,""[\d]+""),""GB"")"),"20GB") -> 20GB | F53: =D53&E53 -> Conta de Email (20Gb) 50 Cx NOVO20GB | G53: 1 | H53: 50 | I53: GB | J53: 887.86 | K53: Mensal | M53: =(if(L53="sob consulta","sob consulta", ROUND(L53*(1+pconfig!$B$6),2))) -> 0 | O53: =J53/H53 -> 17.7572 | P53: =ROUND(O53*(1+pconfig!$B$6),2) -> 18.34
A54: 2 - Data Center | B54: Hospedagem | C54: 5530 | D54: Conta de Email (20Gb) 100 Cx NOVO | E54: =IFERROR(__xludf.DUMMYFUNCTION("CONCATENATE(REGEXEXTRACT(D54,""[\d]+""),""GB"")"),"20GB") -> 20GB | F54: =D54&E54 -> Conta de Email (20Gb) 100 Cx NOVO20GB | G54: 1 | H54: 100 | I54: GB | J54: 1738.21 | K54: Mensal | M54: =(if(L54="sob consulta","sob consulta", ROUND(L54*(1+pconfig!$B$6),2))) -> 0 | O54: =J54/H54 -> 17.3821 | P54: =ROUND(O54*(1+pconfig!$B$6),2) -> 17.95
A55: 2 - Data Center | B55: Hospedagem | C55: 5530 | D55: Conta de Email (20Gb) 500 Cx NOVO | E55: =IFERROR(__xludf.DUMMYFUNCTION("CONCATENATE(REGEXEXTRACT(D55,""[\d]+""),""GB"")"),"20GB") -> 20GB | F55: =D55&E55 -> Conta de Email (20Gb) 500 Cx NOVO20GB | G55: 1 | H55: 500 | I55: GB | J55: 8600.08 | K55: Mensal | M55: =(if(L55="sob consulta","sob consulta", ROUND(L55*(1+pconfig!$B$6),2))) -> 0 | O55: =J55/H55 -> 17.20016 | P55: =ROUND(O55*(1+pconfig!$B$6),2) -> 17.76
A56: 2 - Data Center | B56: Hospedagem | C56: 5530 | D56: Conta de Email (20Gb) 1000 Cx NOVO | E56: =IFERROR(__xludf.DUMMYFUNCTION("CONCATENATE(REGEXEXTRACT(D56,""[\d]+""),""GB"")"),"20GB") -> 20GB | F56: =D56&E56 -> Conta de Email (20Gb) 1000 Cx NOVO20GB | G56: 1 | H56: 1000 | I56: GB | J56: 17012.59 | K56: Mensal | M56: =(if(L56="sob consulta","sob consulta", ROUND(L56*(1+pconfig!$B$6),2))) -> 0 | O56: =J56/H56 -> 17.01259 | P56: =ROUND(O56*(1+pconfig!$B$6),2) -> 17.57
A57: 2 - Data Center | B57: Hospedagem | C57: 5530 | D57: Conta de Email (25Gb) 1 Cx NOVO | E57: =IFERROR(__xludf.DUMMYFUNCTION("CONCATENATE(REGEXEXTRACT(D57,""[\d]+""),""GB"")"),"25GB") -> 25GB | F57: =D57&E57 -> Conta de Email (25Gb) 1 Cx NOVO25GB | G57: 1 | H57: 1 | I57: GB | J57: 24.57 | K57: Mensal | M57: =(if(L57="sob consulta","sob consulta", ROUND(L57*(1+pconfig!$B$6),2))) -> 0 | O57: =J57/H57 -> 24.57 | P57: =ROUND(O57*(1+pconfig!$B$6),2) -> 25.38
A58: 2 - Data Center | B58: Hospedagem | C58: 5530 | D58: Conta de Email (25Gb) 25 Cx NOVO | E58: =IFERROR(__xludf.DUMMYFUNCTION("CONCATENATE(REGEXEXTRACT(D58,""[\d]+""),""GB"")"),"25GB") -> 25GB | F58: =D58&E58 -> Conta de Email (25Gb) 25 Cx NOVO25GB | G58: 1 | H58: 25 | I58: GB | J58: 590.01 | K58: Mensal | M58: =(if(L58="sob consulta","sob consulta", ROUND(L58*(1+pconfig!$B$6),2))) -> 0 | O58: =J58/H58 -> 23.6004 | P58: =ROUND(O58*(1+pconfig!$B$6),2) -> 24.37
A59: 2 - Data Center | B59: Hospedagem | C59: 5530 | D59: Conta de Email (25Gb) 50 Cx NOVO | E59: =IFERROR(__xludf.DUMMYFUNCTION("CONCATENATE(REGEXEXTRACT(D59,""[\d]+""),""GB"")"),"25GB") -> 25GB | F59: =D59&E59 -> Conta de Email (25Gb) 50 Cx NOVO25GB | G59: 1 | H59: 50 | I59: GB | J59: 1155.01 | K59: Mensal | M59: =(if(L59="sob consulta","sob consulta", ROUND(L59*(1+pconfig!$B$6),2))) -> 0 | O59: =J59/H59 -> 23.1002 | P59: =ROUND(O59*(1+pconfig!$B$6),2) -> 23.86
A60: 2 - Data Center | B60: Hospedagem | C60: 5530 | D60: Conta de Email (25Gb) 100 Cx NOVO | E60: =IFERROR(__xludf.DUMMYFUNCTION("CONCATENATE(REGEXEXTRACT(D60,""[\d]+""),""GB"")"),"25GB") -> 25GB | F60: =D60&E60 -> Conta de Email (25Gb) 100 Cx NOVO25GB | G60: 1 | H60: 100 | I60: GB | J60: 2170.2 | K60: Mensal | M60: =(if(L60="sob consulta","sob consulta", ROUND(L60*(1+pconfig!$B$6),2))) -> 0 | O60: =J60/H60 -> 21.702 | P60: =ROUND(O60*(1+pconfig!$B$6),2) -> 22.41
A61: 2 - Data Center | B61: Hospedagem | C61: 5530 | D61: Conta de Email (25Gb) 500 Cx NOVO | E61: =IFERROR(__xludf.DUMMYFUNCTION("CONCATENATE(REGEXEXTRACT(D61,""[\d]+""),""GB"")"),"25GB") -> 25GB | F61: =D61&E61 -> Conta de Email (25Gb) 500 Cx NOVO25GB | G61: 1 | H61: 500 | I61: GB | J61: 11180.68 | K61: Mensal | M61: =(if(L61="sob consulta","sob consulta", ROUND(L61*(1+pconfig!$B$6),2))) -> 0 | O61: =J61/H61 -> 22.36136 | P61: =ROUND(O61*(1+pconfig!$B$6),2) -> 23.09
A62: 2 - Data Center | B62: Hospedagem | C62: 5530 | D62: Conta de Email (25Gb) 1000 Cx NOVO | E62: =IFERROR(__xludf.DUMMYFUNCTION("CONCATENATE(REGEXEXTRACT(D62,""[\d]+""),""GB"")"),"25GB") -> 25GB | F62: =D62&E62 -> Conta de Email (25Gb) 1000 Cx NOVO25GB | G62: 1 | H62: 1000 | I62: GB | J62: 22122.62 | K62: Mensal | M62: =(if(L62="sob consulta","sob consulta", ROUND(L62*(1+pconfig!$B$6),2))) -> 0 | O62: =J62/H62 -> 22.12262 | P62: =ROUND(O62*(1+pconfig!$B$6),2) -> 22.85
A63: 2 - Data Center | B63: Hospedagem | C63: 5530 | D63: Conta de Email (30Gb) 1 Cx NOVO | E63: =IFERROR(__xludf.DUMMYFUNCTION("CONCATENATE(REGEXEXTRACT(D63,""[\d]+""),""GB"")"),"30GB") -> 30GB | F63: =D63&E63 -> Conta de Email (30Gb) 1 Cx NOVO30GB | G63: 1 | H63: 1 | I63: GB | J63: 31.94 | K63: Mensal | M63: =(if(L63="sob consulta","sob consulta", ROUND(L63*(1+pconfig!$B$6),2))) -> 0 | O63: =J63/H63 -> 31.94 | P63: =ROUND(O63*(1+pconfig!$B$6),2) -> 32.99
A64: 2 - Data Center | B64: Hospedagem | C64: 5530 | D64: Conta de Email (30Gb) 25 Cx NOVO | E64: =IFERROR(__xludf.DUMMYFUNCTION("CONCATENATE(REGEXEXTRACT(D64,""[\d]+""),""GB"")"),"30GB") -> 30GB | F64: =D64&E64 -> Conta de Email (30Gb) 25 Cx NOVO30GB | G64: 1 | H64: 25 | I64: GB | J64: 767.07 | K64: Mensal | M64: =(if(L64="sob consulta","sob consulta", ROUND(L64*(1+pconfig!$B$6),2))) -> 0 | O64: =J64/H64 -> 30.6828 | P64: =ROUND(O64*(1+pconfig!$B$6),2) -> 31.69
A65: 2 - Data Center | B65: Hospedagem | C65: 5530 | D65: Conta de Email (30Gb) 50 Cx NOVO | E65: =IFERROR(__xludf.DUMMYFUNCTION("CONCATENATE(REGEXEXTRACT(D65,""[\d]+""),""GB"")"),"30GB") -> 30GB | F65: =D65&E65 -> Conta de Email (30Gb) 50 Cx NOVO30GB | G65: 1 | H65: 50 | I65: GB | J65: 1501.75 | K65: Mensal | M65: =(if(L65="sob consulta","sob consulta", ROUND(L65*(1+pconfig!$B$6),2))) -> 0 | O65: =J65/H65 -> 30.035 | P65: =ROUND(O65*(1+pconfig!$B$6),2) -> 31.02
A66: 2 - Data Center | B66: Hospedagem | C66: 5530 | D66: Conta de Email (30Gb) 100 Cx NOVO | E66: =IFERROR(__xludf.DUMMYFUNCTION("CONCATENATE(REGEXEXTRACT(D66,""[\d]+""),""GB"")"),"30GB") -> 30GB | F66: =D66&E66 -> Conta de Email (30Gb) 100 Cx NOVO30GB | G66: 1 | H66: 100 | I66: GB | J66: 2939.83 | K66: Mensal | M66: =(if(L66="sob consulta","sob consulta", ROUND(L66*(1+pconfig!$B$6),2))) -> 0 | O66: =J66/H66 -> 29.3983 | P66: =ROUND(O66*(1+pconfig!$B$6),2) -> 30.36
A67: 2 - Data Center | B67: Hospedagem | C67: 5530 | D67: Conta de Email (30Gb) 500 Cx NOVO | E67: =IFERROR(__xludf.DUMMYFUNCTION("CONCATENATE(REGEXEXTRACT(D67,""[\d]+""),""GB"")"),"30GB") -> 30GB | F67: =D67&E67 -> Conta de Email (30Gb) 500 Cx NOVO30GB | G67: 1 | H67: 500 | I67: GB | J67: 14540 | K67: Mensal | M67: =(if(L67="sob consulta","sob consulta", ROUND(L67*(1+pconfig!$B$6),2))) -> 0 | O67: =J67/H67 -> 29.08 | P67: =ROUND(O67*(1+pconfig!$B$6),2) -> 30.03
A68: 2 - Data Center | B68: Hospedagem | C68: 5530 | D68: Conta de Email (30Gb) 1000 Cx NOVO | E68: =IFERROR(__xludf.DUMMYFUNCTION("CONCATENATE(REGEXEXTRACT(D68,""[\d]+""),""GB"")"),"30GB") -> 30GB | F68: =D68&E68 -> Conta de Email (30Gb) 1000 Cx NOVO30GB | G68: 1 | H68: 1000 | I68: GB | J68: 28761.69 | K68: Mensal | M68: =(if(L68="sob consulta","sob consulta", ROUND(L68*(1+pconfig!$B$6),2))) -> 0 | O68: =J68/H68 -> 28.76169 | P68: =ROUND(O68*(1+pconfig!$B$6),2) -> 29.71
A69: 3 - Impressão Corporativa | B69: Carteiras e Crachás | D69: Emissão de cartão/carteira/crachá pvc (com tratamento) | F69: =D69&E69 -> Emissão de cartão/carteira/crachá pvc (com tratamento) | I69: Cartão | K69: Sob demanda | M69: =(if(L69="sob consulta","sob consulta", ROUND(L69*(1+pconfig!$B$6),2))) -> 0 | O69: 15.35 | P69: =ROUND(O69*(1+pconfig!$B$6),2) -> 15.85
A70: 3 - Impressão Corporativa | B70: Carteiras e Crachás | D70: Emissão de cartão/carteira/crachá pvc (sem tratamento) | F70: =D70&E70 -> Emissão de cartão/carteira/crachá pvc (sem tratamento) | I70: Cartão | K70: Sob demanda | M70: =(if(L70="sob consulta","sob consulta", ROUND(L70*(1+pconfig!$B$6),2))) -> 0 | O70: 9.66 | P70: =ROUND(O70*(1+pconfig!$B$6),2) -> 9.98
A71: 3 - Impressão Corporativa | B71: Impressão e Envelopamento | D71: Envelopamento papel A4 | F71: =D71&E71 -> Envelopamento papel A4 | I71: Página | K71: Sob demanda | M71: =(if(L71="sob consulta","sob consulta", ROUND(L71*(1+pconfig!$B$6),2))) -> 0 | O71: 0.1 | P71: =ROUND(O71*(1+pconfig!$B$6),2) -> 0.1
A72: 3 - Impressão Corporativa | B72: Impressão e Envelopamento | D72: Impressão – A4 Simplex Preto e Branco | F72: =D72&E72 -> Impressão – A4 Simplex Preto e Branco | I72: Página | K72: Sob demanda | M72: =(if(L72="sob consulta","sob consulta", ROUND(L72*(1+pconfig!$B$6),2))) -> 0 | O72: 0.3 | P72: =ROUND(O72*(1+pconfig!$B$6),2) -> 0.31
A73: 3 - Impressão Corporativa | B73: Impressão e Envelopamento | D73: Impressão – A4 Simplex Colorida | F73: =D73&E73 -> Impressão – A4 Simplex Colorida | I73: Página | K73: Sob demanda | M73: =(if(L73="sob consulta","sob consulta", ROUND(L73*(1+pconfig!$B$6),2))) -> 0 | O73: 2.58 | P73: =ROUND(O73*(1+pconfig!$B$6),2) -> 2.66
A74: 3 - Impressão Corporativa | B74: Impressão e Envelopamento | D74: Impressão – A4 Duplex Preto e Branco | F74: =D74&E74 -> Impressão – A4 Duplex Preto e Branco | I74: Página | K74: Sob demanda | M74: =(if(L74="sob consulta","sob consulta", ROUND(L74*(1+pconfig!$B$6),2))) -> 0 | O74: 0.6 | P74: =ROUND(O74*(1+pconfig!$B$6),2) -> 0.62
A75: 3 - Impressão Corporativa | B75: Impressão e Envelopamento | D75: Impressão – A4 Duplex Colorida | F75: =D75&E75 -> Impressão – A4 Duplex Colorida | I75: Página | K75: Mensal | M75: =(if(L75="sob consulta","sob consulta", ROUND(L75*(1+pconfig!$B$6),2))) -> 0 | O75: 5.15 | P75: =ROUND(O75*(1+pconfig!$B$6),2) -> 5.32
A76: 4- Microfilmagem e Digitalização | B76: Preparação do acervo | D76: Preparação do acervo | F76: =D76&E76 -> Preparação do acervo | I76: Preparação | K76: Mensal | M76: =(if(L76="sob consulta","sob consulta", ROUND(L76*(1+pconfig!$B$6),2))) -> 0 | O76: 4442.03 | P76: =ROUND(O76*(1+pconfig!$B$6),2) -> 4587.73
A77: 4- Microfilmagem e Digitalização | B77: Microfilmagem de Documentos 16mm | D77: Microfilmagem 16mm (até 100.000) | F77: =D77&E77 -> Microfilmagem 16mm (até 100.000) | G77: 1 | H77: 100000 | I77: Fotograma | K77: Sob demanda | M77: =(if(L77="sob consulta","sob consulta", ROUND(L77*(1+pconfig!$B$6),2))) -> 0 | O77: 0.43 | P77: =ROUND(O77*(1+pconfig!$B$6),2) -> 0.44
A78: 4- Microfilmagem e Digitalização | B78: Microfilmagem de Documentos 16mm | D78: Microfilmagem 16mm (até 1.000.000) | F78: =D78&E78 -> Microfilmagem 16mm (até 1.000.000) | G78: 1 | H78: 1000000 | I78: Fotograma | K78: Sob demanda | M78: =(if(L78="sob consulta","sob consulta", ROUND(L78*(1+pconfig!$B$6),2))) -> 0 | O78: 0.42 | P78: =ROUND(O78*(1+pconfig!$B$6),2) -> 0.43
A79: 4- Microfilmagem e Digitalização | B79: Microfilmagem de Documentos 16mm | D79: Microfilmagem 16mm (até 2.000.000) | F79: =D79&E79 -> Microfilmagem 16mm (até 2.000.000) | G79: 1 | H79: 2000000 | I79: Fotograma | K79: Sob demanda | M79: =(if(L79="sob consulta","sob consulta", ROUND(L79*(1+pconfig!$B$6),2))) -> 0 | O79: 0.4 | P79: =ROUND(O79*(1+pconfig!$B$6),2) -> 0.41
A80: 4- Microfilmagem e Digitalização | B80: Microfilmagem de Documentos 16mm | D80: Microfilmagem 16mm (acima de 2.000.000) | F80: =D80&E80 -> Microfilmagem 16mm (acima de 2.000.000) | I80: Fotograma | K80: Sob demanda | M80: =(if(L80="sob consulta","sob consulta", ROUND(L80*(1+pconfig!$B$6),2))) -> 0 | O80: 0.39 | P80: =ROUND(O80*(1+pconfig!$B$6),2) -> 0.4
A81: 4- Microfilmagem e Digitalização | B81: Microfilmagem de Documentos 35mm | D81: Microfilmagem 35mm (até 100.000) | F81: =D81&E81 -> Microfilmagem 35mm (até 100.000) | H81: 100000 | I81: Fotograma | K81: Sob demanda | M81: =(if(L81="sob consulta","sob consulta", ROUND(L81*(1+pconfig!$B$6),2))) -> 0 | O81: 2.27 | P81: =ROUND(O81*(1+pconfig!$B$6),2) -> 2.34
A82: 4- Microfilmagem e Digitalização | B82: Microfilmagem de Documentos 35mm | D82: Microfilmagem 35mm (até 1.000.000) | F82: =D82&E82 -> Microfilmagem 35mm (até 1.000.000) | H82: 1000000 | I82: Fotograma | K82: Sob demanda | M82: =(if(L82="sob consulta","sob consulta", ROUND(L82*(1+pconfig!$B$6),2))) -> 0 | O82: 2.26 | P82: =ROUND(O82*(1+pconfig!$B$6),2) -> 2.33
A83: 4- Microfilmagem e Digitalização | B83: Microfilmagem de Documentos 35mm | D83: Microfilmagem 35mm (até 2.000.000) | F83: =D83&E83 -> Microfilmagem 35mm (até 2.000.000) | H83: 2000000 | I83: Fotograma | K83: Sob demanda | M83: =(if(L83="sob consulta","sob consulta", ROUND(L83*(1+pconfig!$B$6),2))) -> 0 | O83: 2.25 | P83: =ROUND(O83*(1+pconfig!$B$6),2) -> 2.32
A84: 4- Microfilmagem e Digitalização | B84: Microfilmagem de Documentos 35mm | D84: Microfilmagem 35mm (acima de 2.000.000) | F84: =D84&E84 -> Microfilmagem 35mm (acima de 2.000.000) | I84: Fotograma | K84: Sob demanda | M84: =(if(L84="sob consulta","sob consulta", ROUND(L84*(1+pconfig!$B$6),2))) -> 0 | O84: 2.24 | P84: =ROUND(O84*(1+pconfig!$B$6),2) -> 2.31
A85: 4- Microfilmagem e Digitalização | B85: Microfilmagem e Digitalização 16mm | D85: Microfilmagem e Digitalização 16mm (até 100.000) | F85: =D85&E85 -> Microfilmagem e Digitalização 16mm (até 100.000) | H85: 100000 | I85: Fotograma | K85: Sob demanda | M85: =(if(L85="sob consulta","sob consulta", ROUND(L85*(1+pconfig!$B$6),2))) -> 0 | O85: 0.47 | P85: =ROUND(O85*(1+pconfig!$B$6),2) -> 0.49
A86: 4- Microfilmagem e Digitalização | B86: Microfilmagem e Digitalização 16mm | D86: Microfilmagem e Digitalização 16mm (até 1.000.000) | F86: =D86&E86 -> Microfilmagem e Digitalização 16mm (até 1.000.000) | H86: 1000000 | I86: Fotograma | K86: Sob demanda | M86: =(if(L86="sob consulta","sob consulta", ROUND(L86*(1+pconfig!$B$6),2))) -> 0 | O86: 0.45 | P86: =ROUND(O86*(1+pconfig!$B$6),2) -> 0.46
A87: 4- Microfilmagem e Digitalização | B87: Microfilmagem e Digitalização 16mm | D87: Microfilmagem e Digitalização 16mm (até 2.000.000) | F87: =D87&E87 -> Microfilmagem e Digitalização 16mm (até 2.000.000) | H87: 2000000 | I87: Fotograma | K87: Sob demanda | M87: =(if(L87="sob consulta","sob consulta", ROUND(L87*(1+pconfig!$B$6),2))) -> 0 | O87: 0.44 | P87: =ROUND(O87*(1+pconfig!$B$6),2) -> 0.45
A88: 4- Microfilmagem e Digitalização | B88: Microfilmagem e Digitalização 16mm | D88: Microfilmagem e Digitalização 16mm (acima de 2.000.000) | F88: =D88&E88 -> Microfilmagem e Digitalização 16mm (acima de 2.000.000) | I88: Fotograma | K88: Sob demanda | M88: =(if(L88="sob consulta","sob consulta", ROUND(L88*(1+pconfig!$B$6),2))) -> 0 | O88: 0.43 | P88: =ROUND(O88*(1+pconfig!$B$6),2) -> 0.44
A89: 4- Microfilmagem e Digitalização | B89: Microfilmagem e Digitalização 35mm | D89: Microfilmagem e Digitalização 35mm (até 100.000) | F89: =D89&E89 -> Microfilmagem e Digitalização 35mm (até 100.000) | H89: 100000 | I89: Fotograma | K89: Sob demanda | M89: =(if(L89="sob consulta","sob consulta", ROUND(L89*(1+pconfig!$B$6),2))) -> 0 | O89: 2.34 | P89: =ROUND(O89*(1+pconfig!$B$6),2) -> 2.42
A90: 4- Microfilmagem e Digitalização | B90: Microfilmagem e Digitalização 35mm | D90: Microfilmagem e Digitalização 35mm (até 1.000.000) | F90: =D90&E90 -> Microfilmagem e Digitalização 35mm (até 1.000.000) | H90: 1000000 | I90: Fotograma | K90: Sob demanda | M90: =(if(L90="sob consulta","sob consulta", ROUND(L90*(1+pconfig!$B$6),2))) -> 0 | O90: 2.33 | P90: =ROUND(O90*(1+pconfig!$B$6),2) -> 2.41
A91: 4- Microfilmagem e Digitalização | B91: Microfilmagem e Digitalização 35mm | D91: Microfilmagem e Digitalização 35mm (até 2.000.000) | F91: =D91&E91 -> Microfilmagem e Digitalização 35mm (até 2.000.000) | H91: 2000000 | I91: Fotograma | K91: Sob demanda | M91: =(if(L91="sob consulta","sob consulta", ROUND(L91*(1+pconfig!$B$6),2))) -> 0 | O91: 2.32 | P91: =(if(O91="sob consulta","sob consulta", ROUND(O91*(1+pconfig!$B$6),2))) -> 2.4
A92: 4- Microfilmagem e Digitalização | B92: Microfilmagem e Digitalização 35mm | D92: Microfilmagem e Digitalização 35mm (acima de 2.000.000) | F92: =D92&E92 -> Microfilmagem e Digitalização 35mm (acima de 2.000.000) | I92: Fotograma | K92: Sob demanda | M92: =(if(L92="sob consulta","sob consulta", ROUND(L92*(1+pconfig!$B$6),2))) -> 0 | O92: 2.31 | P92: =(if(O92="sob consulta","sob consulta", ROUND(O92*(1+pconfig!$B$6),2))) -> 2.39
A93: 4- Microfilmagem e Digitalização | B93: Digitalização de Documento | D93: Digitalização de Documento | F93: =D93&E93 -> Digitalização de Documento | I93: documento | K93: Sob demanda | M93: =(if(L93="sob consulta","sob consulta", ROUND(L93*(1+pconfig!$B$6),2))) -> 0 | O93: 0.24 | P93: =(if(O93="sob consulta","sob consulta", ROUND(O93*(1+pconfig!$B$6),2))) -> 0.25
A94: 4- Microfilmagem e Digitalização | B94: Digitalização de Fotograma 16mm | D94: Digitalização de Fotograma 16mm | F94: =D94&E94 -> Digitalização de Fotograma 16mm | I94: Fotograma | K94: Sob demanda | M94: =(if(L94="sob consulta","sob consulta", ROUND(L94*(1+pconfig!$B$6),2))) -> 0 | O94: 0.25 | P94: =(if(O94="sob consulta","sob consulta", ROUND(O94*(1+pconfig!$B$6),2))) -> 0.26
A95: 4- Microfilmagem e Digitalização | B95: Digitalização de Fotograma 35mm | D95: Digitalização de Fotograma 35mm | F95: =D95&E95 -> Digitalização de Fotograma 35mm | I95: Fotograma | K95: Sob demanda | M95: =(if(L95="sob consulta","sob consulta", ROUND(L95*(1+pconfig!$B$6),2))) -> 0 | O95: 0.28 | P95: =(if(O95="sob consulta","sob consulta", ROUND(O95*(1+pconfig!$B$6),2))) -> 0.29
A96: 4- Microfilmagem e Digitalização | B96: Licença do sistema INDEXA | D96: Licença do sistema INDEXA – mensal | F96: =D96&E96 -> Licença do sistema INDEXA – mensal | I96: Licença de software | K96: Mensal | L96: 4139.32 | M96: =(if(L96="sob consulta","sob consulta", ROUND(L96*(1+pconfig!$B$6),2))) -> 4275.09 | O96: =L96/12 -> 344.94333 | P96: =(if(O96="sob consulta","sob consulta", ROUND(O96*(1+pconfig!$B$6),2))) -> 356.26
A97: 4- Microfilmagem e Digitalização | B97: Armazenamento de Imagem Digital - Novo | D97: Armazenamento de Imagem Digital até 80 GB | E97: 80GB | F97: =D97&E97 -> Armazenamento de Imagem Digital até 80 GB80GB | I97: GB | M97: =(if(L97="sob consulta","sob consulta", ROUND(L97*(1+pconfig!$B$6),2))) -> 0 | O97: 1.25 | P97: =(if(O97="sob consulta","sob consulta", ROUND(O97*(1+pconfig!$B$6),2))) -> 1.29
A98: 4- Microfilmagem e Digitalização | B98: Armazenamento de Imagem Digital - Novo | D98: Armazenamento de Imagem Digital até 160 GB | E98: 160 | F98: =D98&E98 -> Armazenamento de Imagem Digital até 160 GB160 | I98: GB | M98: =(if(L98="sob consulta","sob consulta", ROUND(L98*(1+pconfig!$B$6),2))) -> 0 | O98: 1.14 | P98: =(if(O98="sob consulta","sob consulta", ROUND(O98*(1+pconfig!$B$6),2))) -> 1.18
A99: 4- Microfilmagem e Digitalização | B99: Armazenamento de Imagem Digital - Novo | D99: Armazenamento de Imagem Digital até 240 GB | E99: 240 | F99: =D99&E99 -> Armazenamento de Imagem Digital até 240 GB240 | I99: GB | M99: =(if(L99="sob consulta","sob consulta", ROUND(L99*(1+pconfig!$B$6),2))) -> 0 | O99: 1.03 | P99: =(if(O99="sob consulta","sob consulta", ROUND(O99*(1+pconfig!$B$6),2))) -> 1.06
A100: 4- Microfilmagem e Digitalização | B100: Armazenamento de Imagem Digital - Novo | D100: Armazenamento de Imagem Digital até 320 GB | E100: 320 | F100: =D100&E100 -> Armazenamento de Imagem Digital até 320 GB320 | I100: GB | M100: =(if(L100="sob consulta","sob consulta", ROUND(L100*(1+pconfig!$B$6),2))) -> 0 | O100: 0.92 | P100: =(if(O100="sob consulta","sob consulta", ROUND(O100*(1+pconfig!$B$6),2))) -> 0.95
...

Sheet linkdados
A1: item | B1: MunicIpio | C1: Modalidade | D1: tecnologias | E1: indice | F1: Mbps | G1: Mesorreg | H1: ATENDIDO | I1: Regint | J1: Degrau | K1: UnitTransporte | L1: UnitTransFinal | M1: Cmanut | N1: Cmanutfinal | O1: Preço Final | P1: PvTranporte | Q1: PvTransportDesc | R1: PvFinal
A2: 1 | B2: ABAETETUBA | C2: RADIO | D2: ALVARION, CALIUM, AIRMUX | E2: =B2&C2 -> ABAETETUBARADIO | F2: 1 | G2: NORDESTE | H2: {=XLOOKUP(B2,municipios,regiao!$D$6:$D$150,0)} -> SIM | I2: TOCANTINS | J2: D2 | K2: 15.65 | L2: =K2/(1-pconfig!$G$2-pconfig!$G$3-pconfig!$G$4) -> 29.550604 | M2: 138.285 | N2: =M2/(1-pconfig!$G$2-pconfig!$G$3-pconfig!$G$4) -> 261.11216 | O2: =((K2*F2)+M2)/(1-pconfig!$G$2-pconfig!$G$3-pconfig!$G$4) -> 290.66276 | P2: =K2*F2/(1-pconfig!$G$2-pconfig!$G$3-pconfig!$G$4) -> 29.550604 | Q2: =IFS(F2<=pconfig!$B$12,P2*pconfig!$C$12,F2<=pconfig!$B$13,P2*pconfig!$C$13,F2<=pconfig!$B$14,P2*pconfig!$C$14,F2<=pconfig!$B$15,P2*pconfig!$C$15,F2<=pconfig!$B$16,P2*pconfig!$C$16,F2<=pconfig!$B$17,P2*pconfig!$C$17,F2<=pconfig!$B$18,P2*pconfig!$C$18,F2<=pconfig!$B$19,P2*pconfig!$C$19,F2<=pconfig!$B$20,P2*pconfig!$C$20,F2<=pconfig!$B$21,P2*pconfig!$C$21) -> 29.550604 | R2: =IF(Q2=0,P2+N2,Q2+N2) -> 290.66276
A3: =A2+1 -> 2 | B3: ABAETETUBA | C3: FIBRA | D3: METRO, GPON | E3: =B3&C3 -> ABAETETUBAFIBRA | F3: 1 | G3: NORDESTE | H3: {=XLOOKUP(B3,municipios,regiao!$D$6:$D$150,0)} -> SIM | I3: TOCANTINS | J3: D2 | K3: 15.65 | L3: =K3/(1-pconfig!$G$2-pconfig!$G$3-pconfig!$G$4) -> 29.550604 | M3: 314.77 | N3: =M3/(1-pconfig!$G$2-pconfig!$G$3-pconfig!$G$4) -> 594.35423 | O3: =((K3*F3)+M3)/(1-pconfig!$G$2-pconfig!$G$3-pconfig!$G$4) -> 623.90483 | P3: =(K3*F3/(1-pconfig!$G$2-pconfig!$G$3-pconfig!$G$4)) -> 29.550604 | Q3: =IFS(F3<=pconfig!$B$12,P3*pconfig!$C$12,F3<=pconfig!$B$13,P3*pconfig!$C$13,F3<=pconfig!$B$14,P3*pconfig!$C$14,F3<=pconfig!$B$15,P3*pconfig!$C$15,F3<=pconfig!$B$16,P3*pconfig!$C$16,F3<=pconfig!$B$17,P3*pconfig!$C$17,F3<=pconfig!$B$18,P3*pconfig!$C$18,F3<=pconfig!$B$19,P3*pconfig!$C$19,F3<=pconfig!$B$20,P3*pconfig!$C$20,F3<=pconfig!$B$21,P3*pconfig!$C$21) -> 29.550604 | R3: =IF(Q3=0,P3+N3,Q3+N3) -> 623.90483
A4: =A3+1 -> 3 | B4: ABAETETUBA | C4: SATELITE | D4: TELEBRAS | E4: =B4&C4 -> ABAETETUBASATELITE | F4: 1 | G4: NORDESTE | H4: {=XLOOKUP(B4,municipios,regiao!$D$6:$D$150,0)} -> SIM | I4: TOCANTINS | J4: - | K4: 4799 | L4: =K4/(1-pconfig!$G$2-pconfig!$G$3-pconfig!$G$4) -> 9061.5559 | M4: 314.77 | N4: =M4/(1-pconfig!$G$2-pconfig!$G$3-pconfig!$G$4) -> 594.35423 | O4: =((K4*F4)+M4)/(1-pconfig!$G$2-pconfig!$G$3-pconfig!$G$4) -> 9655.9101 | P4: =K4*F4/(1-pconfig!$G$2-pconfig!$G$3-pconfig!$G$4) -> 9061.5559 | Q4: =IFS(F4<=pconfig!$B$12,P4*pconfig!$C$12,F4<=pconfig!$B$13,P4*pconfig!$C$13,F4<=pconfig!$B$14,P4*pconfig!$C$14,F4<=pconfig!$B$15,P4*pconfig!$C$15,F4<=pconfig!$B$16,P4*pconfig!$C$16,F4<=pconfig!$B$17,P4*pconfig!$C$17,F4<=pconfig!$B$18,P4*pconfig!$C$18,F4<=pconfig!$B$19,P4*pconfig!$C$19,F4<=pconfig!$B$20,P4*pconfig!$C$20,F4<=pconfig!$B$21,P4*pconfig!$C$21) -> 9061.5559 | R4: =IF(Q4=0,P4+N4,Q4+N4) -> 9655.9101
A5: =A4+1 -> 4 | B5: ABEL FIGUEIREDO | C5: FIBRA | D5: METRO, GPON | E5: =B5&C5 -> ABEL FIGUEIREDOFIBRA | F5: 1 | G5: SUDESTE | H5: {=XLOOKUP(B5,municipios,regiao!$D$6:$D$150,0)} -> NÃO | I5: RIO CAPIM | J5: D6 | K5: 29.29 | L5: =K5/(1-pconfig!$G$2-pconfig!$G$3-pconfig!$G$4) -> 55.305891 | M5: 63.39 | N5: =M5/(1-pconfig!$G$2-pconfig!$G$3-pconfig!$G$4) -> 119.69411 | O5: =((K5*F5)+M5)/(1-pconfig!$G$2-pconfig!$G$3-pconfig!$G$4) -> 175 | P5: =K5*F5/(1-pconfig!$G$2-pconfig!$G$3-pconfig!$G$4) -> 55.305891 | Q5: =IFS(F5<=pconfig!$B$12,P5*pconfig!$C$12,F5<=pconfig!$B$13,P5*pconfig!$C$13,F5<=pconfig!$B$14,P5*pconfig!$C$14,F5<=pconfig!$B$15,P5*pconfig!$C$15,F5<=pconfig!$B$16,P5*pconfig!$C$16,F5<=pconfig!$B$17,P5*pconfig!$C$17,F5<=pconfig!$B$18,P5*pconfig!$C$18,F5<=pconfig!$B$19,P5*pconfig!$C$19,F5<=pconfig!$B$20,P5*pconfig!$C$20,F5<=pconfig!$B$21,P5*pconfig!$C$21) -> 55.305891 | R5: =IF(Q5=0,P5+N5,Q5+N5) -> 175
A6: =A5+1 -> 5 | B6: ABEL FIGUEIREDO | C6: SATELITE | D6: TELEBRAS | E6: =B6&C6 -> ABEL FIGUEIREDOSATELITE | F6: 1 | G6: SUDESTE | H6: {=XLOOKUP(B6,municipios,regiao!$D$6:$D$150,0)} -> NÃO | I6: RIO CAPIM | J6: - | K6: 4799 | L6: =K6/(1-pconfig!$G$2-pconfig!$G$3-pconfig!$G$4) -> 9061.5559 | M6: 63.39 | N6: =M6/(1-pconfig!$G$2-pconfig!$G$3-pconfig!$G$4) -> 119.69411 | O6: =((K6*F6)+M6)/(1-pconfig!$G$2-pconfig!$G$3-pconfig!$G$4) -> 9181.25 | P6: =K6*F6/(1-pconfig!$G$2-pconfig!$G$3-pconfig!$G$4) -> 9061.5559 | Q6: =IFS(F6<=pconfig!$B$12,P6*pconfig!$C$12,F6<=pconfig!$B$13,P6*pconfig!$C$13,F6<=pconfig!$B$14,P6*pconfig!$C$14,F6<=pconfig!$B$15,P6*pconfig!$C$15,F6<=pconfig!$B$16,P6*pconfig!$C$16,F6<=pconfig!$B$17,P6*pconfig!$C$17,F6<=pconfig!$B$18,P6*pconfig!$C$18,F6<=pconfig!$B$19,P6*pconfig!$C$19,F6<=pconfig!$B$20,P6*pconfig!$C$20,F6<=pconfig!$B$21,P6*pconfig!$C$21) -> 9061.5559 | R6: =IF(Q6=0,P6+N6,Q6+N6) -> 9181.25
A7: =A6+1 -> 6 | B7: ABEL FIGUEIREDO | C7: RADIO | D7: ALVARION, CALIUM, AIRMUX | E7: =B7&C7 -> ABEL FIGUEIREDORADIO | F7: 1 | G7: SUDESTE | H7: {=XLOOKUP(B7,municipios,regiao!$D$6:$D$150,0)} -> NÃO | I7: RIO CAPIM | J7: D6 | K7: 29.29 | L7: =K7/(1-pconfig!$G$2-pconfig!$G$3-pconfig!$G$4) -> 55.305891 | M7: 333.33333 | N7: =M7/(1-pconfig!$G$2-pconfig!$G$3-pconfig!$G$4) -> 629.40584 | O7: =((K7*F7)+M7)/(1-pconfig!$G$2-pconfig!$G$3-pconfig!$G$4) -> 684.71173 | P7: =K7*F7/(1-pconfig!$G$2-pconfig!$G$3-pconfig!$G$4) -> 55.305891 | Q7: =IFS(F7<=pconfig!$B$12,P7*pconfig!$C$12,F7<=pconfig!$B$13,P7*pconfig!$C$13,F7<=pconfig!$B$14,P7*pconfig!$C$14,F7<=pconfig!$B$15,P7*pconfig!$C$15,F7<=pconfig!$B$16,P7*pconfig!$C$16,F7<=pconfig!$B$17,P7*pconfig!$C$17,F7<=pconfig!$B$18,P7*pconfig!$C$18,F7<=pconfig!$B$19,P7*pconfig!$C$19,F7<=pconfig!$B$20,P7*pconfig!$C$20,F7<=pconfig!$B$21,P7*pconfig!$C$21) -> 55.305891 | R7: =IF(Q7=0,P7+N7,Q7+N7) -> 684.71173
A8: =A7+1 -> 7 | B8: ACARA | C8: RADIO | D8: ALVARION, CALIUM, AIRMUX | E8: =B8&C8 -> ACARARADIO | F8: 1 | G8: NORDESTE | H8: {=XLOOKUP(B8,municipios,regiao!$D$6:$D$150,0)} -> NÃO | I8: TOCANTINS | J8: D4 | K8: 20.69 | L8: =K8/(1-pconfig!$G$2-pconfig!$G$3-pconfig!$G$4) -> 39.067221 | M8: 138.285 | N8: =M8/(1-pconfig!$G$2-pconfig!$G$3-pconfig!$G$4) -> 261.11216 | O8: =((K8*F8)+M8)/(1-pconfig!$G$2-pconfig!$G$3-pconfig!$G$4) -> 300.17938 | P8: =K8*F8/(1-pconfig!$G$2-pconfig!$G$3-pconfig!$G$4) -> 39.067221 | Q8: =IFS(F8<=pconfig!$B$12,P8*pconfig!$C$12,F8<=pconfig!$B$13,P8*pconfig!$C$13,F8<=pconfig!$B$14,P8*pconfig!$C$14,F8<=pconfig!$B$15,P8*pconfig!$C$15,F8<=pconfig!$B$16,P8*pconfig!$C$16,F8<=pconfig!$B$17,P8*pconfig!$C$17,F8<=pconfig!$B$18,P8*pconfig!$C$18,F8<=pconfig!$B$19,P8*pconfig!$C$19,F8<=pconfig!$B$20,P8*pconfig!$C$20,F8<=pconfig!$B$21,P8*pconfig!$C$21) -> 39.067221 | R8: =IF(Q8=0,P8+N8,Q8+N8) -> 300.17938
A9: =A8+1 -> 8 | B9: ACARA | C9: FIBRA | D9: METRO, GPON | E9: =B9&C9 -> ACARAFIBRA | F9: 1 | G9: NORDESTE | H9: {=XLOOKUP(B9,municipios,regiao!$D$6:$D$150,0)} -> NÃO | I9: TOCANTINS | J9: D4 | K9: 20.69 | L9: =K9/(1-pconfig!$G$2-pconfig!$G$3-pconfig!$G$4) -> 39.067221 | M9: 314.77 | N9: =M9/(1-pconfig!$G$2-pconfig!$G$3-pconfig!$G$4) -> 594.35423 | O9: =((K9*F9)+M9)/(1-pconfig!$G$2-pconfig!$G$3-pconfig!$G$4) -> 633.42145 | P9: =K9*F9/(1-pconfig!$G$2-pconfig!$G$3-pconfig!$G$4) -> 39.067221 | Q9: =IFS(F9<=pconfig!$B$12,P9*pconfig!$C$12,F9<=pconfig!$B$13,P9*pconfig!$C$13,F9<=pconfig!$B$14,P9*pconfig!$C$14,F9<=pconfig!$B$15,P9*pconfig!$C$15,F9<=pconfig!$B$16,P9*pconfig!$C$16,F9<=pconfig!$B$17,P9*pconfig!$C$17,F9<=pconfig!$B$18,P9*pconfig!$C$18,F9<=pconfig!$B$19,P9*pconfig!$C$19,F9<=pconfig!$B$20,P9*pconfig!$C$20,F9<=pconfig!$B$21,P9*pconfig!$C$21) -> 39.067221 | R9: =IF(Q9=0,P9+N9,Q9+N9) -> 633.42145
A10: =A9+1 -> 9 | B10: ACARA | C10: SATELITE | D10: TELEBRAS | E10: =B10&C10 -> ACARASATELITE | F10: 1 | G10: NORDESTE | H10: {=XLOOKUP(B10,municipios,regiao!$D$6:$D$150,0)} -> NÃO | I10: TOCANTINS | J10: - | K10: 4799 | L10: =K10/(1-pconfig!$G$2-pconfig!$G$3-pconfig!$G$4) -> 9061.5559 | M10: 314.77 | N10: =M10/(1-pconfig!$G$2-pconfig!$G$3-pconfig!$G$4) -> 594.35423 | O10: =((K10*F10)+M10)/(1-pconfig!$G$2-pconfig!$G$3-pconfig!$G$4) -> 9655.9101 | P10: =K10*F10/(1-pconfig!$G$2-pconfig!$G$3-pconfig!$G$4) -> 9061.5559 | Q10: =IFS(F10<=pconfig!$B$12,P10*pconfig!$C$12,F10<=pconfig!$B$13,P10*pconfig!$C$13,F10<=pconfig!$B$14,P10*pconfig!$C$14,F10<=pconfig!$B$15,P10*pconfig!$C$15,F10<=pconfig!$B$16,P10*pconfig!$C$16,F10<=pconfig!$B$17,P10*pconfig!$C$17,F10<=pconfig!$B$18,P10*pconfig!$C$18,F10<=pconfig!$B$19,P10*pconfig!$C$19,F10<=pconfig!$B$20,P10*pconfig!$C$20,F10<=pconfig!$B$21,P10*pconfig!$C$21) -> 9061.5559 | R10: =IF(Q10=0,P10+N10,Q10+N10) -> 9655.9101
A11: =A10+1 -> 10 | B11: AFUA | C11: RADIO | D11: ALVARION, CALIUM, AIRMUX | E11: =B11&C11 -> AFUARADIO | F11: 1 | G11: MARAJÓ | H11: {=XLOOKUP(B11,municipios,regiao!$D$6:$D$150,0)} -> NÃO | I11: MARAJÓ | J11: D7 | K11: 35.73 | L11: =K11/(1-pconfig!$G$2-pconfig!$G$3-pconfig!$G$4) -> 67.466012 | M11: 106.69333 | N11: =M11/(1-pconfig!$G$2-pconfig!$G$3-pconfig!$G$4) -> 201.46022 | O11: =((K11*F11)+M11)/(1-pconfig!$G$2-pconfig!$G$3-pconfig!$G$4) -> 268.92623 | P11: =K11*F11/(1-pconfig!$G$2-pconfig!$G$3-pconfig!$G$4) -> 67.466012 | Q11: =IFS(F11<=pconfig!$B$12,P11*pconfig!$C$12,F11<=pconfig!$B$13,P11*pconfig!$C$13,F11<=pconfig!$B$14,P11*pconfig!$C$14,F11<=pconfig!$B$15,P11*pconfig!$C$15,F11<=pconfig!$B$16,P11*pconfig!$C$16,F11<=pconfig!$B$17,P11*pconfig!$C$17,F11<=pconfig!$B$18,P11*pconfig!$C$18,F11<=pconfig!$B$19,P11*pconfig!$C$19,F11<=pconfig!$B$20,P11*pconfig!$C$20,F11<=pconfig!$B$21,P11*pconfig!$C$21) -> 67.466012 | R11: =IF(Q11=0,P11+N11,Q11+N11) -> 268.92623
A12: =A11+1 -> 11 | B12: AFUA | C12: FIBRA | D12: METRO, GPON | E12: =B12&C12 -> AFUAFIBRA | F12: 1 | G12: MARAJÓ | H12: {=XLOOKUP(B12,municipios,regiao!$D$6:$D$150,0)} -> NÃO | I12: MARAJÓ | J12: D7 | K12: 35.73 | L12: =K12/(1-pconfig!$G$2-pconfig!$G$3-pconfig!$G$4) -> 67.466012 | M12: 519.17 | N12: =M12/(1-pconfig!$G$2-pconfig!$G$3-pconfig!$G$4) -> 980.30589 | O12: =((K12*F12)+M12)/(1-pconfig!$G$2-pconfig!$G$3-pconfig!$G$4) -> 1047.7719 | P12: =K12*F12/(1-pconfig!$G$2-pconfig!$G$3-pconfig!$G$4) -> 67.466012 | Q12: =IFS(F12<=pconfig!$B$12,P12*pconfig!$C$12,F12<=pconfig!$B$13,P12*pconfig!$C$13,F12<=pconfig!$B$14,P12*pconfig!$C$14,F12<=pconfig!$B$15,P12*pconfig!$C$15,F12<=pconfig!$B$16,P12*pconfig!$C$16,F12<=pconfig!$B$17,P12*pconfig!$C$17,F12<=pconfig!$B$18,P12*pconfig!$C$18,F12<=pconfig!$B$19,P12*pconfig!$C$19,F12<=pconfig!$B$20,P12*pconfig!$C$20,F12<=pconfig!$B$21,P12*pconfig!$C$21) -> 67.466012 | R12: =IF(Q12=0,P12+N12,Q12+N12) -> 1047.7719
A13: =A12+1 -> 12 | B13: AFUA | C13: SATELITE | D13: TELEBRAS | E13: =B13&C13 -> AFUASATELITE | F13: 1 | G13: MARAJÓ | H13: {=XLOOKUP(B13,municipios,regiao!$D$6:$D$150,0)} -> NÃO | I13: MARAJÓ | J13: - | K13: 4799 | L13: =K13/(1-pconfig!$G$2-pconfig!$G$3-pconfig!$G$4) -> 9061.5559 | M13: 519.17 | N13: =M13/(1-pconfig!$G$2-pconfig!$G$3-pconfig!$G$4) -> 980.30589 | O13: =((K13*F13)+M13)/(1-pconfig!$G$2-pconfig!$G$3-pconfig!$G$4) -> 10041.862 | P13: =K13*F13/(1-pconfig!$G$2-pconfig!$G$3-pconfig!$G$4) -> 9061.5559 | Q13: =IFS(F13<=pconfig!$B$12,P13*pconfig!$C$12,F13<=pconfig!$B$13,P13*pconfig!$C$13,F13<=pconfig!$B$14,P13*pconfig!$C$14,F13<=pconfig!$B$15,P13*pconfig!$C$15,F13<=pconfig!$B$16,P13*pconfig!$C$16,F13<=pconfig!$B$17,P13*pconfig!$C$17,F13<=pconfig!$B$18,P13*pconfig!$C$18,F13<=pconfig!$B$19,P13*pconfig!$C$19,F13<=pconfig!$B$20,P13*pconfig!$C$20,F13<=pconfig!$B$21,P13*pconfig!$C$21) -> 9061.5559 | R13: =IF(Q13=0,P13+N13,Q13+N13) -> 10041.862
A14: =A13+1 -> 13 | B14: AGUA AZUL DO NORTE | C14: RADIO | D14: ALVARION, CALIUM, AIRMUX | E14: =B14&C14 -> AGUA AZUL DO NORTERADIO | F14: 1 | G14: SUDESTE | H14: {=XLOOKUP(B14,municipios,regiao!$D$6:$D$150,0)} -> NÃO | I14: ARAGUAIA | J14: D6 | K14: 29.29 | L14: =K14/(1-pconfig!$G$2-pconfig!$G$3-pconfig!$G$4) -> 55.305891 | M14: 336.07417 | N14: =M14/(1-pconfig!$G$2-pconfig!$G$3-pconfig!$G$4) -> 634.58113 | O14: =((K14*F14)+M14)/(1-pconfig!$G$2-pconfig!$G$3-pconfig!$G$4) -> 689.88702 | P14: =K14*F14/(1-pconfig!$G$2-pconfig!$G$3-pconfig!$G$4) -> 55.305891 | Q14: =IFS(F14<=pconfig!$B$12,P14*pconfig!$C$12,F14<=pconfig!$B$13,P14*pconfig!$C$13,F14<=pconfig!$B$14,P14*pconfig!$C$14,F14<=pconfig!$B$15,P14*pconfig!$C$15,F14<=pconfig!$B$16,P14*pconfig!$C$16,F14<=pconfig!$B$17,P14*pconfig!$C$17,F14<=pconfig!$B$18,P14*pconfig!$C$18,F14<=pconfig!$B$19,P14*pconfig!$C$19,F14<=pconfig!$B$20,P14*pconfig!$C$20,F14<=pconfig!$B$21,P14*pconfig!$C$21) -> 55.305891 | R14: =IF(Q14=0,P14+N14,Q14+N14) -> 689.88702
A15: =A14+1 -> 14 | B15: AGUA AZUL DO NORTE | C15: FIBRA | D15: METRO, GPON | E15: =B15&C15 -> AGUA AZUL DO NORTEFIBRA | F15: 1 | G15: SUDESTE | H15: {=XLOOKUP(B15,municipios,regiao!$D$6:$D$150,0)} -> NÃO | I15: ARAGUAIA | J15: D6 | K15: 29.29 | L15: =K15/(1-pconfig!$G$2-pconfig!$G$3-pconfig!$G$4) -> 55.305891 | M15: 447.5 | N15: =M15/(1-pconfig!$G$2-pconfig!$G$3-pconfig!$G$4) -> 844.97734 | O15: =((K15*F15)+M15)/(1-pconfig!$G$2-pconfig!$G$3-pconfig!$G$4) -> 900.28323 | P15: =K15*F15/(1-pconfig!$G$2-pconfig!$G$3-pconfig!$G$4) -> 55.305891 | Q15: =IFS(F15<=pconfig!$B$12,P15*pconfig!$C$12,F15<=pconfig!$B$13,P15*pconfig!$C$13,F15<=pconfig!$B$14,P15*pconfig!$C$14,F15<=pconfig!$B$15,P15*pconfig!$C$15,F15<=pconfig!$B$16,P15*pconfig!$C$16,F15<=pconfig!$B$17,P15*pconfig!$C$17,F15<=pconfig!$B$18,P15*pconfig!$C$18,F15<=pconfig!$B$19,P15*pconfig!$C$19,F15<=pconfig!$B$20,P15*pconfig!$C$20,F15<=pconfig!$B$21,P15*pconfig!$C$21) -> 55.305891 | R15: =IF(Q15=0,P15+N15,Q15+N15) -> 900.28323
... A433: =A432+1 -> 432 | B433: XINGUARA | C433: SATELITE | D433: TELEBRAS | E433: =B433&C433 -> XINGUARASATELITE | F433: 1 | G433: SUDESTE | H433: {=XLOOKUP(B433,municipios,regiao!$D$6:$D$150,0)} -> SIM | I433: ARAGUAIA | J433: - | K433: 4799 | L433: =K433/(1-pconfig!$G$2-pconfig!$G$3-pconfig!$G$4) -> 9061.5559 | M433: 447.5 | N433: =M433/(1-pconfig!$G$2-pconfig!$G$3-pconfig!$G$4) -> 844.97734 | O433: =((K433*F433)+M433)/(1-pconfig!$G$2-pconfig!$G$3-pconfig!$G$4) -> 9906.5332 | P433: =K433*F433/(1-pconfig!$G$2-pconfig!$G$3-pconfig!$G$4) -> 9061.5559 | Q433: =IFS(F433<=pconfig!$B$12,P433*pconfig!$C$12,F433<=pconfig!$B$13,P433*pconfig!$C$13,F433<=pconfig!$B$14,P433*pconfig!$C$14,F433<=pconfig!$B$15,P433*pconfig!$C$15,F433<=pconfig!$B$16,P433*pconfig!$C$16,F433<=pconfig!$B$17,P433*pconfig!$C$17,F433<=pconfig!$B$18,P433*pconfig!$C$18,F433<=pconfig!$B$19,P433*pconfig!$C$19,F433<=pconfig!$B$20,P433*pconfig!$C$20,F433<=pconfig!$B$21,P433*pconfig!$C$21) -> 9061.5559 | R433: =IF(Q433=0,P433+N433,Q433+N433) -> 9906.5332

Sheet contatos
A1: =IFERROR(__xludf.DUMMYFUNCTION("IMPORTRANGE(""https://docs.google.com/spreadsheets/d/1fiSxYvppz5DsfdaqAWe6egd1vzr2a7h0sdUdR2hpq6w/edit?usp=sharing"",""Contatos!A:J"")"),"Id") -> Id | B1: =IFERROR(__xludf.DUMMYFUNCTION("""COMPUTED_VALUE"""),"CodUnico") -> CodUnico | C1: =IFERROR(__xludf.DUMMYFUNCTION("""COMPUTED_VALUE"""),"Sigla") -> Sigla | D1: =IFERROR(__xludf.DUMMYFUNCTION("""COMPUTED_VALUE"""),"Contato") -> Contato | E1: =IFERROR(__xludf.DUMMYFUNCTION("""COMPUTED_VALUE"""),"Cargo") -> Cargo | F1: =IFERROR(__xludf.DUMMYFUNCTION("""COMPUTED_VALUE"""),"Setor") -> Setor | G1: =IFERROR(__xludf.DUMMYFUNCTION("""COMPUTED_VALUE"""),"Telefone") -> Telefone | H1: =IFERROR(__xludf.DUMMYFUNCTION("""COMPUTED_VALUE"""),"Celular") -> Celular | I1: =IFERROR(__xludf.DUMMYFUNCTION("""COMPUTED_VALUE"""),"Email principal") -> Email principal | J1: =IFERROR(__xludf.DUMMYFUNCTION("""COMPUTED_VALUE"""),"Email secundario") -> Email secundario
B2: =IFERROR(__xludf.DUMMYFUNCTION("""COMPUTED_VALUE"""),"ADEPARÁ1") -> ADEPARÁ1 | C2: =IFERROR(__xludf.DUMMYFUNCTION("""COMPUTED_VALUE"""),"ADEPARÁ") -> ADEPARÁ | D2: =IFERROR(__xludf.DUMMYFUNCTION("""COMPUTED_VALUE"""),"Emerson Ribeiro da Silva") -> Emerson Ribeiro da Silva | F2: =IFERROR(__xludf.DUMMYFUNCTION("""COMPUTED_VALUE"""),"Gerência de Tecnologia da Informação - GTI") -> Gerência de Tecnologia da Informação - GTI | I2: =IFERROR(__xludf.DUMMYFUNCTION("""COMPUTED_VALUE"""),"gti@adepara.pa.gov.br") -> gti@adepara.pa.gov.br
B3: =IFERROR(__xludf.DUMMYFUNCTION("""COMPUTED_VALUE"""),"ADEPARÁ2") -> ADEPARÁ2 | C3: =IFERROR(__xludf.DUMMYFUNCTION("""COMPUTED_VALUE"""),"ADEPARÁ") -> ADEPARÁ | D3: =IFERROR(__xludf.DUMMYFUNCTION("""COMPUTED_VALUE"""),"Hugo ") -> Hugo | E3: =IFERROR(__xludf.DUMMYFUNCTION("""COMPUTED_VALUE"""),"Técnico/Analista") -> Técnico/Analista | F3: =IFERROR(__xludf.DUMMYFUNCTION("""COMPUTED_VALUE"""),"Gerência de Tecnologia da Informação - GTI") -> Gerência de Tecnologia da Informação - GTI | H3: =IFERROR(__xludf.DUMMYFUNCTION("""COMPUTED_VALUE"""),"(91) 9122-0441") -> (91) 9122-0441 | I3: =IFERROR(__xludf.DUMMYFUNCTION("""COMPUTED_VALUE"""),"inteligencia@adepara.pa.gov.br") -> inteligencia@adepara.pa.gov.br
B4: =IFERROR(__xludf.DUMMYFUNCTION("""COMPUTED_VALUE"""),"ADEPARÁ3") -> ADEPARÁ3 | C4: =IFERROR(__xludf.DUMMYFUNCTION("""COMPUTED_VALUE"""),"ADEPARÁ") -> ADEPARÁ | D4: =IFERROR(__xludf.DUMMYFUNCTION("""COMPUTED_VALUE"""),"Youssef") -> Youssef | E4: =IFERROR(__xludf.DUMMYFUNCTION("""COMPUTED_VALUE"""),"Desenvolvedor") -> Desenvolvedor | F4: =IFERROR(__xludf.DUMMYFUNCTION("""COMPUTED_VALUE"""),"Gerência de Tecnologia da Informação - GTI") -> Gerência de Tecnologia da Informação - GTI | G4: =IFERROR(__xludf.DUMMYFUNCTION("""COMPUTED_VALUE"""),"(351) 924 989 103") -> (351) 924 989 103 | I4: =IFERROR(__xludf.DUMMYFUNCTION("""COMPUTED_VALUE"""),"gti@adepara.pa.gov.br") -> gti@adepara.pa.gov.br
B5: =IFERROR(__xludf.DUMMYFUNCTION("""COMPUTED_VALUE"""),"ALEPA1") -> ALEPA1 | C5: =IFERROR(__xludf.DUMMYFUNCTION("""COMPUTED_VALUE"""),"ALEPA") -> ALEPA | D5: =IFERROR(__xludf.DUMMYFUNCTION("""COMPUTED_VALUE"""),"Ôrencio Junior") -> Ôrencio Junior | E5: =IFERROR(__xludf.DUMMYFUNCTION("""COMPUTED_VALUE"""),"Gerente de Rede ") -> Gerente de Rede | F5: =IFERROR(__xludf.DUMMYFUNCTION("""COMPUTED_VALUE"""),"T.I") -> T.I | H5: =IFERROR(__xludf.DUMMYFUNCTION("""COMPUTED_VALUE""")," 99114-6282 ") -> 99114-6282 | I5: =IFERROR(__xludf.DUMMYFUNCTION("""COMPUTED_VALUE"""),"orenciojunior@gmail.com") -> orenciojunior@gmail.com | J5: =IFERROR(__xludf.DUMMYFUNCTION("""COMPUTED_VALUE"""),"orencio@alepa.pa.gov.br") -> orencio@alepa.pa.gov.br
B6: =IFERROR(__xludf.DUMMYFUNCTION("""COMPUTED_VALUE"""),"ALEPA2") -> ALEPA2 | C6: =IFERROR(__xludf.DUMMYFUNCTION("""COMPUTED_VALUE"""),"ALEPA") -> ALEPA | D6: =IFERROR(__xludf.DUMMYFUNCTION("""COMPUTED_VALUE"""),"Danielly") -> Danielly | F6: =IFERROR(__xludf.DUMMYFUNCTION("""COMPUTED_VALUE"""),"Contabilidade") -> Contabilidade | G6: =IFERROR(__xludf.DUMMYFUNCTION("""COMPUTED_VALUE"""),"98159-2958 ") -> 98159-2958
B7: =IFERROR(__xludf.DUMMYFUNCTION("""COMPUTED_VALUE"""),"ALEPA3") -> ALEPA3 | C7: =IFERROR(__xludf.DUMMYFUNCTION("""COMPUTED_VALUE"""),"ALEPA") -> ALEPA | D7: =IFERROR(__xludf.DUMMYFUNCTION("""COMPUTED_VALUE"""),"Paulo André Ramalho") -> Paulo André Ramalho | E7: =IFERROR(__xludf.DUMMYFUNCTION("""COMPUTED_VALUE"""),"Analista de Suporte") -> Analista de Suporte
B8: =IFERROR(__xludf.DUMMYFUNCTION("""COMPUTED_VALUE"""),"ALEPA4") -> ALEPA4 | C8: =IFERROR(__xludf.DUMMYFUNCTION("""COMPUTED_VALUE"""),"ALEPA") -> ALEPA | D8: =IFERROR(__xludf.DUMMYFUNCTION("""COMPUTED_VALUE"""),"LICITAÇÃO") -> LICITAÇÃO | I8: =IFERROR(__xludf.DUMMYFUNCTION("""COMPUTED_VALUE"""),"licitacao@alepa.pa.gov.br") -> licitacao@alepa.pa.gov.br
B9: =IFERROR(__xludf.DUMMYFUNCTION("""COMPUTED_VALUE"""),"ARCON1") -> ARCON1 | C9: =IFERROR(__xludf.DUMMYFUNCTION("""COMPUTED_VALUE"""),"ARCON") -> ARCON
B10: =IFERROR(__xludf.DUMMYFUNCTION("""COMPUTED_VALUE"""),"ARTRAN1") -> ARTRAN1 | C10: =IFERROR(__xludf.DUMMYFUNCTION("""COMPUTED_VALUE"""),"ARTRAN") -> ARTRAN | D10: =IFERROR(__xludf.DUMMYFUNCTION("""COMPUTED_VALUE"""),"Leandro P. Pereira") -> Leandro P. Pereira | F10: =IFERROR(__xludf.DUMMYFUNCTION("""COMPUTED_VALUE"""),"Gerência de Tecnologia da Informação - GTI") -> Gerência de Tecnologia da Informação - GTI | H10: =IFERROR(__xludf.DUMMYFUNCTION("""COMPUTED_VALUE"""),"(91) 99147-9675") -> (91) 99147-9675 | I10: =IFERROR(__xludf.DUMMYFUNCTION("""COMPUTED_VALUE"""),"leandro.pereira@artran.pa.gov.br") -> leandro.pereira@artran.pa.gov.br
B11: =IFERROR(__xludf.DUMMYFUNCTION("""COMPUTED_VALUE"""),"ARTRAN2") -> ARTRAN2 | C11: =IFERROR(__xludf.DUMMYFUNCTION("""COMPUTED_VALUE"""),"ARTRAN") -> ARTRAN | D11: =IFERROR(__xludf.DUMMYFUNCTION("""COMPUTED_VALUE"""),"Simone Santos Linhares") -> Simone Santos Linhares | F11: =IFERROR(__xludf.DUMMYFUNCTION("""COMPUTED_VALUE"""),"Gerência de Contratos") -> Gerência de Contratos | I11: =IFERROR(__xludf.DUMMYFUNCTION("""COMPUTED_VALUE"""),"simone.linhares@artran.pa.gov.br") -> simone.linhares@artran.pa.gov.br
B12: =IFERROR(__xludf.DUMMYFUNCTION("""COMPUTED_VALUE"""),"BANPARÁ1") -> BANPARÁ1 | C12: =IFERROR(__xludf.DUMMYFUNCTION("""COMPUTED_VALUE"""),"BANPARÁ") -> BANPARÁ | D12: =IFERROR(__xludf.DUMMYFUNCTION("""COMPUTED_VALUE"""),"Raika Tessy Sousa Cavalcante Dourado") -> Raika Tessy Sousa Cavalcante Dourado | E12: =IFERROR(__xludf.DUMMYFUNCTION("""COMPUTED_VALUE"""),"Técnico de Atendimento em TI") -> Técnico de Atendimento em TI | F12: =IFERROR(__xludf.DUMMYFUNCTION("""COMPUTED_VALUE"""),"SUPRO / GETEL") -> SUPRO / GETEL | G12: =IFERROR(__xludf.DUMMYFUNCTION("""COMPUTED_VALUE"""),"(91) 3348-3029") -> (91) 3348-3029 | I12: =IFERROR(__xludf.DUMMYFUNCTION("""COMPUTED_VALUE"""),"rdourado@banparanet.com.br") -> rdourado@banparanet.com.br
B13: =IFERROR(__xludf.DUMMYFUNCTION("""COMPUTED_VALUE"""),"BANPARÁ2") -> BANPARÁ2 | C13: =IFERROR(__xludf.DUMMYFUNCTION("""COMPUTED_VALUE"""),"BANPARÁ") -> BANPARÁ | D13: =IFERROR(__xludf.DUMMYFUNCTION("""COMPUTED_VALUE"""),"Neldson") -> Neldson | F13: =IFERROR(__xludf.DUMMYFUNCTION("""COMPUTED_VALUE"""),"GETEL") -> GETEL | G13: =IFERROR(__xludf.DUMMYFUNCTION("""COMPUTED_VALUE"""),"(91) 3348-2980") -> (91) 3348-2980 | I13: =IFERROR(__xludf.DUMMYFUNCTION("""COMPUTED_VALUE"""),"njsilva@banparanet.com.br") -> njsilva@banparanet.com.br
B14: =IFERROR(__xludf.DUMMYFUNCTION("""COMPUTED_VALUE"""),"BANPARÁ3") -> BANPARÁ3 | C14: =IFERROR(__xludf.DUMMYFUNCTION("""COMPUTED_VALUE"""),"BANPARÁ") -> BANPARÁ | D14: =IFERROR(__xludf.DUMMYFUNCTION("""COMPUTED_VALUE"""),"Nery da Fonseca Barros") -> Nery da Fonseca Barros | E14: =IFERROR(__xludf.DUMMYFUNCTION("""COMPUTED_VALUE"""),"Técnico em atendimento de TI") -> Técnico em atendimento de TI | F14: =IFERROR(__xludf.DUMMYFUNCTION("""COMPUTED_VALUE"""),"GETEL") -> GETEL | G14: =IFERROR(__xludf.DUMMYFUNCTION("""COMPUTED_VALUE"""),"(91) 3348-3078") -> (91) 3348-3078
B15: =IFERROR(__xludf.DUMMYFUNCTION("""COMPUTED_VALUE"""),"BASA1") -> BASA1 | C15: =IFERROR(__xludf.DUMMYFUNCTION("""COMPUTED_VALUE"""),"BASA") -> BASA | D15: =IFERROR(__xludf.DUMMYFUNCTION("""COMPUTED_VALUE"""),"Aline do Socorro Furtado da Silva") -> Aline do Socorro Furtado da Silva | F15: =IFERROR(__xludf.DUMMYFUNCTION("""COMPUTED_VALUE"""),"Diretoria de Tecnologia - DITEC") -> Diretoria de Tecnologia - DITEC | I15: =IFERROR(__xludf.DUMMYFUNCTION("""COMPUTED_VALUE"""),"aline.silva@basa.com.br") -> aline.silva@basa.com.br
B16: =IFERROR(__xludf.DUMMYFUNCTION("""COMPUTED_VALUE"""),"CAPP1") -> CAPP1 | C16: =IFERROR(__xludf.DUMMYFUNCTION("""COMPUTED_VALUE"""),"CAPP") -> CAPP | D16: =IFERROR(__xludf.DUMMYFUNCTION("""COMPUTED_VALUE"""),"Wagner") -> Wagner | E16: =IFERROR(__xludf.DUMMYFUNCTION("""COMPUTED_VALUE"""),"Presidente") -> Presidente | F16: =IFERROR(__xludf.DUMMYFUNCTION("""COMPUTED_VALUE"""),"Presidência") -> Presidência | G16: =IFERROR(__xludf.DUMMYFUNCTION("""COMPUTED_VALUE"""),"(91) 3251-2790") -> (91) 3251-2790 | H16: =IFERROR(__xludf.DUMMYFUNCTION("""COMPUTED_VALUE"""),"(91) 98111-4567") -> (91) 98111-4567
B17: =IFERROR(__xludf.DUMMYFUNCTION("""COMPUTED_VALUE"""),"CBM1") -> CBM1 | C17: =IFERROR(__xludf.DUMMYFUNCTION("""COMPUTED_VALUE"""),"CBM") -> CBM | D17: =IFERROR(__xludf.DUMMYFUNCTION("""COMPUTED_VALUE"""),"Heron Araquem") -> Heron Araquem | H17: =IFERROR(__xludf.DUMMYFUNCTION("""COMPUTED_VALUE"""),"(91) 98168-1606") -> (91) 98168-1606 | I17: =IFERROR(__xludf.DUMMYFUNCTION("""COMPUTED_VALUE"""),"heron_icm@hotmail.com") -> heron_icm@hotmail.com
B18: =IFERROR(__xludf.DUMMYFUNCTION("""COMPUTED_VALUE"""),"CBM2") -> CBM2 | C18: =IFERROR(__xludf.DUMMYFUNCTION("""COMPUTED_VALUE"""),"CBM") -> CBM | D18: =IFERROR(__xludf.DUMMYFUNCTION("""COMPUTED_VALUE"""),"Matheus Renan Mendes dos Santos") -> Matheus Renan Mendes dos Santos | E18: =IFERROR(__xludf.DUMMYFUNCTION("""COMPUTED_VALUE"""),"Auxiliar na Seção de Contratos") -> Auxiliar na Seção de Contratos | F18: =IFERROR(__xludf.DUMMYFUNCTION("""COMPUTED_VALUE"""),"Diretoria de Apoio Logístico") -> Diretoria de Apoio Logístico | H18: =IFERROR(__xludf.DUMMYFUNCTION("""COMPUTED_VALUE"""),"(91) 98899-6316") -> (91) 98899-6316 | I18: =IFERROR(__xludf.DUMMYFUNCTION("""COMPUTED_VALUE"""),"contratoscbmpa@gmail.com") -> contratoscbmpa@gmail.com
B19: =IFERROR(__xludf.DUMMYFUNCTION("""COMPUTED_VALUE"""),"CBMP1") -> CBMP1 | C19: =IFERROR(__xludf.DUMMYFUNCTION("""COMPUTED_VALUE"""),"CBMP") -> CBMP | D19: =IFERROR(__xludf.DUMMYFUNCTION("""COMPUTED_VALUE"""),"Tenente Coronel Luiz Alfredo Silva Galiza Dos Santos") -> Tenente Coronel Luiz Alfredo Silva Galiza Dos Santos | E19: =IFERROR(__xludf.DUMMYFUNCTION("""COMPUTED_VALUE"""),"Diretor de Telemática e Estatística") -> Diretor de Telemática e Estatística | G19: =IFERROR(__xludf.DUMMYFUNCTION("""COMPUTED_VALUE""")," 4006-8396 ") -> 4006-8396 | I19: =IFERROR(__xludf.DUMMYFUNCTION("""COMPUTED_VALUE"""),"scmtgeral@gmail.com") -> scmtgeral@gmail.com
B20: =IFERROR(__xludf.DUMMYFUNCTION("""COMPUTED_VALUE"""),"CBMP2") -> CBMP2 | C20: =IFERROR(__xludf.DUMMYFUNCTION("""COMPUTED_VALUE"""),"CBMP") -> CBMP | D20: =IFERROR(__xludf.DUMMYFUNCTION("""COMPUTED_VALUE"""),"3º Sgto. Luiz Antônio Andrade de Sousa") -> 3º Sgto. Luiz Antônio Andrade de Sousa | G20: =IFERROR(__xludf.DUMMYFUNCTION("""COMPUTED_VALUE""")," 98482-3737") -> 98482-3737
B21: =IFERROR(__xludf.DUMMYFUNCTION("""COMPUTED_VALUE"""),"CBMP3") -> CBMP3 | C21: =IFERROR(__xludf.DUMMYFUNCTION("""COMPUTED_VALUE"""),"CBMP") -> CBMP | D21: =IFERROR(__xludf.DUMMYFUNCTION("""COMPUTED_VALUE"""),"Heron Araquém ( Sgto. Araquém)") -> Heron Araquém ( Sgto. Araquém) | F21: =IFERROR(__xludf.DUMMYFUNCTION("""COMPUTED_VALUE"""),"Fiscal De Contratos") -> Fiscal De Contratos | G21: =IFERROR(__xludf.DUMMYFUNCTION("""COMPUTED_VALUE"""),"98168-1606") -> 98168-1606 | I21: =IFERROR(__xludf.DUMMYFUNCTION("""COMPUTED_VALUE"""),"heron_icm@hotmail.com") -> heron_icm@hotmail.com
B22: =IFERROR(__xludf.DUMMYFUNCTION("""COMPUTED_VALUE"""),"CCG1") -> CCG1 | C22: =IFERROR(__xludf.DUMMYFUNCTION("""COMPUTED_VALUE"""),"CCG") -> CCG | D22: =IFERROR(__xludf.DUMMYFUNCTION("""COMPUTED_VALUE"""),"Matheus Tavares") -> Matheus Tavares | E22: =IFERROR(__xludf.DUMMYFUNCTION("""COMPUTED_VALUE"""),"Assessor") -> Assessor | F22: =IFERROR(__xludf.DUMMYFUNCTION("""COMPUTED_VALUE"""),"Coordenação de Licitação e Convênios - CLCC") -> Coordenação de Licitação e Convênios - CLCC | G22: =IFERROR(__xludf.DUMMYFUNCTION("""COMPUTED_VALUE"""),"(91) 3216-8860") -> (91) 3216-8860 | I22: =IFERROR(__xludf.DUMMYFUNCTION("""COMPUTED_VALUE"""),"matheus.tavares@palacio.pa.gov.br") -> matheus.tavares@palacio.pa.gov.br
B23: =IFERROR(__xludf.DUMMYFUNCTION("""COMPUTED_VALUE"""),"CCG2") -> CCG2 | C23: =IFERROR(__xludf.DUMMYFUNCTION("""COMPUTED_VALUE"""),"CCG") -> CCG | D23: =IFERROR(__xludf.DUMMYFUNCTION("""COMPUTED_VALUE"""),"Paulo Gomes") -> Paulo Gomes | F23: =IFERROR(__xludf.DUMMYFUNCTION("""COMPUTED_VALUE"""),"Diretoria de Tecnologia da Informação - DTI") -> Diretoria de Tecnologia da Informação - DTI | H23: =IFERROR(__xludf.DUMMYFUNCTION("""COMPUTED_VALUE"""),"(91) 98892-6261") -> (91) 98892-6261 | I23: =IFERROR(__xludf.DUMMYFUNCTION("""COMPUTED_VALUE"""),"dti@palacio.pa.gov.br") -> dti@palacio.pa.gov.br
B24: =IFERROR(__xludf.DUMMYFUNCTION("""COMPUTED_VALUE"""),"CCG3") -> CCG3 | C24: =IFERROR(__xludf.DUMMYFUNCTION("""COMPUTED_VALUE"""),"CCG") -> CCG | D24: =IFERROR(__xludf.DUMMYFUNCTION("""COMPUTED_VALUE"""),"Daniel Moraes") -> Daniel Moraes | E24: =IFERROR(__xludf.DUMMYFUNCTION("""COMPUTED_VALUE"""),"Coordenador") -> Coordenador | F24: =IFERROR(__xludf.DUMMYFUNCTION("""COMPUTED_VALUE"""),"Coordenação de Licitação, Contratos e Convênios - CLCC") -> Coordenação de Licitação, Contratos e Convênios - CLCC | G24: =IFERROR(__xludf.DUMMYFUNCTION("""COMPUTED_VALUE"""),"(91) 3216-8860") -> (91) 3216-8860 | H24: =IFERROR(__xludf.DUMMYFUNCTION("""COMPUTED_VALUE"""),"(91) 98209-4077") -> (91) 98209-4077 | I24: =IFERROR(__xludf.DUMMYFUNCTION("""COMPUTED_VALUE"""),"daniel.correa@palacio.pa.gov.br") -> daniel.correa@palacio.pa.gov.br | J24: =IFERROR(__xludf.DUMMYFUNCTION("""COMPUTED_VALUE"""),"licitacao@palacio.pa.gov.br") -> licitacao@palacio.pa.gov.br
B25: =IFERROR(__xludf.DUMMYFUNCTION("""COMPUTED_VALUE"""),"CCG4") -> CCG4 | C25: =IFERROR(__xludf.DUMMYFUNCTION("""COMPUTED_VALUE"""),"CCG") -> CCG
B26: =IFERROR(__xludf.DUMMYFUNCTION("""COMPUTED_VALUE"""),"CEASA1") -> CEASA1 | C26: =IFERROR(__xludf.DUMMYFUNCTION("""COMPUTED_VALUE"""),"CEASA") -> CEASA | D26: =IFERROR(__xludf.DUMMYFUNCTION("""COMPUTED_VALUE"""),"Leandro Ribeiro") -> Leandro Ribeiro | E26: =IFERROR(__xludf.DUMMYFUNCTION("""COMPUTED_VALUE"""),"Gerente De T.I") -> Gerente De T.I | G26: =IFERROR(__xludf.DUMMYFUNCTION("""COMPUTED_VALUE"""),"98182-8546") -> 98182-8546 | I26: =IFERROR(__xludf.DUMMYFUNCTION("""COMPUTED_VALUE"""),"leandro.ribeiro.ceasa@gmail.com") -> leandro.ribeiro.ceasa@gmail.com
B27: =IFERROR(__xludf.DUMMYFUNCTION("""COMPUTED_VALUE"""),"CEASA2") -> CEASA2 | C27: =IFERROR(__xludf.DUMMYFUNCTION("""COMPUTED_VALUE"""),"CEASA") -> CEASA | D27: =IFERROR(__xludf.DUMMYFUNCTION("""COMPUTED_VALUE"""),"Marcelo Pinto") -> Marcelo Pinto | G27: =IFERROR(__xludf.DUMMYFUNCTION("""COMPUTED_VALUE"""),"98397-4555") -> 98397-4555 | H27: =IFERROR(__xludf.DUMMYFUNCTION("""COMPUTED_VALUE"""),"3205-4032") -> 3205-4032 | I27: =IFERROR(__xludf.DUMMYFUNCTION("""COMPUTED_VALUE"""),"marcelo.tpinto@ceasa.pa.gov.br") -> marcelo.tpinto@ceasa.pa.gov.br
B28: =IFERROR(__xludf.DUMMYFUNCTION("""COMPUTED_VALUE"""),"CGE1") -> CGE1 | C28: =IFERROR(__xludf.DUMMYFUNCTION("""COMPUTED_VALUE"""),"CGE") -> CGE | D28: =IFERROR(__xludf.DUMMYFUNCTION("""COMPUTED_VALUE"""),"Roberto Carlos") -> Roberto Carlos | G28: =IFERROR(__xludf.DUMMYFUNCTION("""COMPUTED_VALUE"""),"(91) 3239-6461") -> (91) 3239-6461
B29: =IFERROR(__xludf.DUMMYFUNCTION("""COMPUTED_VALUE"""),"CGE2") -> CGE2 | C29: =IFERROR(__xludf.DUMMYFUNCTION("""COMPUTED_VALUE"""),"CGE") -> CGE | D29: =IFERROR(__xludf.DUMMYFUNCTION("""COMPUTED_VALUE"""),"Luis Claudio") -> Luis Claudio | G29: =IFERROR(__xludf.DUMMYFUNCTION("""COMPUTED_VALUE"""),"9 8265-1119 ") -> 9 8265-1119
B30: =IFERROR(__xludf.DUMMYFUNCTION("""COMPUTED_VALUE"""),"CGE3") -> CGE3 | C30: =IFERROR(__xludf.DUMMYFUNCTION("""COMPUTED_VALUE"""),"CGE") -> CGE | D30: =IFERROR(__xludf.DUMMYFUNCTION("""COMPUTED_VALUE"""),"Adriana ") -> Adriana | E30: =IFERROR(__xludf.DUMMYFUNCTION("""COMPUTED_VALUE"""),"Setor de Contrato") -> Setor de Contrato | G30: =IFERROR(__xludf.DUMMYFUNCTION("""COMPUTED_VALUE""")," 3239-6457") -> 3239-6457
B31: =IFERROR(__xludf.DUMMYFUNCTION("""COMPUTED_VALUE"""),"CINBESA1") -> CINBESA1 | C31: =IFERROR(__xludf.DUMMYFUNCTION("""COMPUTED_VALUE"""),"CINBESA") -> CINBESA | D31: =IFERROR(__xludf.DUMMYFUNCTION("""COMPUTED_VALUE"""),"Claudio Moraes") -> Claudio Moraes | H31: =IFERROR(__xludf.DUMMYFUNCTION("""COMPUTED_VALUE"""),"(91) 98113-6135") -> (91) 98113-6135 | I31: =IFERROR(__xludf.DUMMYFUNCTION("""COMPUTED_VALUE"""),"claudio.morais@cinbesa.pmb.pa.gov.br") -> claudio.morais@cinbesa.pmb.pa.gov.br
B32: =IFERROR(__xludf.DUMMYFUNCTION("""COMPUTED_VALUE"""),"CINBESA2") -> CINBESA2 | C32: =IFERROR(__xludf.DUMMYFUNCTION("""COMPUTED_VALUE"""),"CINBESA") -> CINBESA | D32: =IFERROR(__xludf.DUMMYFUNCTION("""COMPUTED_VALUE"""),"Paulo Brasil") -> Paulo Brasil | I32: =IFERROR(__xludf.DUMMYFUNCTION("""COMPUTED_VALUE"""),"paulo.brasil@cinbesa.com.br") -> paulo.brasil@cinbesa.com.br
B33: =IFERROR(__xludf.DUMMYFUNCTION("""COMPUTED_VALUE"""),"CM Anapú1") -> CM Anapú1 | C33: =IFERROR(__xludf.DUMMYFUNCTION("""COMPUTED_VALUE"""),"CM Anapú") -> CM Anapú | D33: =IFERROR(__xludf.DUMMYFUNCTION("""COMPUTED_VALUE"""),"Michele") -> Michele | H33: =IFERROR(__xludf.DUMMYFUNCTION("""COMPUTED_VALUE"""),"(93) 9 9111-7877") -> (93) 9 9111-7877 | I33: =IFERROR(__xludf.DUMMYFUNCTION("""COMPUTED_VALUE"""),"s.identificacaocma@gmail.com") -> s.identificacaocma@gmail.com
B34: =IFERROR(__xludf.DUMMYFUNCTION("""COMPUTED_VALUE"""),"CM Anapú2") -> CM Anapú2 | C34: =IFERROR(__xludf.DUMMYFUNCTION("""COMPUTED_VALUE"""),"CM Anapú") -> CM Anapú | D34: =IFERROR(__xludf.DUMMYFUNCTION("""COMPUTED_VALUE"""),"Krys") -> Krys | H34: =IFERROR(__xludf.DUMMYFUNCTION("""COMPUTED_VALUE"""),"(91) 9 8628-3861") -> (91) 9 8628-3861
B35: =IFERROR(__xludf.DUMMYFUNCTION("""COMPUTED_VALUE"""),"CM Barcarena1") -> CM Barcarena1 | C35: =IFERROR(__xludf.DUMMYFUNCTION("""COMPUTED_VALUE"""),"CM Barcarena") -> CM Barcarena | D35: =IFERROR(__xludf.DUMMYFUNCTION("""COMPUTED_VALUE"""),"Lucia Wanzeler") -> Lucia Wanzeler | G35: =IFERROR(__xludf.DUMMYFUNCTION("""COMPUTED_VALUE"""),"(91) 3753-3104") -> (91) 3753-3104 | H35: =IFERROR(__xludf.DUMMYFUNCTION("""COMPUTED_VALUE""")," (91) 9 8228-3317") -> (91) 9 8228-3317 | I35: =IFERROR(__xludf.DUMMYFUNCTION("""COMPUTED_VALUE"""),"lucia.wanzeler@gmail.com") -> lucia.wanzeler@gmail.com
B36: =IFERROR(__xludf.DUMMYFUNCTION("""COMPUTED_VALUE"""),"CM Barcarena2") -> CM Barcarena2 | C36: =IFERROR(__xludf.DUMMYFUNCTION("""COMPUTED_VALUE"""),"CM Barcarena") -> CM Barcarena | D36: =IFERROR(__xludf.DUMMYFUNCTION("""COMPUTED_VALUE""")," Flavia do S. M. Cunha") -> Flavia do S. M. Cunha | E36: =IFERROR(__xludf.DUMMYFUNCTION("""COMPUTED_VALUE"""),"Diretora-NACI/CMB") -> Diretora-NACI/CMB | F36: =IFERROR(__xludf.DUMMYFUNCTION("""COMPUTED_VALUE"""),"Núcle de Ass. ao Cidadão-NACI") -> Núcle de Ass. ao Cidadão-NACI | G36: =IFERROR(__xludf.DUMMYFUNCTION("""COMPUTED_VALUE"""),"(91) 3753-3102") -> (91) 3753-3102 | H36: =IFERROR(__xludf.DUMMYFUNCTION("""COMPUTED_VALUE""")," (91) 9 8584-4145") -> (91) 9 8584-4145 | I36: =IFERROR(__xludf.DUMMYFUNCTION("""COMPUTED_VALUE"""),"flaviamcunha77@gmail.com") -> flaviamcunha77@gmail.com
B37: =IFERROR(__xludf.DUMMYFUNCTION("""COMPUTED_VALUE"""),"CM Belém1") -> CM Belém1 | C37: =IFERROR(__xludf.DUMMYFUNCTION("""COMPUTED_VALUE"""),"CM Belém") -> CM Belém | D37: =IFERROR(__xludf.DUMMYFUNCTION("""COMPUTED_VALUE"""),"Rodimar Santos") -> Rodimar Santos | F37: =IFERROR(__xludf.DUMMYFUNCTION("""COMPUTED_VALUE"""),"DEAFIN") -> DEAFIN | I37: =IFERROR(__xludf.DUMMYFUNCTION("""COMPUTED_VALUE"""),"deafin@cmb.pa.gov.br") -> deafin@cmb.pa.gov.br
B38: =IFERROR(__xludf.DUMMYFUNCTION("""COMPUTED_VALUE"""),"CM Marituba1") -> CM Marituba1 | C38: =IFERROR(__xludf.DUMMYFUNCTION("""COMPUTED_VALUE"""),"CM Marituba") -> CM Marituba | D38: =IFERROR(__xludf.DUMMYFUNCTION("""COMPUTED_VALUE""")," Flávio Damasceno") -> Flávio Damasceno | E38: =IFERROR(__xludf.DUMMYFUNCTION("""COMPUTED_VALUE"""),"Coordenador") -> Coordenador | F38: =IFERROR(__xludf.DUMMYFUNCTION("""COMPUTED_VALUE"""),"Núcleo de Contratos") -> Núcleo de Contratos | G38: =IFERROR(__xludf.DUMMYFUNCTION("""COMPUTED_VALUE"""),"(91) 3256- 5667") -> (91) 3256- 5667 | I38: =IFERROR(__xludf.DUMMYFUNCTION("""COMPUTED_VALUE"""),"secretariageral@camaramarituba.pa.gov.br") -> secretariageral@camaramarituba.pa.gov.br
B39: =IFERROR(__xludf.DUMMYFUNCTION("""COMPUTED_VALUE"""),"CM Prainha1") -> CM Prainha1 | C39: =IFERROR(__xludf.DUMMYFUNCTION("""COMPUTED_VALUE"""),"CM Prainha") -> CM Prainha | D39: =IFERROR(__xludf.DUMMYFUNCTION("""COMPUTED_VALUE"""),"Andrea") -> Andrea | E39: =IFERROR(__xludf.DUMMYFUNCTION("""COMPUTED_VALUE"""),"Agente de contratação") -> Agente de contratação | G39: =IFERROR(__xludf.DUMMYFUNCTION("""COMPUTED_VALUE"""),"(93) 8435-0562") -> (93) 8435-0562 | I39: =IFERROR(__xludf.DUMMYFUNCTION("""COMPUTED_VALUE"""),"cmpprainha@gmail.com") -> cmpprainha@gmail.com | J39: =IFERROR(__xludf.DUMMYFUNCTION("""COMPUTED_VALUE"""),"licitacoes@camaradeprainha.pa.gov.br") -> licitacoes@camaradeprainha.pa.gov.br
B40: =IFERROR(__xludf.DUMMYFUNCTION("""COMPUTED_VALUE"""),"CODEC1") -> CODEC1 | C40: =IFERROR(__xludf.DUMMYFUNCTION("""COMPUTED_VALUE"""),"CODEC") -> CODEC | D40: =IFERROR(__xludf.DUMMYFUNCTION("""COMPUTED_VALUE"""),"Kleber Murat") -> Kleber Murat | E40: =IFERROR(__xludf.DUMMYFUNCTION("""COMPUTED_VALUE"""),"Gerente de Tecnologia da Informação") -> Gerente de Tecnologia da Informação | G40: =IFERROR(__xludf.DUMMYFUNCTION("""COMPUTED_VALUE"""),"(91) 3236-2884") -> (91) 3236-2884 | H40: =IFERROR(__xludf.DUMMYFUNCTION("""COMPUTED_VALUE"""),"9 8174-4302 ") -> 9 8174-4302 | I40: =IFERROR(__xludf.DUMMYFUNCTION("""COMPUTED_VALUE"""),"kleber.murat@codec.pa.gov.br") -> kleber.murat@codec.pa.gov.br
B41: =IFERROR(__xludf.DUMMYFUNCTION("""COMPUTED_VALUE"""),"COREN1") -> COREN1 | C41: =IFERROR(__xludf.DUMMYFUNCTION("""COMPUTED_VALUE"""),"COREN") -> COREN | D41: =IFERROR(__xludf.DUMMYFUNCTION("""COMPUTED_VALUE"""),"Adinaldo Vilhena Ferreira Junior") -> Adinaldo Vilhena Ferreira Junior | G41: =IFERROR(__xludf.DUMMYFUNCTION("""COMPUTED_VALUE"""),"(91) 3226-0740 / 3266-3618 ") -> (91) 3226-0740 / 3266-3618 | H41: =IFERROR(__xludf.DUMMYFUNCTION("""COMPUTED_VALUE"""),"98188-3326") -> 98188-3326 | I41: =IFERROR(__xludf.DUMMYFUNCTION("""COMPUTED_VALUE"""),"informatica@corenpa.org.br") -> informatica@corenpa.org.br | J41: =IFERROR(__xludf.DUMMYFUNCTION("""COMPUTED_VALUE"""),"coren.informatica@gmail.com") -> coren.informatica@gmail.com
B42: =IFERROR(__xludf.DUMMYFUNCTION("""COMPUTED_VALUE"""),"COSANPA1") -> COSANPA1 | C42: =IFERROR(__xludf.DUMMYFUNCTION("""COMPUTED_VALUE"""),"COSANPA") -> COSANPA | D42: =IFERROR(__xludf.DUMMYFUNCTION("""COMPUTED_VALUE"""),"Danielle Nunes") -> Danielle Nunes | H42: =IFERROR(__xludf.DUMMYFUNCTION("""COMPUTED_VALUE"""),"(91) 99881-7881") -> (91) 99881-7881 | I42: =IFERROR(__xludf.DUMMYFUNCTION("""COMPUTED_VALUE"""),"danielle.nunes@cosanpa.pa.gov.br") -> danielle.nunes@cosanpa.pa.gov.br
B43: =IFERROR(__xludf.DUMMYFUNCTION("""COMPUTED_VALUE"""),"COSANPA2") -> COSANPA2 | C43: =IFERROR(__xludf.DUMMYFUNCTION("""COMPUTED_VALUE"""),"COSANPA") -> COSANPA | D43: =IFERROR(__xludf.DUMMYFUNCTION("""COMPUTED_VALUE"""),"Márcia Costa") -> Márcia Costa | E43: =IFERROR(__xludf.DUMMYFUNCTION("""COMPUTED_VALUE"""),"Gerente de Suporte Tecnológico ") -> Gerente de Suporte Tecnológico | F43: =IFERROR(__xludf.DUMMYFUNCTION("""COMPUTED_VALUE"""),"UEST") -> UEST | G43: =IFERROR(__xludf.DUMMYFUNCTION("""COMPUTED_VALUE"""),"(91) 3251-7885") -> (91) 3251-7885 | H43: =IFERROR(__xludf.DUMMYFUNCTION("""COMPUTED_VALUE"""),"(91) 97638-5454") -> (91) 97638-5454 | I43: =IFERROR(__xludf.DUMMYFUNCTION("""COMPUTED_VALUE"""),"marcia.costa@cosanpa.pa.gov.br") -> marcia.costa@cosanpa.pa.gov.br
B44: =IFERROR(__xludf.DUMMYFUNCTION("""COMPUTED_VALUE"""),"COSANPA3") -> COSANPA3 | C44: =IFERROR(__xludf.DUMMYFUNCTION("""COMPUTED_VALUE"""),"COSANPA") -> COSANPA | F44: =IFERROR(__xludf.DUMMYFUNCTION("""COMPUTED_VALUE"""),"Contratos e Convênios") -> Contratos e Convênios | G44: =IFERROR(__xludf.DUMMYFUNCTION("""COMPUTED_VALUE"""),"(91) 3251-7888") -> (91) 3251-7888 | I44: =IFERROR(__xludf.DUMMYFUNCTION("""COMPUTED_VALUE"""),"cosanpa.contrato@gmail.com") -> cosanpa.contrato@gmail.com
B45: =IFERROR(__xludf.DUMMYFUNCTION("""COMPUTED_VALUE"""),"CPH1") -> CPH1 | C45: =IFERROR(__xludf.DUMMYFUNCTION("""COMPUTED_VALUE"""),"CPH") -> CPH | D45: =IFERROR(__xludf.DUMMYFUNCTION("""COMPUTED_VALUE"""),"Silvio S M Santos") -> Silvio S M Santos | F45: =IFERROR(__xludf.DUMMYFUNCTION("""COMPUTED_VALUE"""),"Núcleo de Contratos") -> Núcleo de Contratos | H45: =IFERROR(__xludf.DUMMYFUNCTION("""COMPUTED_VALUE"""),"(91) 98229-8904") -> (91) 98229-8904 | I45: =IFERROR(__xludf.DUMMYFUNCTION("""COMPUTED_VALUE"""),"silvio.santos@cph.pa.go.br") -> silvio.santos@cph.pa.go.br
B46: =IFERROR(__xludf.DUMMYFUNCTION("""COMPUTED_VALUE"""),"CPH2") -> CPH2 | C46: =IFERROR(__xludf.DUMMYFUNCTION("""COMPUTED_VALUE"""),"CPH") -> CPH | D46: =IFERROR(__xludf.DUMMYFUNCTION("""COMPUTED_VALUE"""),"Juliana Machado") -> Juliana Machado | E46: =IFERROR(__xludf.DUMMYFUNCTION("""COMPUTED_VALUE"""),"Gestora de TI") -> Gestora de TI | G46: =IFERROR(__xludf.DUMMYFUNCTION("""COMPUTED_VALUE"""),"3221-4100/4116/4122 (DIRETO) ") -> 3221-4100/4116/4122 (DIRETO) | I46: =IFERROR(__xludf.DUMMYFUNCTION("""COMPUTED_VALUE"""),"juliana.machado@cph.pa.gov.br") -> juliana.machado@cph.pa.gov.br
B47: =IFERROR(__xludf.DUMMYFUNCTION("""COMPUTED_VALUE"""),"DEFPUB1") -> DEFPUB1 | C47: =IFERROR(__xludf.DUMMYFUNCTION("""COMPUTED_VALUE"""),"DEFPUB") -> DEFPUB | D47: =IFERROR(__xludf.DUMMYFUNCTION("""COMPUTED_VALUE"""),"Levy André Damasceno Araújo") -> Levy André Damasceno Araújo | E47: =IFERROR(__xludf.DUMMYFUNCTION("""COMPUTED_VALUE"""),"Analista de redes / Fiscal do contrato") -> Analista de redes / Fiscal do contrato | H47: =IFERROR(__xludf.DUMMYFUNCTION("""COMPUTED_VALUE"""),"(91) 3251-3921") -> (91) 3251-3921 | I47: =IFERROR(__xludf.DUMMYFUNCTION("""COMPUTED_VALUE"""),"levy.araujo@defensoria.pa.def.br") -> levy.araujo@defensoria.pa.def.br
B48: =IFERROR(__xludf.DUMMYFUNCTION("""COMPUTED_VALUE"""),"DEFPUB2") -> DEFPUB2 | C48: =IFERROR(__xludf.DUMMYFUNCTION("""COMPUTED_VALUE"""),"DEFPUB") -> DEFPUB | D48: =IFERROR(__xludf.DUMMYFUNCTION("""COMPUTED_VALUE"""),"Natália Couto") -> Natália Couto | E48: =IFERROR(__xludf.DUMMYFUNCTION("""COMPUTED_VALUE"""),"Coordenadora") -> Coordenadora | F48: =IFERROR(__xludf.DUMMYFUNCTION("""COMPUTED_VALUE"""),"Núcleo de Tecnologia da Informação - NTI") -> Núcleo de Tecnologia da Informação - NTI | G48: =IFERROR(__xludf.DUMMYFUNCTION("""COMPUTED_VALUE"""),"(910 3217-2344") -> (910 3217-2344 | H48: =IFERROR(__xludf.DUMMYFUNCTION("""COMPUTED_VALUE"""),"(91) 98431-5969") -> (91) 98431-5969 | I48: =IFERROR(__xludf.DUMMYFUNCTION("""COMPUTED_VALUE"""),"coordenacao.nti@defensoria.pa.def.br") -> coordenacao.nti@defensoria.pa.def.br | J48: =IFERROR(__xludf.DUMMYFUNCTION("""COMPUTED_VALUE"""),"natalia.couto@defensoria.pa.def.br") -> natalia.couto@defensoria.pa.def.br
B49: =IFERROR(__xludf.DUMMYFUNCTION("""COMPUTED_VALUE"""),"DEFPUB3") -> DEFPUB3 | C49: =IFERROR(__xludf.DUMMYFUNCTION("""COMPUTED_VALUE"""),"DEFPUB") -> DEFPUB | D49: =IFERROR(__xludf.DUMMYFUNCTION("""COMPUTED_VALUE"""),"Dalton") -> Dalton | E49: =IFERROR(__xludf.DUMMYFUNCTION("""COMPUTED_VALUE"""),"Secretário") -> Secretário | F49: =IFERROR(__xludf.DUMMYFUNCTION("""COMPUTED_VALUE"""),"Coordenação de Licitação e Convênios - CLCC") -> Coordenação de Licitação e Convênios - CLCC | G49: =IFERROR(__xludf.DUMMYFUNCTION("""COMPUTED_VALUE"""),"(91) 3251-3715") -> (91) 3251-3715 | H49: =IFERROR(__xludf.DUMMYFUNCTION("""COMPUTED_VALUE"""),"(91) 97400-6058") -> (91) 97400-6058 | I49: =IFERROR(__xludf.DUMMYFUNCTION("""COMPUTED_VALUE"""),"licitacao@defensoria.pa.def.br") -> licitacao@defensoria.pa.def.br
B50: =IFERROR(__xludf.DUMMYFUNCTION("""COMPUTED_VALUE"""),"DEFPUB4") -> DEFPUB4 | C50: =IFERROR(__xludf.DUMMYFUNCTION("""COMPUTED_VALUE"""),"DEFPUB") -> DEFPUB | D50: =IFERROR(__xludf.DUMMYFUNCTION("""COMPUTED_VALUE"""),"Breno Abdon Julio") -> Breno Abdon Julio | E50: =IFERROR(__xludf.DUMMYFUNCTION("""COMPUTED_VALUE"""),"Coordenador de Operações de Tecnologia da Informação e Comunicação") -> Coordenador de Operações de Tecnologia da Informação e Comunicação | F50: =IFERROR(__xludf.DUMMYFUNCTION("""COMPUTED_VALUE"""),"DITEC") -> DITEC | G50: =IFERROR(__xludf.DUMMYFUNCTION("""COMPUTED_VALUE"""),"(91)3251-3931") -> (91)3251-3931 | I50: =IFERROR(__xludf.DUMMYFUNCTION("""COMPUTED_VALUE"""),"breno.julio@defensoria.pa.def.br") -> breno.julio@defensoria.pa.def.br
B51: =IFERROR(__xludf.DUMMYFUNCTION("""COMPUTED_VALUE"""),"DEFPUB5") -> DEFPUB5 | C51: =IFERROR(__xludf.DUMMYFUNCTION("""COMPUTED_VALUE"""),"DEFPUB") -> DEFPUB | D51: =IFERROR(__xludf.DUMMYFUNCTION("""COMPUTED_VALUE"""),"Samuel Junior") -> Samuel Junior | E51: =IFERROR(__xludf.DUMMYFUNCTION("""COMPUTED_VALUE"""),"Fiscal do contrato") -> Fiscal do contrato | H51: =IFERROR(__xludf.DUMMYFUNCTION("""COMPUTED_VALUE"""),"91 8290-6600") -> 91 8290-6600 | I51: =IFERROR(__xludf.DUMMYFUNCTION("""COMPUTED_VALUE"""),"samuel.junior@defensoria.pa.def.br") -> samuel.junior@defensoria.pa.def.br
B52: =IFERROR(__xludf.DUMMYFUNCTION("""COMPUTED_VALUE"""),"DEFPUB6") -> DEFPUB6 | C52: =IFERROR(__xludf.DUMMYFUNCTION("""COMPUTED_VALUE"""),"DEFPUB") -> DEFPUB | D52: =IFERROR(__xludf.DUMMYFUNCTION("""COMPUTED_VALUE"""),"Alan Demberguer Carneiro Maia") -> Alan Demberguer Carneiro Maia | E52: =IFERROR(__xludf.DUMMYFUNCTION("""COMPUTED_VALUE"""),"Analista de virtualização") -> Analista de virtualização | I52: =IFERROR(__xludf.DUMMYFUNCTION("""COMPUTED_VALUE"""),"alan.maia@ctctech.com.br") -> alan.maia@ctctech.com.br
B53: =IFERROR(__xludf.DUMMYFUNCTION("""COMPUTED_VALUE"""),"DESKCORP1") -> DESKCORP1 | C53: =IFERROR(__xludf.DUMMYFUNCTION("""COMPUTED_VALUE"""),"DESKCORP") -> DESKCORP | D53: =IFERROR(__xludf.DUMMYFUNCTION("""COMPUTED_VALUE"""),"Vatusy Simões") -> Vatusy Simões | E53: =IFERROR(__xludf.DUMMYFUNCTION("""COMPUTED_VALUE"""),"Analista de projetos") -> Analista de projetos | H53: =IFERROR(__xludf.DUMMYFUNCTION("""COMPUTED_VALUE"""),"(91) 98117-8114") -> (91) 98117-8114 | I53: =IFERROR(__xludf.DUMMYFUNCTION("""COMPUTED_VALUE"""),"vatusy.simoes@deskcorp.com.br") -> vatusy.simoes@deskcorp.com.br
B54: =IFERROR(__xludf.DUMMYFUNCTION("""COMPUTED_VALUE"""),"DETRAN1") -> DETRAN1 | C54: =IFERROR(__xludf.DUMMYFUNCTION("""COMPUTED_VALUE"""),"DETRAN") -> DETRAN | D54: =IFERROR(__xludf.DUMMYFUNCTION("""COMPUTED_VALUE"""),"Sérgio Oliveira") -> Sérgio Oliveira | E54: =IFERROR(__xludf.DUMMYFUNCTION("""COMPUTED_VALUE"""),"Gerente De Suporte Tecnológico") -> Gerente De Suporte Tecnológico | G54: =IFERROR(__xludf.DUMMYFUNCTION("""COMPUTED_VALUE"""),"99601-5463 ") -> 99601-5463 | I54: =IFERROR(__xludf.DUMMYFUNCTION("""COMPUTED_VALUE"""),"sergio.oliveira@detran.pa.gov.br") -> sergio.oliveira@detran.pa.gov.br
B55: =IFERROR(__xludf.DUMMYFUNCTION("""COMPUTED_VALUE"""),"DETRAN2") -> DETRAN2 | C55: =IFERROR(__xludf.DUMMYFUNCTION("""COMPUTED_VALUE"""),"DETRAN") -> DETRAN | D55: =IFERROR(__xludf.DUMMYFUNCTION("""COMPUTED_VALUE"""),"Marcio Oliveira") -> Marcio Oliveira | G55: =IFERROR(__xludf.DUMMYFUNCTION("""COMPUTED_VALUE""")," 3214-6391") -> 3214-6391 | I55: =IFERROR(__xludf.DUMMYFUNCTION("""COMPUTED_VALUE"""),"marcio.figueiredo@detran.pa.gov.br") -> marcio.figueiredo@detran.pa.gov.br
B56: =IFERROR(__xludf.DUMMYFUNCTION("""COMPUTED_VALUE"""),"DETRAN3") -> DETRAN3 | C56: =IFERROR(__xludf.DUMMYFUNCTION("""COMPUTED_VALUE"""),"DETRAN") -> DETRAN | D56: =IFERROR(__xludf.DUMMYFUNCTION("""COMPUTED_VALUE"""),"Patrick Fialho Vieitas") -> Patrick Fialho Vieitas | E56: =IFERROR(__xludf.DUMMYFUNCTION("""COMPUTED_VALUE"""),"Fiscal do Contrato nº 096/2022") -> Fiscal do Contrato nº 096/2022 | G56: =IFERROR(__xludf.DUMMYFUNCTION("""COMPUTED_VALUE""")," 3214-6349 ") -> 3214-6349 | H56: =IFERROR(__xludf.DUMMYFUNCTION("""COMPUTED_VALUE"""),"98153-3996") -> 98153-3996
B57: =IFERROR(__xludf.DUMMYFUNCTION("""COMPUTED_VALUE"""),"EGPA1") -> EGPA1 | C57: =IFERROR(__xludf.DUMMYFUNCTION("""COMPUTED_VALUE"""),"EGPA") -> EGPA | D57: =IFERROR(__xludf.DUMMYFUNCTION("""COMPUTED_VALUE"""),"Jefferson Vieira Siad") -> Jefferson Vieira Siad | E57: =IFERROR(__xludf.DUMMYFUNCTION("""COMPUTED_VALUE"""),"Fiscal do contrato") -> Fiscal do contrato | I57: =IFERROR(__xludf.DUMMYFUNCTION("""COMPUTED_VALUE"""),"jvsiade@gmail.com") -> jvsiade@gmail.com
B58: =IFERROR(__xludf.DUMMYFUNCTION("""COMPUTED_VALUE"""),"EGPA2") -> EGPA2 | C58: =IFERROR(__xludf.DUMMYFUNCTION("""COMPUTED_VALUE"""),"EGPA") -> EGPA | D58: =IFERROR(__xludf.DUMMYFUNCTION("""COMPUTED_VALUE"""),"Railson Borges Moura") -> Railson Borges Moura | H58: =IFERROR(__xludf.DUMMYFUNCTION("""COMPUTED_VALUE"""),"(91) 98965-7596") -> (91) 98965-7596 | I58: =IFERROR(__xludf.DUMMYFUNCTION("""COMPUTED_VALUE"""),"rbmoura32@gmail.com") -> rbmoura32@gmail.com
B59: =IFERROR(__xludf.DUMMYFUNCTION("""COMPUTED_VALUE"""),"EGPA3") -> EGPA3 | C59: =IFERROR(__xludf.DUMMYFUNCTION("""COMPUTED_VALUE"""),"EGPA") -> EGPA | D59: =IFERROR(__xludf.DUMMYFUNCTION("""COMPUTED_VALUE"""),"Andrey") -> Andrey | G59: =IFERROR(__xludf.DUMMYFUNCTION("""COMPUTED_VALUE"""),"(91) 3214-6822") -> (91) 3214-6822 | H59: =IFERROR(__xludf.DUMMYFUNCTION("""COMPUTED_VALUE"""),"(91) 99623-1033 / 98040-3240") -> (91) 99623-1033 / 98040-3240 | I59: =IFERROR(__xludf.DUMMYFUNCTION("""COMPUTED_VALUE"""),"egpa.compras@gmail.com") -> egpa.compras@gmail.com
B60: =IFERROR(__xludf.DUMMYFUNCTION("""COMPUTED_VALUE"""),"EMATER1") -> EMATER1 | C60: =IFERROR(__xludf.DUMMYFUNCTION("""COMPUTED_VALUE"""),"EMATER") -> EMATER | D60: =IFERROR(__xludf.DUMMYFUNCTION("""COMPUTED_VALUE"""),"Jorge Augusto Macedo de Souza") -> Jorge Augusto Macedo de Souza | E60: =IFERROR(__xludf.DUMMYFUNCTION("""COMPUTED_VALUE"""),"Coordenador") -> Coordenador | F60: =IFERROR(__xludf.DUMMYFUNCTION("""COMPUTED_VALUE"""),"Coordenação de Tecnologia da Informação e Comunicação - CTIC") -> Coordenação de Tecnologia da Informação e Comunicação - CTIC | G60: =IFERROR(__xludf.DUMMYFUNCTION("""COMPUTED_VALUE"""),"(91) 98494-0081") -> (91) 98494-0081 | H60: =IFERROR(__xludf.DUMMYFUNCTION("""COMPUTED_VALUE"""),"(91) 98143-3506") -> (91) 98143-3506 | I60: =IFERROR(__xludf.DUMMYFUNCTION("""COMPUTED_VALUE"""),"ctic@emater.pa.gov.br") -> ctic@emater.pa.gov.br
B61: =IFERROR(__xludf.DUMMYFUNCTION("""COMPUTED_VALUE"""),"EMATER2") -> EMATER2 | C61: =IFERROR(__xludf.DUMMYFUNCTION("""COMPUTED_VALUE"""),"EMATER") -> EMATER | D61: =IFERROR(__xludf.DUMMYFUNCTION("""COMPUTED_VALUE"""),"Laysa Sena") -> Laysa Sena | E61: =IFERROR(__xludf.DUMMYFUNCTION("""COMPUTED_VALUE"""),"Assessoria Jurídica") -> Assessoria Jurídica | F61: =IFERROR(__xludf.DUMMYFUNCTION("""COMPUTED_VALUE"""),"Assessoria Jurídica - AJUR") -> Assessoria Jurídica - AJUR | G61: =IFERROR(__xludf.DUMMYFUNCTION("""COMPUTED_VALUE"""),"(91) 3299-3468") -> (91) 3299-3468 | I61: =IFERROR(__xludf.DUMMYFUNCTION("""COMPUTED_VALUE"""),"ajur@emater.pa.gov.br") -> ajur@emater.pa.gov.br
B62: =IFERROR(__xludf.DUMMYFUNCTION("""COMPUTED_VALUE"""),"EMATER3") -> EMATER3 | C62: =IFERROR(__xludf.DUMMYFUNCTION("""COMPUTED_VALUE"""),"EMATER") -> EMATER | D62: =IFERROR(__xludf.DUMMYFUNCTION("""COMPUTED_VALUE"""),"Gleison Kiyoshi") -> Gleison Kiyoshi | F62: =IFERROR(__xludf.DUMMYFUNCTION("""COMPUTED_VALUE"""),"CTIC") -> CTIC | G62: =IFERROR(__xludf.DUMMYFUNCTION("""COMPUTED_VALUE"""),"(91) 3299-3451") -> (91) 3299-3451 | H62: =IFERROR(__xludf.DUMMYFUNCTION("""COMPUTED_VALUE"""),"(91) 98017-2027") -> (91) 98017-2027 | I62: =IFERROR(__xludf.DUMMYFUNCTION("""COMPUTED_VALUE"""),"gleison.kiyoshi@emater.pa.gov.br") -> gleison.kiyoshi@emater.pa.gov.br
B63: =IFERROR(__xludf.DUMMYFUNCTION("""COMPUTED_VALUE"""),"FAPESPA1") -> FAPESPA1 | C63: =IFERROR(__xludf.DUMMYFUNCTION("""COMPUTED_VALUE"""),"FAPESPA") -> FAPESPA | D63: =IFERROR(__xludf.DUMMYFUNCTION("""COMPUTED_VALUE"""),"Jessica Monteiro") -> Jessica Monteiro | E63: =IFERROR(__xludf.DUMMYFUNCTION("""COMPUTED_VALUE"""),"Coordenadora de TI") -> Coordenadora de TI | H63: =IFERROR(__xludf.DUMMYFUNCTION("""COMPUTED_VALUE"""),"(91) 98468-6152") -> (91) 98468-6152 | I63: =IFERROR(__xludf.DUMMYFUNCTION("""COMPUTED_VALUE"""),"jessica.monteiro@fapespa.pa.gov.br") -> jessica.monteiro@fapespa.pa.gov.br
B64: =IFERROR(__xludf.DUMMYFUNCTION("""COMPUTED_VALUE"""),"FASEPA1") -> FASEPA1 | C64: =IFERROR(__xludf.DUMMYFUNCTION("""COMPUTED_VALUE"""),"FASEPA") -> FASEPA | D64: =IFERROR(__xludf.DUMMYFUNCTION("""COMPUTED_VALUE"""),"Kildery Alexandre do Vale Costa") -> Kildery Alexandre do Vale Costa | E64: =IFERROR(__xludf.DUMMYFUNCTION("""COMPUTED_VALUE"""),"Técnico em Informática") -> Técnico em Informática | F64: =IFERROR(__xludf.DUMMYFUNCTION("""COMPUTED_VALUE"""),"NTIC") -> NTIC | G64: =IFERROR(__xludf.DUMMYFUNCTION("""COMPUTED_VALUE"""),"(91) 3210-3301") -> (91) 3210-3301 | H64: =IFERROR(__xludf.DUMMYFUNCTION("""COMPUTED_VALUE"""),"(91) 98825-5057") -> (91) 98825-5057 | I64: =IFERROR(__xludf.DUMMYFUNCTION("""COMPUTED_VALUE"""),"kilderydovale@gmail.com") -> kilderydovale@gmail.com
B65: =IFERROR(__xludf.DUMMYFUNCTION("""COMPUTED_VALUE"""),"FASPM1") -> FASPM1 | C65: =IFERROR(__xludf.DUMMYFUNCTION("""COMPUTED_VALUE"""),"FASPM") -> FASPM | D65: =IFERROR(__xludf.DUMMYFUNCTION("""COMPUTED_VALUE"""),"Marcos Barroso Leal ( sargento leal)") -> Marcos Barroso Leal ( sargento leal) | E65: =IFERROR(__xludf.DUMMYFUNCTION("""COMPUTED_VALUE"""),"Gerente De TI") -> Gerente De TI | G65: =IFERROR(__xludf.DUMMYFUNCTION("""COMPUTED_VALUE"""),"3259-6220 / 3038-3904 ") -> 3259-6220 / 3038-3904 | H65: =IFERROR(__xludf.DUMMYFUNCTION("""COMPUTED_VALUE"""),"98421-1070") -> 98421-1070 | I65: =IFERROR(__xludf.DUMMYFUNCTION("""COMPUTED_VALUE"""),"tecnologia@faspmpa.com.br") -> tecnologia@faspmpa.com.br | J65: =IFERROR(__xludf.DUMMYFUNCTION("""COMPUTED_VALUE"""),"contratos@faspm.com.br ") -> contratos@faspm.com.br
B66: =IFERROR(__xludf.DUMMYFUNCTION("""COMPUTED_VALUE"""),"FASPM2") -> FASPM2 | C66: =IFERROR(__xludf.DUMMYFUNCTION("""COMPUTED_VALUE"""),"FASPM") -> FASPM | D66: =IFERROR(__xludf.DUMMYFUNCTION("""COMPUTED_VALUE"""),"Valéria Vilar Garcia") -> Valéria Vilar Garcia | F66: =IFERROR(__xludf.DUMMYFUNCTION("""COMPUTED_VALUE"""),"Subseção de Contratos ") -> Subseção de Contratos | I66: =IFERROR(__xludf.DUMMYFUNCTION("""COMPUTED_VALUE"""),"cpl@faspmpa>com.br") -> cpl@faspmpa>com.br
B67: =IFERROR(__xludf.DUMMYFUNCTION("""COMPUTED_VALUE"""),"FCP1") -> FCP1 | C67: =IFERROR(__xludf.DUMMYFUNCTION("""COMPUTED_VALUE"""),"FCP") -> FCP | D67: =IFERROR(__xludf.DUMMYFUNCTION("""COMPUTED_VALUE"""),"Hugo Nascimento") -> Hugo Nascimento | E67: =IFERROR(__xludf.DUMMYFUNCTION("""COMPUTED_VALUE"""),"Fiscal de contratos") -> Fiscal de contratos | H67: =IFERROR(__xludf.DUMMYFUNCTION("""COMPUTED_VALUE"""),"(91)98499-3650") -> (91)98499-3650 | I67: =IFERROR(__xludf.DUMMYFUNCTION("""COMPUTED_VALUE"""),"hugo.nascimento@fcp.pa.gov.br") -> hugo.nascimento@fcp.pa.gov.br
B68: =IFERROR(__xludf.DUMMYFUNCTION("""COMPUTED_VALUE"""),"FCP2") -> FCP2 | C68: =IFERROR(__xludf.DUMMYFUNCTION("""COMPUTED_VALUE"""),"FCP") -> FCP | D68: =IFERROR(__xludf.DUMMYFUNCTION("""COMPUTED_VALUE"""),"Renato Freire") -> Renato Freire | H68: =IFERROR(__xludf.DUMMYFUNCTION("""COMPUTED_VALUE""")," 98499-3650 ") -> 98499-3650 | I68: =IFERROR(__xludf.DUMMYFUNCTION("""COMPUTED_VALUE"""),"renato.freire@fcp.pv.pa.gov.com.br") -> renato.freire@fcp.pv.pa.gov.com.br
B69: =IFERROR(__xludf.DUMMYFUNCTION("""COMPUTED_VALUE"""),"FCP3") -> FCP3 | C69: =IFERROR(__xludf.DUMMYFUNCTION("""COMPUTED_VALUE"""),"FCP") -> FCP | D69: =IFERROR(__xludf.DUMMYFUNCTION("""COMPUTED_VALUE"""),"Patricia Surubbi") -> Patricia Surubbi | G69: =IFERROR(__xludf.DUMMYFUNCTION("""COMPUTED_VALUE"""),"3202-4303 / 4376") -> 3202-4303 / 4376 | I69: =IFERROR(__xludf.DUMMYFUNCTION("""COMPUTED_VALUE"""),"patricia.sarubbi@fcp.pa.gov.br") -> patricia.sarubbi@fcp.pa.gov.br
B70: =IFERROR(__xludf.DUMMYFUNCTION("""COMPUTED_VALUE"""),"FHCGV1") -> FHCGV1 | C70: =IFERROR(__xludf.DUMMYFUNCTION("""COMPUTED_VALUE"""),"FHCGV") -> FHCGV | D70: =IFERROR(__xludf.DUMMYFUNCTION("""COMPUTED_VALUE"""),"Mayk Vianna") -> Mayk Vianna | F70: =IFERROR(__xludf.DUMMYFUNCTION("""COMPUTED_VALUE"""),"GTI") -> GTI | I70: =IFERROR(__xludf.DUMMYFUNCTION("""COMPUTED_VALUE"""),"mayk.viana@gasparvianna.pa.gov.br") -> mayk.viana@gasparvianna.pa.gov.br | J70: =IFERROR(__xludf.DUMMYFUNCTION("""COMPUTED_VALUE"""),"gti@gasparvianna.pa.gov.br") -> gti@gasparvianna.pa.gov.br
B71: =IFERROR(__xludf.DUMMYFUNCTION("""COMPUTED_VALUE"""),"FHCGV2") -> FHCGV2 | C71: =IFERROR(__xludf.DUMMYFUNCTION("""COMPUTED_VALUE"""),"FHCGV") -> FHCGV | D71: =IFERROR(__xludf.DUMMYFUNCTION("""COMPUTED_VALUE"""),"Cristiano Santos") -> Cristiano Santos | G71: =IFERROR(__xludf.DUMMYFUNCTION("""COMPUTED_VALUE"""),"(91) 4005-2781") -> (91) 4005-2781 | I71: =IFERROR(__xludf.DUMMYFUNCTION("""COMPUTED_VALUE"""),"cristiano.santos@gasparvianna.pa.gov.br") -> cristiano.santos@gasparvianna.pa.gov.br
B72: =IFERROR(__xludf.DUMMYFUNCTION("""COMPUTED_VALUE"""),"FMS PARAGOMINAS1") -> FMS PARAGOMINAS1 | C72: =IFERROR(__xludf.DUMMYFUNCTION("""COMPUTED_VALUE"""),"FMS PARAGOMINAS") -> FMS PARAGOMINAS | D72: =IFERROR(__xludf.DUMMYFUNCTION("""COMPUTED_VALUE"""),"Sérgio Bittencourt") -> Sérgio Bittencourt | H72: =IFERROR(__xludf.DUMMYFUNCTION("""COMPUTED_VALUE"""),"(91) 98200-1639") -> (91) 98200-1639 | I72: =IFERROR(__xludf.DUMMYFUNCTION("""COMPUTED_VALUE"""),"licitacao.setordecontratos@gmail.com") -> licitacao.setordecontratos@gmail.com | J72: =IFERROR(__xludf.DUMMYFUNCTION("""COMPUTED_VALUE"""),"s.bittencourt@hotmail.com") -> s.bittencourt@hotmail.com
B73: =IFERROR(__xludf.DUMMYFUNCTION("""COMPUTED_VALUE"""),"FSCMPA1") -> FSCMPA1 | C73: =IFERROR(__xludf.DUMMYFUNCTION("""COMPUTED_VALUE"""),"FSCMPA") -> FSCMPA | D73: =IFERROR(__xludf.DUMMYFUNCTION("""COMPUTED_VALUE"""),"Bruno Mendes Carmona") -> Bruno Mendes Carmona | E73: =IFERROR(__xludf.DUMMYFUNCTION("""COMPUTED_VALUE"""),"Presidente") -> Presidente | F73: =IFERROR(__xludf.DUMMYFUNCTION("""COMPUTED_VALUE"""),"Gerência de Contratos - GCOT") -> Gerência de Contratos - GCOT | G73: =IFERROR(__xludf.DUMMYFUNCTION("""COMPUTED_VALUE""")," (091) 3251-7430 / (91) 400-2241/2202/0329/2333") -> (091) 3251-7430 / (91) 400-2241/2202/0329/2333 | I73: =IFERROR(__xludf.DUMMYFUNCTION("""COMPUTED_VALUE"""),"contratos@santacasa.pa.gov.br") -> contratos@santacasa.pa.gov.br | J73: =IFERROR(__xludf.DUMMYFUNCTION("""COMPUTED_VALUE"""),"leide.silva@santacasa.pa.gov.br") -> leide.silva@santacasa.pa.gov.br
B74: =IFERROR(__xludf.DUMMYFUNCTION("""COMPUTED_VALUE"""),"FUNSAU1") -> FUNSAU1 | C74: =IFERROR(__xludf.DUMMYFUNCTION("""COMPUTED_VALUE"""),"FUNSAU") -> FUNSAU | D74: =IFERROR(__xludf.DUMMYFUNCTION("""COMPUTED_VALUE"""),"Cap. Haroldo ") -> Cap. Haroldo | E74: =IFERROR(__xludf.DUMMYFUNCTION("""COMPUTED_VALUE"""),"Gestor De Contratos ") -> Gestor De Contratos | H74: =IFERROR(__xludf.DUMMYFUNCTION("""COMPUTED_VALUE""")," 98315-2212 ") -> 98315-2212 | I74: =IFERROR(__xludf.DUMMYFUNCTION("""COMPUTED_VALUE"""),"pmpafunsau.contratos@gmail.com") -> pmpafunsau.contratos@gmail.com | J74: =IFERROR(__xludf.DUMMYFUNCTION("""COMPUTED_VALUE"""),"pmpafunsau@gmail.com ") -> pmpafunsau@gmail.com
B75: =IFERROR(__xludf.DUMMYFUNCTION("""COMPUTED_VALUE"""),"FUNSAU2") -> FUNSAU2 | C75: =IFERROR(__xludf.DUMMYFUNCTION("""COMPUTED_VALUE"""),"FUNSAU") -> FUNSAU | D75: =IFERROR(__xludf.DUMMYFUNCTION("""COMPUTED_VALUE""")," CB PM Álvaro") -> CB PM Álvaro | E75: =IFERROR(__xludf.DUMMYFUNCTION("""COMPUTED_VALUE"""),"Auxiliar da Seção de Planejamento de Compras") -> Auxiliar da Seção de Planejamento de Compras | H75: =IFERROR(__xludf.DUMMYFUNCTION("""COMPUTED_VALUE"""),"98584-6039") -> 98584-6039
B76: =IFERROR(__xludf.DUMMYFUNCTION("""COMPUTED_VALUE"""),"FUNTELPA1") -> FUNTELPA1 | C76: =IFERROR(__xludf.DUMMYFUNCTION("""COMPUTED_VALUE"""),"FUNTELPA") -> FUNTELPA | D76: =IFERROR(__xludf.DUMMYFUNCTION("""COMPUTED_VALUE"""),"Ingrid Sousa") -> Ingrid Sousa | F76: =IFERROR(__xludf.DUMMYFUNCTION("""COMPUTED_VALUE"""),"Recursos Humanos - RH") -> Recursos Humanos - RH | I76: =IFERROR(__xludf.DUMMYFUNCTION("""COMPUTED_VALUE"""),"ingridsousa@funtelpa.net") -> ingridsousa@funtelpa.net | J76: =IFERROR(__xludf.DUMMYFUNCTION("""COMPUTED_VALUE"""),"rh@funtelpa.com.br") -> rh@funtelpa.com.br
B77: =IFERROR(__xludf.DUMMYFUNCTION("""COMPUTED_VALUE"""),"FUNTELPA2") -> FUNTELPA2 | C77: =IFERROR(__xludf.DUMMYFUNCTION("""COMPUTED_VALUE"""),"FUNTELPA") -> FUNTELPA | D77: =IFERROR(__xludf.DUMMYFUNCTION("""COMPUTED_VALUE"""),"Larissa Diniz") -> Larissa Diniz | G77: =IFERROR(__xludf.DUMMYFUNCTION("""COMPUTED_VALUE"""),"(91) 4005-7725") -> (91) 4005-7725 | I77: =IFERROR(__xludf.DUMMYFUNCTION("""COMPUTED_VALUE"""),"larissadiniz@portalcultura.com.br") -> larissadiniz@portalcultura.com.br | J77: =IFERROR(__xludf.DUMMYFUNCTION("""COMPUTED_VALUE"""),"gabinete@funtelpa.com.br") -> gabinete@funtelpa.com.br
B78: =IFERROR(__xludf.DUMMYFUNCTION("""COMPUTED_VALUE"""),"GASPARÁ1") -> GASPARÁ1 | C78: =IFERROR(__xludf.DUMMYFUNCTION("""COMPUTED_VALUE"""),"GASPARÁ") -> GASPARÁ | D78: =IFERROR(__xludf.DUMMYFUNCTION("""COMPUTED_VALUE"""),"Charles William") -> Charles William | E78: =IFERROR(__xludf.DUMMYFUNCTION("""COMPUTED_VALUE"""),"Assistente de TI") -> Assistente de TI | H78: =IFERROR(__xludf.DUMMYFUNCTION("""COMPUTED_VALUE"""),"(91) 98592-1772") -> (91) 98592-1772 | I78: =IFERROR(__xludf.DUMMYFUNCTION("""COMPUTED_VALUE"""),"suporte@gasdopara.com.br") -> suporte@gasdopara.com.br
B79: =IFERROR(__xludf.DUMMYFUNCTION("""COMPUTED_VALUE"""),"GASPARÁ2") -> GASPARÁ2 | C79: =IFERROR(__xludf.DUMMYFUNCTION("""COMPUTED_VALUE"""),"GASPARÁ") -> GASPARÁ | D79: =IFERROR(__xludf.DUMMYFUNCTION("""COMPUTED_VALUE"""),"Jaime Isensee") -> Jaime Isensee | E79: =IFERROR(__xludf.DUMMYFUNCTION("""COMPUTED_VALUE"""),"Gerente Administrativo e Financeiro") -> Gerente Administrativo e Financeiro | H79: =IFERROR(__xludf.DUMMYFUNCTION("""COMPUTED_VALUE"""),"(71) 99737-1066") -> (71) 99737-1066 | I79: =IFERROR(__xludf.DUMMYFUNCTION("""COMPUTED_VALUE"""),"jaime.isensee@gasdopara.com.br") -> jaime.isensee@gasdopara.com.br
B80: =IFERROR(__xludf.DUMMYFUNCTION("""COMPUTED_VALUE"""),"HEMOPA1") -> HEMOPA1 | C80: =IFERROR(__xludf.DUMMYFUNCTION("""COMPUTED_VALUE"""),"HEMOPA") -> HEMOPA | D80: =IFERROR(__xludf.DUMMYFUNCTION("""COMPUTED_VALUE"""),"João Raiol") -> João Raiol | F80: =IFERROR(__xludf.DUMMYFUNCTION("""COMPUTED_VALUE"""),"Gerencia de Tecnologia da Informação - GETIN") -> Gerencia de Tecnologia da Informação - GETIN | G80: =IFERROR(__xludf.DUMMYFUNCTION("""COMPUTED_VALUE"""),"(91) 3110-6547") -> (91) 3110-6547 | I80: =IFERROR(__xludf.DUMMYFUNCTION("""COMPUTED_VALUE"""),"joao.raiol@hemopa.pa.gov.br") -> joao.raiol@hemopa.pa.gov.br
B81: =IFERROR(__xludf.DUMMYFUNCTION("""COMPUTED_VALUE"""),"HEMOPA2") -> HEMOPA2 | C81: =IFERROR(__xludf.DUMMYFUNCTION("""COMPUTED_VALUE"""),"HEMOPA") -> HEMOPA | D81: =IFERROR(__xludf.DUMMYFUNCTION("""COMPUTED_VALUE"""),"João Tadeu Cavalcante Junior") -> João Tadeu Cavalcante Junior | F81: =IFERROR(__xludf.DUMMYFUNCTION("""COMPUTED_VALUE"""),"Comissão de Licitação") -> Comissão de Licitação | I81: =IFERROR(__xludf.DUMMYFUNCTION("""COMPUTED_VALUE"""),"joao.tadeu@hemopa.pa.gov.br") -> joao.tadeu@hemopa.pa.gov.br | J81: =IFERROR(__xludf.DUMMYFUNCTION("""COMPUTED_VALUE"""),"licitacao@hemopa.pa.gov.br") -> licitacao@hemopa.pa.gov.br
B82: =IFERROR(__xludf.DUMMYFUNCTION("""COMPUTED_VALUE"""),"HEMOPA3") -> HEMOPA3 | C82: =IFERROR(__xludf.DUMMYFUNCTION("""COMPUTED_VALUE"""),"HEMOPA") -> HEMOPA | D82: =IFERROR(__xludf.DUMMYFUNCTION("""COMPUTED_VALUE"""),"Brenda Botelho Pinheiro") -> Brenda Botelho Pinheiro | F82: =IFERROR(__xludf.DUMMYFUNCTION("""COMPUTED_VALUE"""),"Assessoria Jurídica - AJUR") -> Assessoria Jurídica - AJUR | G82: =IFERROR(__xludf.DUMMYFUNCTION("""COMPUTED_VALUE"""),"(91) 3110-6503") -> (91) 3110-6503 | I82: =IFERROR(__xludf.DUMMYFUNCTION("""COMPUTED_VALUE"""),"brenda.pinheiro@hemopa.pa.gov.br") -> brenda.pinheiro@hemopa.pa.gov.br
B83: =IFERROR(__xludf.DUMMYFUNCTION("""COMPUTED_VALUE"""),"HOL1") -> HOL1 | C83: =IFERROR(__xludf.DUMMYFUNCTION("""COMPUTED_VALUE"""),"HOL") -> HOL | D83: =IFERROR(__xludf.DUMMYFUNCTION("""COMPUTED_VALUE"""),"Ione") -> Ione | G83: =IFERROR(__xludf.DUMMYFUNCTION("""COMPUTED_VALUE"""),"(91) 3265-6627") -> (91) 3265-6627
B84: =IFERROR(__xludf.DUMMYFUNCTION("""COMPUTED_VALUE"""),"HOL2") -> HOL2 | C84: =IFERROR(__xludf.DUMMYFUNCTION("""COMPUTED_VALUE"""),"HOL") -> HOL | D84: =IFERROR(__xludf.DUMMYFUNCTION("""COMPUTED_VALUE"""),"Gleiciane Bezerra") -> Gleiciane Bezerra | F84: =IFERROR(__xludf.DUMMYFUNCTION("""COMPUTED_VALUE"""),"Coordenação de Contratos") -> Coordenação de Contratos | G84: =IFERROR(__xludf.DUMMYFUNCTION("""COMPUTED_VALUE"""),"(91) 3265-6605") -> (91) 3265-6605 | I84: =IFERROR(__xludf.DUMMYFUNCTION("""COMPUTED_VALUE"""),"contratoshol@gmail.com") -> contratoshol@gmail.com
B85: =IFERROR(__xludf.DUMMYFUNCTION("""COMPUTED_VALUE"""),"HOL3") -> HOL3 | C85: =IFERROR(__xludf.DUMMYFUNCTION("""COMPUTED_VALUE"""),"HOL") -> HOL | D85: =IFERROR(__xludf.DUMMYFUNCTION("""COMPUTED_VALUE"""),"Diego Deleon Mendes Martins") -> Diego Deleon Mendes Martins | E85: =IFERROR(__xludf.DUMMYFUNCTION("""COMPUTED_VALUE"""),"Técnico em Gestão de Informática") -> Técnico em Gestão de Informática | F85: =IFERROR(__xludf.DUMMYFUNCTION("""COMPUTED_VALUE"""),"COORDENAÇÃO DE TI") -> COORDENAÇÃO DE TI | G85: =IFERROR(__xludf.DUMMYFUNCTION("""COMPUTED_VALUE"""),"(91) 99150-2202") -> (91) 99150-2202 | I85: =IFERROR(__xludf.DUMMYFUNCTION("""COMPUTED_VALUE"""),"informatica@ophirloyola.pa.gov.br") -> informatica@ophirloyola.pa.gov.br
B86: =IFERROR(__xludf.DUMMYFUNCTION("""COMPUTED_VALUE"""),"HOL4") -> HOL4 | C86: =IFERROR(__xludf.DUMMYFUNCTION("""COMPUTED_VALUE"""),"HOL") -> HOL | D86: =IFERROR(__xludf.DUMMYFUNCTION("""COMPUTED_VALUE"""),"Frederick Xabregas Pamplona") -> Frederick Xabregas Pamplona | E86: =IFERROR(__xludf.DUMMYFUNCTION("""COMPUTED_VALUE"""),"Coordenador da Tecnologia da Informação") -> Coordenador da Tecnologia da Informação | F86: =IFERROR(__xludf.DUMMYFUNCTION("""COMPUTED_VALUE"""),"COORDENAÇÃO DE TI") -> COORDENAÇÃO DE TI | G86: =IFERROR(__xludf.DUMMYFUNCTION("""COMPUTED_VALUE"""),"(91) 3265-6627") -> (91) 3265-6627 | I86: =IFERROR(__xludf.DUMMYFUNCTION("""COMPUTED_VALUE"""),"coordenacaoti@ophirloyola.pa.gov.br") -> coordenacaoti@ophirloyola.pa.gov.br
B87: =IFERROR(__xludf.DUMMYFUNCTION("""COMPUTED_VALUE"""),"IASEP1") -> IASEP1 | C87: =IFERROR(__xludf.DUMMYFUNCTION("""COMPUTED_VALUE"""),"IASEP") -> IASEP | D87: =IFERROR(__xludf.DUMMYFUNCTION("""COMPUTED_VALUE"""),"Benedito Rodrigues Bitencort Junior") -> Benedito Rodrigues Bitencort Junior | E87: =IFERROR(__xludf.DUMMYFUNCTION("""COMPUTED_VALUE"""),"Analista de Informática / Coordenador") -> Analista de Informática / Coordenador | F87: =IFERROR(__xludf.DUMMYFUNCTION("""COMPUTED_VALUE"""),"Núcleo de Tecnologia da Informação - NTI") -> Núcleo de Tecnologia da Informação - NTI | G87: =IFERROR(__xludf.DUMMYFUNCTION("""COMPUTED_VALUE"""),"(91) 98337-0600") -> (91) 98337-0600 | H87: =IFERROR(__xludf.DUMMYFUNCTION("""COMPUTED_VALUE"""),"(91) 98628-0219") -> (91) 98628-0219 | I87: =IFERROR(__xludf.DUMMYFUNCTION("""COMPUTED_VALUE"""),"benedito.junior@iasep.pa.gov.br") -> benedito.junior@iasep.pa.gov.br
B88: =IFERROR(__xludf.DUMMYFUNCTION("""COMPUTED_VALUE"""),"IASEP2") -> IASEP2 | C88: =IFERROR(__xludf.DUMMYFUNCTION("""COMPUTED_VALUE"""),"IASEP") -> IASEP | D88: =IFERROR(__xludf.DUMMYFUNCTION("""COMPUTED_VALUE"""),"Gilson Aurélio") -> Gilson Aurélio | E88: =IFERROR(__xludf.DUMMYFUNCTION("""COMPUTED_VALUE"""),"Gerente") -> Gerente | F88: =IFERROR(__xludf.DUMMYFUNCTION("""COMPUTED_VALUE"""),"Contratos") -> Contratos | I88: =IFERROR(__xludf.DUMMYFUNCTION("""COMPUTED_VALUE"""),"contrato@iasep.pa.gov.br") -> contrato@iasep.pa.gov.br
B89: =IFERROR(__xludf.DUMMYFUNCTION("""COMPUTED_VALUE"""),"IASEP3") -> IASEP3 | C89: =IFERROR(__xludf.DUMMYFUNCTION("""COMPUTED_VALUE"""),"IASEP") -> IASEP | D89: =IFERROR(__xludf.DUMMYFUNCTION("""COMPUTED_VALUE"""),"Leandro Lucas dos Santos") -> Leandro Lucas dos Santos | E89: =IFERROR(__xludf.DUMMYFUNCTION("""COMPUTED_VALUE"""),"Coordenador Administrativo") -> Coordenador Administrativo | F89: =IFERROR(__xludf.DUMMYFUNCTION("""COMPUTED_VALUE"""),"Gerência Administrativa de Serviços - GAS") -> Gerência Administrativa de Serviços - GAS | I89: =IFERROR(__xludf.DUMMYFUNCTION("""COMPUTED_VALUE"""),"iasep.gmp.gas@gmail.com") -> iasep.gmp.gas@gmail.com
B90: =IFERROR(__xludf.DUMMYFUNCTION("""COMPUTED_VALUE"""),"IDEFLOR1") -> IDEFLOR1 | C90: =IFERROR(__xludf.DUMMYFUNCTION("""COMPUTED_VALUE"""),"IDEFLOR") -> IDEFLOR | D90: =IFERROR(__xludf.DUMMYFUNCTION("""COMPUTED_VALUE"""),"Felipe SIlveira Brazão e Silva") -> Felipe SIlveira Brazão e Silva | E90: =IFERROR(__xludf.DUMMYFUNCTION("""COMPUTED_VALUE"""),"Coordenador") -> Coordenador | F90: =IFERROR(__xludf.DUMMYFUNCTION("""COMPUTED_VALUE"""),"Núcleo de Tecnologia") -> Núcleo de Tecnologia | H90: =IFERROR(__xludf.DUMMYFUNCTION("""COMPUTED_VALUE"""),"(91) 99290-5544") -> (91) 99290-5544 | I90: =IFERROR(__xludf.DUMMYFUNCTION("""COMPUTED_VALUE"""),"felipe.silva@ideflorbio.pa.gov.br") -> felipe.silva@ideflorbio.pa.gov.br
B91: =IFERROR(__xludf.DUMMYFUNCTION("""COMPUTED_VALUE"""),"IGEPPS1") -> IGEPPS1 | C91: =IFERROR(__xludf.DUMMYFUNCTION("""COMPUTED_VALUE"""),"IGEPPS") -> IGEPPS | D91: =IFERROR(__xludf.DUMMYFUNCTION("""COMPUTED_VALUE"""),"Alexandre Correa") -> Alexandre Correa | F91: =IFERROR(__xludf.DUMMYFUNCTION("""COMPUTED_VALUE"""),"Coordenação de Administração e Serviços - COAS") -> Coordenação de Administração e Serviços - COAS | I91: =IFERROR(__xludf.DUMMYFUNCTION("""COMPUTED_VALUE"""),"alexandre.correa@igepps.pa.gov.br") -> alexandre.correa@igepps.pa.gov.br
B92: =IFERROR(__xludf.DUMMYFUNCTION("""COMPUTED_VALUE"""),"IGEPPS2") -> IGEPPS2 | C92: =IFERROR(__xludf.DUMMYFUNCTION("""COMPUTED_VALUE"""),"IGEPPS") -> IGEPPS | D92: =IFERROR(__xludf.DUMMYFUNCTION("""COMPUTED_VALUE"""),"Glenda Leão") -> Glenda Leão | E92: =IFERROR(__xludf.DUMMYFUNCTION("""COMPUTED_VALUE"""),"Técnica de Administração e Finanças") -> Técnica de Administração e Finanças | F92: =IFERROR(__xludf.DUMMYFUNCTION("""COMPUTED_VALUE"""),"Coordenação de Administração e Serviços - COAS") -> Coordenação de Administração e Serviços - COAS | G92: =IFERROR(__xludf.DUMMYFUNCTION("""COMPUTED_VALUE"""),"(91) 3182-3506 / 3507") -> (91) 3182-3506 / 3507 | I92: =IFERROR(__xludf.DUMMYFUNCTION("""COMPUTED_VALUE"""),"glenda.leao@igepps.pa.gov.br") -> glenda.leao@igepps.pa.gov.br
B93: =IFERROR(__xludf.DUMMYFUNCTION("""COMPUTED_VALUE"""),"IGEPPS3") -> IGEPPS3 | C93: =IFERROR(__xludf.DUMMYFUNCTION("""COMPUTED_VALUE"""),"IGEPPS") -> IGEPPS | D93: =IFERROR(__xludf.DUMMYFUNCTION("""COMPUTED_VALUE"""),"Maria do Carmo M. M. Paiva") -> Maria do Carmo M. M. Paiva | E93: =IFERROR(__xludf.DUMMYFUNCTION("""COMPUTED_VALUE"""),"Secretária") -> Secretária | F93: =IFERROR(__xludf.DUMMYFUNCTION("""COMPUTED_VALUE"""),"Coordenação de Administração e Serviços - COAS") -> Coordenação de Administração e Serviços - COAS | G93: =IFERROR(__xludf.DUMMYFUNCTION("""COMPUTED_VALUE"""),"(91) 3182-3506 / 3507") -> (91) 3182-3506 / 3507 | H93: =IFERROR(__xludf.DUMMYFUNCTION("""COMPUTED_VALUE"""),"(91) 8050-0024") -> (91) 8050-0024 | I93: =IFERROR(__xludf.DUMMYFUNCTION("""COMPUTED_VALUE"""),"contratos@igeprev.pa.gov.br") -> contratos@igeprev.pa.gov.br
B94: =IFERROR(__xludf.DUMMYFUNCTION("""COMPUTED_VALUE"""),"IGEPPS4") -> IGEPPS4 | C94: =IFERROR(__xludf.DUMMYFUNCTION("""COMPUTED_VALUE"""),"IGEPPS") -> IGEPPS | D94: =IFERROR(__xludf.DUMMYFUNCTION("""COMPUTED_VALUE"""),"Ruth Monteiro Leão") -> Ruth Monteiro Leão | E94: =IFERROR(__xludf.DUMMYFUNCTION("""COMPUTED_VALUE"""),"Técnica de Administração e Finanças") -> Técnica de Administração e Finanças | F94: =IFERROR(__xludf.DUMMYFUNCTION("""COMPUTED_VALUE"""),"Coordenação de Administração e Serviços - COAS") -> Coordenação de Administração e Serviços - COAS | G94: =IFERROR(__xludf.DUMMYFUNCTION("""COMPUTED_VALUE"""),"(91) 3182-3506 / 3507") -> (91) 3182-3506 / 3507 | I94: =IFERROR(__xludf.DUMMYFUNCTION("""COMPUTED_VALUE"""),"ruth.leao@igepps.pa.gov.br") -> ruth.leao@igepps.pa.gov.br
B95: =IFERROR(__xludf.DUMMYFUNCTION("""COMPUTED_VALUE"""),"IGEPPS5") -> IGEPPS5 | C95: =IFERROR(__xludf.DUMMYFUNCTION("""COMPUTED_VALUE"""),"IGEPPS") -> IGEPPS | D95: =IFERROR(__xludf.DUMMYFUNCTION("""COMPUTED_VALUE"""),"Alexandre Marcos de Assis Nascimento") -> Alexandre Marcos de Assis Nascimento | E95: =IFERROR(__xludf.DUMMYFUNCTION("""COMPUTED_VALUE"""),"Analista de TI") -> Analista de TI | F95: =IFERROR(__xludf.DUMMYFUNCTION("""COMPUTED_VALUE"""),"CTIN") -> CTIN | G95: =IFERROR(__xludf.DUMMYFUNCTION("""COMPUTED_VALUE"""),"(91) 98135-5759") -> (91) 98135-5759 | I95: =IFERROR(__xludf.DUMMYFUNCTION("""COMPUTED_VALUE"""),"alx.marcoss@gmail.com") -> alx.marcoss@gmail.com
B96: =IFERROR(__xludf.DUMMYFUNCTION("""COMPUTED_VALUE"""),"ITERPA1") -> ITERPA1 | C96: =IFERROR(__xludf.DUMMYFUNCTION("""COMPUTED_VALUE"""),"ITERPA") -> ITERPA | D96: =IFERROR(__xludf.DUMMYFUNCTION("""COMPUTED_VALUE"""),"Larissa Baganha") -> Larissa Baganha | E96: =IFERROR(__xludf.DUMMYFUNCTION("""COMPUTED_VALUE"""),"Respónsavel NTI") -> Respónsavel NTI | G96: =IFERROR(__xludf.DUMMYFUNCTION("""COMPUTED_VALUE"""),"(91) 3181-6537") -> (91) 3181-6537 | I96: =IFERROR(__xludf.DUMMYFUNCTION("""COMPUTED_VALUE"""),"larissa.baganha@iterpa.pa.gov.br") -> larissa.baganha@iterpa.pa.gov.br
B97: =IFERROR(__xludf.DUMMYFUNCTION("""COMPUTED_VALUE"""),"ITERPA2") -> ITERPA2 | C97: =IFERROR(__xludf.DUMMYFUNCTION("""COMPUTED_VALUE"""),"ITERPA") -> ITERPA | D97: =IFERROR(__xludf.DUMMYFUNCTION("""COMPUTED_VALUE"""),"Potyguara Prazeres de Oliveira Ferreira ") -> Potyguara Prazeres de Oliveira Ferreira | E97: =IFERROR(__xludf.DUMMYFUNCTION("""COMPUTED_VALUE"""),"Respónsavel NTI") -> Respónsavel NTI | H97: =IFERROR(__xludf.DUMMYFUNCTION("""COMPUTED_VALUE"""),"(91) 99145-6205") -> (91) 99145-6205 | I97: =IFERROR(__xludf.DUMMYFUNCTION("""COMPUTED_VALUE"""),"potyguara.ferreira@iterpa.pa.gov.br") -> potyguara.ferreira@iterpa.pa.gov.br
B98: =IFERROR(__xludf.DUMMYFUNCTION("""COMPUTED_VALUE"""),"ITERPA3") -> ITERPA3 | C98: =IFERROR(__xludf.DUMMYFUNCTION("""COMPUTED_VALUE"""),"ITERPA") -> ITERPA | D98: =IFERROR(__xludf.DUMMYFUNCTION("""COMPUTED_VALUE"""),"Andreia Costa") -> Andreia Costa | E98: =IFERROR(__xludf.DUMMYFUNCTION("""COMPUTED_VALUE"""),"Coordenador") -> Coordenador | F98: =IFERROR(__xludf.DUMMYFUNCTION("""COMPUTED_VALUE"""),"Coordenadoria Administrativa - CA") -> Coordenadoria Administrativa - CA | H98: =IFERROR(__xludf.DUMMYFUNCTION("""COMPUTED_VALUE"""),"(91) 3284-9900") -> (91) 3284-9900 | I98: =IFERROR(__xludf.DUMMYFUNCTION("""COMPUTED_VALUE"""),"ca.iterpa@gmail.com") -> ca.iterpa@gmail.com
B99: =IFERROR(__xludf.DUMMYFUNCTION("""COMPUTED_VALUE"""),"JFPA1") -> JFPA1 | C99: =IFERROR(__xludf.DUMMYFUNCTION("""COMPUTED_VALUE"""),"JFPA") -> JFPA | D99: =IFERROR(__xludf.DUMMYFUNCTION("""COMPUTED_VALUE"""),"Sergio Sierro Leal") -> Sergio Sierro Leal | F99: =IFERROR(__xludf.DUMMYFUNCTION("""COMPUTED_VALUE"""),"Núcleo de Tecnologia - NUTEC") -> Núcleo de Tecnologia - NUTEC | G99: =IFERROR(__xludf.DUMMYFUNCTION("""COMPUTED_VALUE"""),"(91) 3299-6107") -> (91) 3299-6107 | I99: =IFERROR(__xludf.DUMMYFUNCTION("""COMPUTED_VALUE"""),"sergio.sierro@trf1.jus.br") -> sergio.sierro@trf1.jus.br
B100: =IFERROR(__xludf.DUMMYFUNCTION("""COMPUTED_VALUE"""),"JUCEPA3") -> JUCEPA3 | C100: =IFERROR(__xludf.DUMMYFUNCTION("""COMPUTED_VALUE"""),"JUCEPA") -> JUCEPA | D100: =IFERROR(__xludf.DUMMYFUNCTION("""COMPUTED_VALUE"""),"Karla Rego") -> Karla Rego | F100: =IFERROR(__xludf.DUMMYFUNCTION("""COMPUTED_VALUE"""),"Núcleo de Redes e Telecom - NRT ") -> Núcleo de Redes e Telecom - NRT | H100: =IFERROR(__xludf.DUMMYFUNCTION("""COMPUTED_VALUE"""),"(91) 9841-341") -> (91) 9841-341 | I100: =IFERROR(__xludf.DUMMYFUNCTION("""COMPUTED_VALUE"""),"nrt@jucepa.pa.gov.br") -> nrt@jucepa.pa.gov.br
...

Sheet municipios
A1: =IFERROR(__xludf.DUMMYFUNCTION("IMPORTRANGE(""https://docs.google.com/spreadsheets/d/1kIuUqm0AXYpUVVrwUFeIT9R0bdEhsTsg1_qUamlkdW8/edit?usp=sharing"",""municipios"")"),"MUNICÍPIO") -> MUNICÍPIO
A2: =IFERROR(__xludf.DUMMYFUNCTION("""COMPUTED_VALUE"""),"ABAETETUBA") -> ABAETETUBA
A3: =IFERROR(__xludf.DUMMYFUNCTION("""COMPUTED_VALUE"""),"ABEL FIGUEIREDO") -> ABEL FIGUEIREDO
A4: =IFERROR(__xludf.DUMMYFUNCTION("""COMPUTED_VALUE"""),"ACARA") -> ACARA
A5: =IFERROR(__xludf.DUMMYFUNCTION("""COMPUTED_VALUE"""),"AFUA") -> AFUA
A6: =IFERROR(__xludf.DUMMYFUNCTION("""COMPUTED_VALUE"""),"AGUA AZUL DO NORTE") -> AGUA AZUL DO NORTE
A7: =IFERROR(__xludf.DUMMYFUNCTION("""COMPUTED_VALUE"""),"ALENQUER") -> ALENQUER
A8: =IFERROR(__xludf.DUMMYFUNCTION("""COMPUTED_VALUE"""),"ALMEIRIM") -> ALMEIRIM
A9: =IFERROR(__xludf.DUMMYFUNCTION("""COMPUTED_VALUE"""),"ALTAMIRA") -> ALTAMIRA
A10: =IFERROR(__xludf.DUMMYFUNCTION("""COMPUTED_VALUE"""),"ANAJAS") -> ANAJAS
A11: =IFERROR(__xludf.DUMMYFUNCTION("""COMPUTED_VALUE"""),"ANANINDEUA") -> ANANINDEUA
A12: =IFERROR(__xludf.DUMMYFUNCTION("""COMPUTED_VALUE"""),"ANAPU") -> ANAPU
A13: =IFERROR(__xludf.DUMMYFUNCTION("""COMPUTED_VALUE"""),"AUGUSTO CORREA") -> AUGUSTO CORREA
A14: =IFERROR(__xludf.DUMMYFUNCTION("""COMPUTED_VALUE"""),"AURORA DO PARA") -> AURORA DO PARA
A15: =IFERROR(__xludf.DUMMYFUNCTION("""COMPUTED_VALUE"""),"AVEIRO") -> AVEIRO
A16: =IFERROR(__xludf.DUMMYFUNCTION("""COMPUTED_VALUE"""),"BAGRE") -> BAGRE
A17: =IFERROR(__xludf.DUMMYFUNCTION("""COMPUTED_VALUE"""),"BAIAO") -> BAIAO
A18: =IFERROR(__xludf.DUMMYFUNCTION("""COMPUTED_VALUE"""),"BANNACH") -> BANNACH
A19: =IFERROR(__xludf.DUMMYFUNCTION("""COMPUTED_VALUE"""),"BARCARENA") -> BARCARENA
A20: =IFERROR(__xludf.DUMMYFUNCTION("""COMPUTED_VALUE"""),"BELEM") -> BELEM
A21: =IFERROR(__xludf.DUMMYFUNCTION("""COMPUTED_VALUE"""),"BELTERRA") -> BELTERRA
A22: =IFERROR(__xludf.DUMMYFUNCTION("""COMPUTED_VALUE"""),"BENEVIDES") -> BENEVIDES
A23: =IFERROR(__xludf.DUMMYFUNCTION("""COMPUTED_VALUE"""),"BOM JESUS DO TOCANTINS") -> BOM JESUS DO TOCANTINS
A24: =IFERROR(__xludf.DUMMYFUNCTION("""COMPUTED_VALUE"""),"BONITO") -> BONITO
A25: =IFERROR(__xludf.DUMMYFUNCTION("""COMPUTED_VALUE"""),"BRAGANCA") -> BRAGANCA
A26: =IFERROR(__xludf.DUMMYFUNCTION("""COMPUTED_VALUE"""),"BRASIL NOVO") -> BRASIL NOVO
A27: =IFERROR(__xludf.DUMMYFUNCTION("""COMPUTED_VALUE"""),"BREJO GRANDE DO ARAGUAIA") -> BREJO GRANDE DO ARAGUAIA
A28: =IFERROR(__xludf.DUMMYFUNCTION("""COMPUTED_VALUE"""),"BREU BRANCO") -> BREU BRANCO
A29: =IFERROR(__xludf.DUMMYFUNCTION("""COMPUTED_VALUE"""),"BREVES") -> BREVES
A30: =IFERROR(__xludf.DUMMYFUNCTION("""COMPUTED_VALUE"""),"BUJARU") -> BUJARU
A31: =IFERROR(__xludf.DUMMYFUNCTION("""COMPUTED_VALUE"""),"CACHOEIRA DO ARARI") -> CACHOEIRA DO ARARI
A32: =IFERROR(__xludf.DUMMYFUNCTION("""COMPUTED_VALUE"""),"CACHOEIRA DO PIRIA") -> CACHOEIRA DO PIRIA
A33: =IFERROR(__xludf.DUMMYFUNCTION("""COMPUTED_VALUE"""),"CAMETA") -> CAMETA
A34: =IFERROR(__xludf.DUMMYFUNCTION("""COMPUTED_VALUE"""),"CANAA DOS CARAJAS") -> CANAA DOS CARAJAS
A35: =IFERROR(__xludf.DUMMYFUNCTION("""COMPUTED_VALUE"""),"CAPANEMA") -> CAPANEMA
A36: =IFERROR(__xludf.DUMMYFUNCTION("""COMPUTED_VALUE"""),"CAPITAO POCO") -> CAPITAO POCO
A37: =IFERROR(__xludf.DUMMYFUNCTION("""COMPUTED_VALUE"""),"CASTANHAL") -> CASTANHAL
A38: =IFERROR(__xludf.DUMMYFUNCTION("""COMPUTED_VALUE"""),"CHAVES") -> CHAVES
A39: =IFERROR(__xludf.DUMMYFUNCTION("""COMPUTED_VALUE"""),"COLARES") -> COLARES
A40: =IFERROR(__xludf.DUMMYFUNCTION("""COMPUTED_VALUE"""),"CONCEICAO DO ARAGUAIA") -> CONCEICAO DO ARAGUAIA
A41: =IFERROR(__xludf.DUMMYFUNCTION("""COMPUTED_VALUE"""),"CONCORDIA DO PARA") -> CONCORDIA DO PARA
A42: =IFERROR(__xludf.DUMMYFUNCTION("""COMPUTED_VALUE"""),"CUMARU DO NORTE") -> CUMARU DO NORTE
A43: =IFERROR(__xludf.DUMMYFUNCTION("""COMPUTED_VALUE"""),"CURIONOPOLIS") -> CURIONOPOLIS
A44: =IFERROR(__xludf.DUMMYFUNCTION("""COMPUTED_VALUE"""),"CURRALINHO") -> CURRALINHO
A45: =IFERROR(__xludf.DUMMYFUNCTION("""COMPUTED_VALUE"""),"CURUA") -> CURUA
A46: =IFERROR(__xludf.DUMMYFUNCTION("""COMPUTED_VALUE"""),"CURUCA") -> CURUCA
A47: =IFERROR(__xludf.DUMMYFUNCTION("""COMPUTED_VALUE"""),"DOM ELISEU") -> DOM ELISEU
A48: =IFERROR(__xludf.DUMMYFUNCTION("""COMPUTED_VALUE"""),"ELDORADO DOS CARAJAS") -> ELDORADO DOS CARAJAS
A49: =IFERROR(__xludf.DUMMYFUNCTION("""COMPUTED_VALUE"""),"FARO") -> FARO
A50: =IFERROR(__xludf.DUMMYFUNCTION("""COMPUTED_VALUE"""),"FLORESTA DO ARAGUAIA") -> FLORESTA DO ARAGUAIA
A51: =IFERROR(__xludf.DUMMYFUNCTION("""COMPUTED_VALUE"""),"GARRAFAO DO NORTE") -> GARRAFAO DO NORTE
A52: =IFERROR(__xludf.DUMMYFUNCTION("""COMPUTED_VALUE"""),"GOIANESIA DO PARA") -> GOIANESIA DO PARA
A53: =IFERROR(__xludf.DUMMYFUNCTION("""COMPUTED_VALUE"""),"GURUPA") -> GURUPA
A54: =IFERROR(__xludf.DUMMYFUNCTION("""COMPUTED_VALUE"""),"IGARAPE-ACU") -> IGARAPE-ACU
A55: =IFERROR(__xludf.DUMMYFUNCTION("""COMPUTED_VALUE"""),"IGARAPE-MIRI") -> IGARAPE-MIRI
A56: =IFERROR(__xludf.DUMMYFUNCTION("""COMPUTED_VALUE"""),"INHANGAPI") -> INHANGAPI
A57: =IFERROR(__xludf.DUMMYFUNCTION("""COMPUTED_VALUE"""),"IPIXUNA DO PARA") -> IPIXUNA DO PARA
A58: =IFERROR(__xludf.DUMMYFUNCTION("""COMPUTED_VALUE"""),"IRITUIA") -> IRITUIA
A59: =IFERROR(__xludf.DUMMYFUNCTION("""COMPUTED_VALUE"""),"ITAITUBA") -> ITAITUBA
A60: =IFERROR(__xludf.DUMMYFUNCTION("""COMPUTED_VALUE"""),"ITUPIRANGA") -> ITUPIRANGA
A61: =IFERROR(__xludf.DUMMYFUNCTION("""COMPUTED_VALUE"""),"JACAREACANGA") -> JACAREACANGA
A62: =IFERROR(__xludf.DUMMYFUNCTION("""COMPUTED_VALUE"""),"JACUNDA") -> JACUNDA
A63: =IFERROR(__xludf.DUMMYFUNCTION("""COMPUTED_VALUE"""),"JURUTI") -> JURUTI
A64: =IFERROR(__xludf.DUMMYFUNCTION("""COMPUTED_VALUE"""),"LIMOEIRO DO AJURU") -> LIMOEIRO DO AJURU
A65: =IFERROR(__xludf.DUMMYFUNCTION("""COMPUTED_VALUE"""),"MAE DO RIO") -> MAE DO RIO
A66: =IFERROR(__xludf.DUMMYFUNCTION("""COMPUTED_VALUE"""),"MAGALHAES BARATA") -> MAGALHAES BARATA
A67: =IFERROR(__xludf.DUMMYFUNCTION("""COMPUTED_VALUE"""),"MARABA") -> MARABA
A68: =IFERROR(__xludf.DUMMYFUNCTION("""COMPUTED_VALUE"""),"MARACANA") -> MARACANA
A69: =IFERROR(__xludf.DUMMYFUNCTION("""COMPUTED_VALUE"""),"MARAPANIM") -> MARAPANIM
A70: =IFERROR(__xludf.DUMMYFUNCTION("""COMPUTED_VALUE"""),"MARITUBA") -> MARITUBA
A71: =IFERROR(__xludf.DUMMYFUNCTION("""COMPUTED_VALUE"""),"MEDICILANDIA") -> MEDICILANDIA
A72: =IFERROR(__xludf.DUMMYFUNCTION("""COMPUTED_VALUE"""),"MELGACO") -> MELGACO
A73: =IFERROR(__xludf.DUMMYFUNCTION("""COMPUTED_VALUE"""),"MOCAJUBA") -> MOCAJUBA
A74: =IFERROR(__xludf.DUMMYFUNCTION("""COMPUTED_VALUE"""),"MOJU") -> MOJU
A75: =IFERROR(__xludf.DUMMYFUNCTION("""COMPUTED_VALUE"""),"MOJUI DOS CAMPOS") -> MOJUI DOS CAMPOS
A76: =IFERROR(__xludf.DUMMYFUNCTION("""COMPUTED_VALUE"""),"MONTE ALEGRE") -> MONTE ALEGRE
A77: =IFERROR(__xludf.DUMMYFUNCTION("""COMPUTED_VALUE"""),"MUANA") -> MUANA
A78: =IFERROR(__xludf.DUMMYFUNCTION("""COMPUTED_VALUE"""),"NOVA ESPERANCA DO PIRIA") -> NOVA ESPERANCA DO PIRIA
A79: =IFERROR(__xludf.DUMMYFUNCTION("""COMPUTED_VALUE"""),"NOVA IPIXUNA") -> NOVA IPIXUNA
A80: =IFERROR(__xludf.DUMMYFUNCTION("""COMPUTED_VALUE"""),"NOVA TIMBOTEUA") -> NOVA TIMBOTEUA
A81: =IFERROR(__xludf.DUMMYFUNCTION("""COMPUTED_VALUE"""),"NOVO PROGRESSO") -> NOVO PROGRESSO
A82: =IFERROR(__xludf.DUMMYFUNCTION("""COMPUTED_VALUE"""),"NOVO REPARTIMENTO") -> NOVO REPARTIMENTO
A83: =IFERROR(__xludf.DUMMYFUNCTION("""COMPUTED_VALUE"""),"OBIDOS") -> OBIDOS
A84: =IFERROR(__xludf.DUMMYFUNCTION("""COMPUTED_VALUE"""),"OEIRAS DO PARA") -> OEIRAS DO PARA
A85: =IFERROR(__xludf.DUMMYFUNCTION("""COMPUTED_VALUE"""),"ORIXIMINA") -> ORIXIMINA
A86: =IFERROR(__xludf.DUMMYFUNCTION("""COMPUTED_VALUE"""),"OUREM") -> OUREM
A87: =IFERROR(__xludf.DUMMYFUNCTION("""COMPUTED_VALUE"""),"OURILANDIA DO NORTE") -> OURILANDIA DO NORTE
A88: =IFERROR(__xludf.DUMMYFUNCTION("""COMPUTED_VALUE"""),"PACAJA") -> PACAJA
A89: =IFERROR(__xludf.DUMMYFUNCTION("""COMPUTED_VALUE"""),"PALESTINA DO PARA") -> PALESTINA DO PARA
A90: =IFERROR(__xludf.DUMMYFUNCTION("""COMPUTED_VALUE"""),"PARAGOMINAS") -> PARAGOMINAS
A91: =IFERROR(__xludf.DUMMYFUNCTION("""COMPUTED_VALUE"""),"PARAUAPEBAS") -> PARAUAPEBAS
A92: =IFERROR(__xludf.DUMMYFUNCTION("""COMPUTED_VALUE"""),"PAU DARCO") -> PAU DARCO
A93: =IFERROR(__xludf.DUMMYFUNCTION("""COMPUTED_VALUE"""),"PEIXE-BOI") -> PEIXE-BOI
A94: =IFERROR(__xludf.DUMMYFUNCTION("""COMPUTED_VALUE"""),"PICARRA") -> PICARRA
A95: =IFERROR(__xludf.DUMMYFUNCTION("""COMPUTED_VALUE"""),"PLACAS") -> PLACAS
A96: =IFERROR(__xludf.DUMMYFUNCTION("""COMPUTED_VALUE"""),"PONTA DE PEDRAS") -> PONTA DE PEDRAS
A97: =IFERROR(__xludf.DUMMYFUNCTION("""COMPUTED_VALUE"""),"PORTEL") -> PORTEL
A98: =IFERROR(__xludf.DUMMYFUNCTION("""COMPUTED_VALUE"""),"PORTO DE MOZ") -> PORTO DE MOZ
A99: =IFERROR(__xludf.DUMMYFUNCTION("""COMPUTED_VALUE"""),"PRAINHA") -> PRAINHA
A100: =IFERROR(__xludf.DUMMYFUNCTION("""COMPUTED_VALUE"""),"PRIMAVERA") -> PRIMAVERA
...

Sheet clientes
A1: =IFERROR(__xludf.DUMMYFUNCTION("IMPORTRANGE(""https://docs.google.com/spreadsheets/d/1fiSxYvppz5DsfdaqAWe6egd1vzr2a7h0sdUdR2hpq6w/edit?usp=sharing"",""Cliente!B:M"")"),"Sigla") -> Sigla | B1: =IFERROR(__xludf.DUMMYFUNCTION("""COMPUTED_VALUE"""),"Instituição") -> Instituição | C1: =IFERROR(__xludf.DUMMYFUNCTION("""COMPUTED_VALUE"""),"Esfera") -> Esfera | D1: =IFERROR(__xludf.DUMMYFUNCTION("""COMPUTED_VALUE"""),"CNPJ") -> CNPJ | E1: =IFERROR(__xludf.DUMMYFUNCTION("""COMPUTED_VALUE"""),"Representante") -> Representante | F1: =IFERROR(__xludf.DUMMYFUNCTION("""COMPUTED_VALUE"""),"Cargo do representante") -> Cargo do representante | G1: =IFERROR(__xludf.DUMMYFUNCTION("""COMPUTED_VALUE"""),"Telefone-Sede") -> Telefone-Sede | H1: =IFERROR(__xludf.DUMMYFUNCTION("""COMPUTED_VALUE"""),"Endereço - Sede") -> Endereço - Sede | I1: =IFERROR(__xludf.DUMMYFUNCTION("""COMPUTED_VALUE"""),"Bairro") -> Bairro | J1: =IFERROR(__xludf.DUMMYFUNCTION("""COMPUTED_VALUE"""),"CEP") -> CEP | K1: =IFERROR(__xludf.DUMMYFUNCTION("""COMPUTED_VALUE"""),"Município") -> Município | L1: =IFERROR(__xludf.DUMMYFUNCTION("""COMPUTED_VALUE"""),"UF") -> UF
A2: =IFERROR(__xludf.DUMMYFUNCTION("""COMPUTED_VALUE"""),"ADEPARÁ") -> ADEPARÁ | B2: =IFERROR(__xludf.DUMMYFUNCTION("""COMPUTED_VALUE"""),"Agência de Defesa Agropecuária do Estado do Pará") -> Agência de Defesa Agropecuária do Estado do Pará | C2: =IFERROR(__xludf.DUMMYFUNCTION("""COMPUTED_VALUE"""),"Estadual") -> Estadual | D2: =IFERROR(__xludf.DUMMYFUNCTION("""COMPUTED_VALUE"""),"05.470.347/0001-11") -> 05.470.347/0001-11 | E2: =IFERROR(__xludf.DUMMYFUNCTION("""COMPUTED_VALUE"""),"Jamir Junior Paraguasú Macedo") -> Jamir Junior Paraguasú Macedo | F2: =IFERROR(__xludf.DUMMYFUNCTION("""COMPUTED_VALUE"""),"Diretor Geral") -> Diretor Geral | G2: =IFERROR(__xludf.DUMMYFUNCTION("""COMPUTED_VALUE"""),"(91) 3210-1104 / 3210- 1100") -> (91) 3210-1104 / 3210- 1100 | H2: =IFERROR(__xludf.DUMMYFUNCTION("""COMPUTED_VALUE"""),"Tv. da Estrella, 1184") -> Tv. da Estrella, 1184 | I2: =IFERROR(__xludf.DUMMYFUNCTION("""COMPUTED_VALUE"""),"Pedreira") -> Pedreira | J2: =IFERROR(__xludf.DUMMYFUNCTION("""COMPUTED_VALUE"""),"66080-008") -> 66080-008 | K2: =IFERROR(__xludf.DUMMYFUNCTION("""COMPUTED_VALUE"""),"Belém") -> Belém | L2: =IFERROR(__xludf.DUMMYFUNCTION("""COMPUTED_VALUE"""),"PA") -> PA
A3: =IFERROR(__xludf.DUMMYFUNCTION("""COMPUTED_VALUE"""),"ARCON") -> ARCON | B3: =IFERROR(__xludf.DUMMYFUNCTION("""COMPUTED_VALUE"""),"Agência de Regulação e Controle de Serviços Públicos") -> Agência de Regulação e Controle de Serviços Públicos | C3: =IFERROR(__xludf.DUMMYFUNCTION("""COMPUTED_VALUE"""),"Estadual") -> Estadual | D3: =IFERROR(__xludf.DUMMYFUNCTION("""COMPUTED_VALUE"""),"02.598.119/0001-33") -> 02.598.119/0001-33 | E3: =IFERROR(__xludf.DUMMYFUNCTION("""COMPUTED_VALUE"""),"Fabrício Rodrigues Costa") -> Fabrício Rodrigues Costa | F3: =IFERROR(__xludf.DUMMYFUNCTION("""COMPUTED_VALUE"""),"Diretor Geral") -> Diretor Geral | G3: =IFERROR(__xludf.DUMMYFUNCTION("""COMPUTED_VALUE"""),"(91) 3321- 9680 / 9675") -> (91) 3321- 9680 / 9675 | H3: =IFERROR(__xludf.DUMMYFUNCTION("""COMPUTED_VALUE"""),"Rua dos Pariquis, 1905") -> Rua dos Pariquis, 1905 | I3: =IFERROR(__xludf.DUMMYFUNCTION("""COMPUTED_VALUE"""),"Batista Campos") -> Batista Campos | J3: =IFERROR(__xludf.DUMMYFUNCTION("""COMPUTED_VALUE"""),"66035-370") -> 66035-370 | K3: =IFERROR(__xludf.DUMMYFUNCTION("""COMPUTED_VALUE"""),"Belém") -> Belém | L3: =IFERROR(__xludf.DUMMYFUNCTION("""COMPUTED_VALUE"""),"PA") -> PA
A4: =IFERROR(__xludf.DUMMYFUNCTION("""COMPUTED_VALUE"""),"ARTRAN") -> ARTRAN | B4: =IFERROR(__xludf.DUMMYFUNCTION("""COMPUTED_VALUE"""),"Agência de Regulação e Controle dos Serviços Públicos de Transporte do Estado do Pará") -> Agência de Regulação e Controle dos Serviços Públicos de Transporte do Estado do Pará | C4: =IFERROR(__xludf.DUMMYFUNCTION("""COMPUTED_VALUE"""),"Estadual") -> Estadual | D4: =IFERROR(__xludf.DUMMYFUNCTION("""COMPUTED_VALUE"""),"53.538.860/0001-40") -> 53.538.860/0001-40 | E4: =IFERROR(__xludf.DUMMYFUNCTION("""COMPUTED_VALUE"""),"Eduardo de Castro Ribeiro Junior") -> Eduardo de Castro Ribeiro Junior | F4: =IFERROR(__xludf.DUMMYFUNCTION("""COMPUTED_VALUE"""),"Diretor Geral") -> Diretor Geral | G4: =IFERROR(__xludf.DUMMYFUNCTION("""COMPUTED_VALUE"""),"(91) 98418-5906") -> (91) 98418-5906 | H4: =IFERROR(__xludf.DUMMYFUNCTION("""COMPUTED_VALUE"""),"Rua dos Pariquis, 190") -> Rua dos Pariquis, 190 | I4: =IFERROR(__xludf.DUMMYFUNCTION("""COMPUTED_VALUE"""),"Batista Campos") -> Batista Campos | J4: =IFERROR(__xludf.DUMMYFUNCTION("""COMPUTED_VALUE"""),"66033-11") -> 66033-11 | K4: =IFERROR(__xludf.DUMMYFUNCTION("""COMPUTED_VALUE"""),"Belém") -> Belém | L4: =IFERROR(__xludf.DUMMYFUNCTION("""COMPUTED_VALUE"""),"PA") -> PA
A5: =IFERROR(__xludf.DUMMYFUNCTION("""COMPUTED_VALUE"""),"BANPARÁ") -> BANPARÁ | B5: =IFERROR(__xludf.DUMMYFUNCTION("""COMPUTED_VALUE"""),"Banco do Estado do Pará") -> Banco do Estado do Pará | C5: =IFERROR(__xludf.DUMMYFUNCTION("""COMPUTED_VALUE"""),"Estadual") -> Estadual | D5: =IFERROR(__xludf.DUMMYFUNCTION("""COMPUTED_VALUE"""),"04.913.711/0001-08") -> 04.913.711/0001-08 | E5: =IFERROR(__xludf.DUMMYFUNCTION("""COMPUTED_VALUE"""),"Ruth Pimentel Mello") -> Ruth Pimentel Mello | F5: =IFERROR(__xludf.DUMMYFUNCTION("""COMPUTED_VALUE"""),"Presidente") -> Presidente | H5: =IFERROR(__xludf.DUMMYFUNCTION("""COMPUTED_VALUE"""),"Av. Presidente Vargas, 251") -> Av. Presidente Vargas, 251 | I5: =IFERROR(__xludf.DUMMYFUNCTION("""COMPUTED_VALUE"""),"Campina") -> Campina | J5: =IFERROR(__xludf.DUMMYFUNCTION("""COMPUTED_VALUE"""),"66.010-000") -> 66.010-000 | K5: =IFERROR(__xludf.DUMMYFUNCTION("""COMPUTED_VALUE"""),"Belém") -> Belém | L5: =IFERROR(__xludf.DUMMYFUNCTION("""COMPUTED_VALUE"""),"PA") -> PA
A6: =IFERROR(__xludf.DUMMYFUNCTION("""COMPUTED_VALUE"""),"CM Belém") -> CM Belém | B6: =IFERROR(__xludf.DUMMYFUNCTION("""COMPUTED_VALUE"""),"Câmara Municipal de Belém") -> Câmara Municipal de Belém | C6: =IFERROR(__xludf.DUMMYFUNCTION("""COMPUTED_VALUE"""),"Municipal") -> Municipal | D6: =IFERROR(__xludf.DUMMYFUNCTION("""COMPUTED_VALUE"""),"14.068.357/0001-16") -> 14.068.357/0001-16 | G6: =IFERROR(__xludf.DUMMYFUNCTION("""COMPUTED_VALUE"""),"(91) 4008-2254 ") -> (91) 4008-2254 | K6: =IFERROR(__xludf.DUMMYFUNCTION("""COMPUTED_VALUE"""),"Belém") -> Belém | L6: =IFERROR(__xludf.DUMMYFUNCTION("""COMPUTED_VALUE"""),"PA") -> PA
A7: =IFERROR(__xludf.DUMMYFUNCTION("""COMPUTED_VALUE"""),"CM Anapú") -> CM Anapú | B7: =IFERROR(__xludf.DUMMYFUNCTION("""COMPUTED_VALUE"""),"Câmara Municipal de Anapú") -> Câmara Municipal de Anapú | C7: =IFERROR(__xludf.DUMMYFUNCTION("""COMPUTED_VALUE"""),"Municipal") -> Municipal | D7: =IFERROR(__xludf.DUMMYFUNCTION("""COMPUTED_VALUE"""),"01.681.776/0001-87") -> 01.681.776/0001-87 | G7: =IFERROR(__xludf.DUMMYFUNCTION("""COMPUTED_VALUE"""),"(91) 2222-3333") -> (91) 2222-3333 | H7: =IFERROR(__xludf.DUMMYFUNCTION("""COMPUTED_VALUE"""),"Rua Santa Luzia, nº 102") -> Rua Santa Luzia, nº 102 | K7: =IFERROR(__xludf.DUMMYFUNCTION("""COMPUTED_VALUE"""),"Anapú") -> Anapú | L7: =IFERROR(__xludf.DUMMYFUNCTION("""COMPUTED_VALUE"""),"PA") -> PA
A8: =IFERROR(__xludf.DUMMYFUNCTION("""COMPUTED_VALUE"""),"CM Barcarena") -> CM Barcarena | B8: =IFERROR(__xludf.DUMMYFUNCTION("""COMPUTED_VALUE"""),"Câmara Municipal de Barcarena") -> Câmara Municipal de Barcarena | C8: =IFERROR(__xludf.DUMMYFUNCTION("""COMPUTED_VALUE"""),"Municipal") -> Municipal | D8: =IFERROR(__xludf.DUMMYFUNCTION("""COMPUTED_VALUE"""),"22.943.229/0001-00") -> 22.943.229/0001-00 | G8: =IFERROR(__xludf.DUMMYFUNCTION("""COMPUTED_VALUE""")," (91) 9 8228-3317 ") -> (91) 9 8228-3317 | K8: =IFERROR(__xludf.DUMMYFUNCTION("""COMPUTED_VALUE"""),"Barcarena") -> Barcarena | L8: =IFERROR(__xludf.DUMMYFUNCTION("""COMPUTED_VALUE"""),"PA") -> PA
A9: =IFERROR(__xludf.DUMMYFUNCTION("""COMPUTED_VALUE"""),"CM Cachoeira do Piriá") -> CM Cachoeira do Piriá | B9: =IFERROR(__xludf.DUMMYFUNCTION("""COMPUTED_VALUE"""),"Câmara Municipal de Cachoeira do Piriá") -> Câmara Municipal de Cachoeira do Piriá | C9: =IFERROR(__xludf.DUMMYFUNCTION("""COMPUTED_VALUE"""),"Municipal") -> Municipal | D9: =IFERROR(__xludf.DUMMYFUNCTION("""COMPUTED_VALUE"""),"01.612.359/0001-82") -> 01.612.359/0001-82 | G9: =IFERROR(__xludf.DUMMYFUNCTION("""COMPUTED_VALUE"""),"(91) 9 8596-1331 ") -> (91) 9 8596-1331 | K9: =IFERROR(__xludf.DUMMYFUNCTION("""COMPUTED_VALUE"""),"Cachoeira do Piriá") -> Cachoeira do Piriá | L9: =IFERROR(__xludf.DUMMYFUNCTION("""COMPUTED_VALUE"""),"PA") -> PA
A10: =IFERROR(__xludf.DUMMYFUNCTION("""COMPUTED_VALUE"""),"CM Castanhal") -> CM Castanhal | B10: =IFERROR(__xludf.DUMMYFUNCTION("""COMPUTED_VALUE"""),"Câmara Municipal de Castanhal") -> Câmara Municipal de Castanhal | C10: =IFERROR(__xludf.DUMMYFUNCTION("""COMPUTED_VALUE"""),"Municipal") -> Municipal | D10: =IFERROR(__xludf.DUMMYFUNCTION("""COMPUTED_VALUE"""),"05.111.372/0001-09") -> 05.111.372/0001-09 | G10: =IFERROR(__xludf.DUMMYFUNCTION("""COMPUTED_VALUE"""),"(91) 9 8715-4796 ") -> (91) 9 8715-4796 | K10: =IFERROR(__xludf.DUMMYFUNCTION("""COMPUTED_VALUE"""),"Castanhal") -> Castanhal | L10: =IFERROR(__xludf.DUMMYFUNCTION("""COMPUTED_VALUE"""),"PA") -> PA
A11: =IFERROR(__xludf.DUMMYFUNCTION("""COMPUTED_VALUE"""),"CM Concórdia do Pará") -> CM Concórdia do Pará | B11: =IFERROR(__xludf.DUMMYFUNCTION("""COMPUTED_VALUE"""),"Câmara Municipal de Concórdia do Pará") -> Câmara Municipal de Concórdia do Pará | C11: =IFERROR(__xludf.DUMMYFUNCTION("""COMPUTED_VALUE"""),"Municipal") -> Municipal | D11: =IFERROR(__xludf.DUMMYFUNCTION("""COMPUTED_VALUE"""),"14.145.817/0001-62") -> 14.145.817/0001-62 | G11: =IFERROR(__xludf.DUMMYFUNCTION("""COMPUTED_VALUE"""),"(91) 9 8643-101") -> (91) 9 8643-101 | K11: =IFERROR(__xludf.DUMMYFUNCTION("""COMPUTED_VALUE"""),"Concórdia do Pará") -> Concórdia do Pará | L11: =IFERROR(__xludf.DUMMYFUNCTION("""COMPUTED_VALUE"""),"PA") -> PA
A12: =IFERROR(__xludf.DUMMYFUNCTION("""COMPUTED_VALUE"""),"CM Itaituba") -> CM Itaituba | B12: =IFERROR(__xludf.DUMMYFUNCTION("""COMPUTED_VALUE"""),"Câmara Municipal de Itaituba") -> Câmara Municipal de Itaituba | C12: =IFERROR(__xludf.DUMMYFUNCTION("""COMPUTED_VALUE"""),"Municipal") -> Municipal | D12: =IFERROR(__xludf.DUMMYFUNCTION("""COMPUTED_VALUE"""),"10.221.281/0001-66") -> 10.221.281/0001-66 | G12: =IFERROR(__xludf.DUMMYFUNCTION("""COMPUTED_VALUE"""),"(93) 9 9184-0402 ") -> (93) 9 9184-0402 | K12: =IFERROR(__xludf.DUMMYFUNCTION("""COMPUTED_VALUE"""),"Itaituba") -> Itaituba | L12: =IFERROR(__xludf.DUMMYFUNCTION("""COMPUTED_VALUE"""),"PA") -> PA
A13: =IFERROR(__xludf.DUMMYFUNCTION("""COMPUTED_VALUE"""),"CM Marituba") -> CM Marituba | B13: =IFERROR(__xludf.DUMMYFUNCTION("""COMPUTED_VALUE"""),"Câmara Municipal de Marituba") -> Câmara Municipal de Marituba | C13: =IFERROR(__xludf.DUMMYFUNCTION("""COMPUTED_VALUE"""),"Municipal") -> Municipal | D13: =IFERROR(__xludf.DUMMYFUNCTION("""COMPUTED_VALUE"""),"01.615.610/0001-62") -> 01.615.610/0001-62 | G13: =IFERROR(__xludf.DUMMYFUNCTION("""COMPUTED_VALUE""")," (91) 3256- 5667 ") -> (91) 3256- 5667 | K13: =IFERROR(__xludf.DUMMYFUNCTION("""COMPUTED_VALUE"""),"Marituba") -> Marituba | L13: =IFERROR(__xludf.DUMMYFUNCTION("""COMPUTED_VALUE"""),"PA") -> PA
A14: =IFERROR(__xludf.DUMMYFUNCTION("""COMPUTED_VALUE"""),"CM Óbidos") -> CM Óbidos | B14: =IFERROR(__xludf.DUMMYFUNCTION("""COMPUTED_VALUE"""),"Câmara Municipal de Óbidos") -> Câmara Municipal de Óbidos | C14: =IFERROR(__xludf.DUMMYFUNCTION("""COMPUTED_VALUE"""),"Municipal") -> Municipal | D14: =IFERROR(__xludf.DUMMYFUNCTION("""COMPUTED_VALUE"""),"05.131.180/0001-64") -> 05.131.180/0001-64 | G14: =IFERROR(__xludf.DUMMYFUNCTION("""COMPUTED_VALUE""")," (93) 9 9152-6161 ") -> (93) 9 9152-6161 | K14: =IFERROR(__xludf.DUMMYFUNCTION("""COMPUTED_VALUE"""),"Óbidos") -> Óbidos | L14: =IFERROR(__xludf.DUMMYFUNCTION("""COMPUTED_VALUE"""),"PA") -> PA
A15: =IFERROR(__xludf.DUMMYFUNCTION("""COMPUTED_VALUE"""),"CM Oriximiná") -> CM Oriximiná | B15: =IFERROR(__xludf.DUMMYFUNCTION("""COMPUTED_VALUE"""),"Câmara Municipal de Oriximiná") -> Câmara Municipal de Oriximiná | C15: =IFERROR(__xludf.DUMMYFUNCTION("""COMPUTED_VALUE"""),"Municipal") -> Municipal | D15: =IFERROR(__xludf.DUMMYFUNCTION("""COMPUTED_VALUE"""),"04.546.941/0001-86") -> 04.546.941/0001-86 | G15: =IFERROR(__xludf.DUMMYFUNCTION("""COMPUTED_VALUE"""),"(93) 9 9134-5575 ") -> (93) 9 9134-5575 | K15: =IFERROR(__xludf.DUMMYFUNCTION("""COMPUTED_VALUE"""),"Oriximiná") -> Oriximiná | L15: =IFERROR(__xludf.DUMMYFUNCTION("""COMPUTED_VALUE"""),"PA") -> PA
A16: =IFERROR(__xludf.DUMMYFUNCTION("""COMPUTED_VALUE"""),"CM Prainha") -> CM Prainha | B16: =IFERROR(__xludf.DUMMYFUNCTION("""COMPUTED_VALUE"""),"Câmara Municipal de Prainha") -> Câmara Municipal de Prainha | C16: =IFERROR(__xludf.DUMMYFUNCTION("""COMPUTED_VALUE"""),"Municipal") -> Municipal | D16: =IFERROR(__xludf.DUMMYFUNCTION("""COMPUTED_VALUE"""),"10.220.671/0001-11") -> 10.220.671/0001-11 | G16: =IFERROR(__xludf.DUMMYFUNCTION("""COMPUTED_VALUE"""),"(93) 9 8411-3416 ") -> (93) 9 8411-3416 | K16: =IFERROR(__xludf.DUMMYFUNCTION("""COMPUTED_VALUE"""),"Prainha") -> Prainha | L16: =IFERROR(__xludf.DUMMYFUNCTION("""COMPUTED_VALUE"""),"PA") -> PA
A17: =IFERROR(__xludf.DUMMYFUNCTION("""COMPUTED_VALUE"""),"CM Santana do Araguaia") -> CM Santana do Araguaia | B17: =IFERROR(__xludf.DUMMYFUNCTION("""COMPUTED_VALUE"""),"Câmara Municipal de Santana do Araguaia") -> Câmara Municipal de Santana do Araguaia | C17: =IFERROR(__xludf.DUMMYFUNCTION("""COMPUTED_VALUE"""),"Municipal") -> Municipal | K17: =IFERROR(__xludf.DUMMYFUNCTION("""COMPUTED_VALUE"""),"Santana do Araguaia") -> Santana do Araguaia | L17: =IFERROR(__xludf.DUMMYFUNCTION("""COMPUTED_VALUE"""),"PA") -> PA
A18: =IFERROR(__xludf.DUMMYFUNCTION("""COMPUTED_VALUE"""),"CM Tucumã") -> CM Tucumã | B18: =IFERROR(__xludf.DUMMYFUNCTION("""COMPUTED_VALUE"""),"Câmara Municipal de Tucumã") -> Câmara Municipal de Tucumã | C18: =IFERROR(__xludf.DUMMYFUNCTION("""COMPUTED_VALUE"""),"Municipal") -> Municipal | D18: =IFERROR(__xludf.DUMMYFUNCTION("""COMPUTED_VALUE"""),"22.981.088/0001-02") -> 22.981.088/0001-02 | K18: =IFERROR(__xludf.DUMMYFUNCTION("""COMPUTED_VALUE"""),"Tucumã") -> Tucumã | L18: =IFERROR(__xludf.DUMMYFUNCTION("""COMPUTED_VALUE"""),"PA") -> PA
A19: =IFERROR(__xludf.DUMMYFUNCTION("""COMPUTED_VALUE"""),"CCG") -> CCG | B19: =IFERROR(__xludf.DUMMYFUNCTION("""COMPUTED_VALUE"""),"Casa Civil da Governadoria do Estado") -> Casa Civil da Governadoria do Estado | C19: =IFERROR(__xludf.DUMMYFUNCTION("""COMPUTED_VALUE"""),"Estadual") -> Estadual | D19: =IFERROR(__xludf.DUMMYFUNCTION("""COMPUTED_VALUE"""),"07.730.458/0001-45") -> 07.730.458/0001-45 | E19: =IFERROR(__xludf.DUMMYFUNCTION("""COMPUTED_VALUE"""),"Luiziel Henderson Guedes de Oliveira") -> Luiziel Henderson Guedes de Oliveira | F19: =IFERROR(__xludf.DUMMYFUNCTION("""COMPUTED_VALUE"""),"Chefe") -> Chefe | G19: =IFERROR(__xludf.DUMMYFUNCTION("""COMPUTED_VALUE"""),"(91) 3216 -8831") -> (91) 3216 -8831 | H19: =IFERROR(__xludf.DUMMYFUNCTION("""COMPUTED_VALUE"""),"Av. Dr. Freitas, 2.531.") -> Av. Dr. Freitas, 2.531. | I19: =IFERROR(__xludf.DUMMYFUNCTION("""COMPUTED_VALUE"""),"Marco") -> Marco | J19: =IFERROR(__xludf.DUMMYFUNCTION("""COMPUTED_VALUE"""),"66087-812") -> 66087-812 | K19: =IFERROR(__xludf.DUMMYFUNCTION("""COMPUTED_VALUE"""),"Belém") -> Belém | L19: =IFERROR(__xludf.DUMMYFUNCTION("""COMPUTED_VALUE"""),"PA") -> PA
A20: =IFERROR(__xludf.DUMMYFUNCTION("""COMPUTED_VALUE"""),"CMG") -> CMG | B20: =IFERROR(__xludf.DUMMYFUNCTION("""COMPUTED_VALUE"""),"Casa MIlitar da Governadoria do Estado") -> Casa MIlitar da Governadoria do Estado | C20: =IFERROR(__xludf.DUMMYFUNCTION("""COMPUTED_VALUE"""),"Estadual") -> Estadual | D20: =IFERROR(__xludf.DUMMYFUNCTION("""COMPUTED_VALUE"""),"07.313.542/0001-63") -> 07.313.542/0001-63 | E20: =IFERROR(__xludf.DUMMYFUNCTION("""COMPUTED_VALUE"""),"Cel. PM. Osmar Vieira da Costa Júnior") -> Cel. PM. Osmar Vieira da Costa Júnior | F20: =IFERROR(__xludf.DUMMYFUNCTION("""COMPUTED_VALUE"""),"Chefe") -> Chefe | G20: =IFERROR(__xludf.DUMMYFUNCTION("""COMPUTED_VALUE"""),"(91) 3321-9700") -> (91) 3321-9700 | H20: =IFERROR(__xludf.DUMMYFUNCTION("""COMPUTED_VALUE"""),"Av. Almirante Barroso esquina com, Av. Dr. Freitas") -> Av. Almirante Barroso esquina com, Av. Dr. Freitas | I20: =IFERROR(__xludf.DUMMYFUNCTION("""COMPUTED_VALUE"""),"Marco") -> Marco | J20: =IFERROR(__xludf.DUMMYFUNCTION("""COMPUTED_VALUE"""),"66087-812") -> 66087-812 | K20: =IFERROR(__xludf.DUMMYFUNCTION("""COMPUTED_VALUE"""),"Belém") -> Belém | L20: =IFERROR(__xludf.DUMMYFUNCTION("""COMPUTED_VALUE"""),"PA") -> PA
A21: =IFERROR(__xludf.DUMMYFUNCTION("""COMPUTED_VALUE"""),"CEASA") -> CEASA | B21: =IFERROR(__xludf.DUMMYFUNCTION("""COMPUTED_VALUE"""),"Centrais de Abastecimento do Pará S/A") -> Centrais de Abastecimento do Pará S/A | C21: =IFERROR(__xludf.DUMMYFUNCTION("""COMPUTED_VALUE"""),"Estadual") -> Estadual | D21: =IFERROR(__xludf.DUMMYFUNCTION("""COMPUTED_VALUE"""),"04.819.728/0001-09") -> 04.819.728/0001-09 | E21: =IFERROR(__xludf.DUMMYFUNCTION("""COMPUTED_VALUE"""),"Raimundo José Pinheiro dos Santos Júnior") -> Raimundo José Pinheiro dos Santos Júnior | F21: =IFERROR(__xludf.DUMMYFUNCTION("""COMPUTED_VALUE"""),"Presidente") -> Presidente | L21: =IFERROR(__xludf.DUMMYFUNCTION("""COMPUTED_VALUE"""),"PA") -> PA
A22: =IFERROR(__xludf.DUMMYFUNCTION("""COMPUTED_VALUE"""),"COHAB") -> COHAB | B22: =IFERROR(__xludf.DUMMYFUNCTION("""COMPUTED_VALUE"""),"Comnhia de Habitação do Estado do Pará") -> Comnhia de Habitação do Estado do Pará | C22: =IFERROR(__xludf.DUMMYFUNCTION("""COMPUTED_VALUE"""),"Estadual") -> Estadual | D22: =IFERROR(__xludf.DUMMYFUNCTION("""COMPUTED_VALUE"""),"04.887.055/0001-16") -> 04.887.055/0001-16 | E22: =IFERROR(__xludf.DUMMYFUNCTION("""COMPUTED_VALUE"""),"Manoel Carlos Antunes") -> Manoel Carlos Antunes | F22: =IFERROR(__xludf.DUMMYFUNCTION("""COMPUTED_VALUE"""),"Presidente") -> Presidente | L22: =IFERROR(__xludf.DUMMYFUNCTION("""COMPUTED_VALUE"""),"PA") -> PA
A23: =IFERROR(__xludf.DUMMYFUNCTION("""COMPUTED_VALUE"""),"CODEC") -> CODEC | B23: =IFERROR(__xludf.DUMMYFUNCTION("""COMPUTED_VALUE"""),"Companhia de Desenvolvimento Econômico do Pará") -> Companhia de Desenvolvimento Econômico do Pará | C23: =IFERROR(__xludf.DUMMYFUNCTION("""COMPUTED_VALUE"""),"Estadual") -> Estadual | D23: =IFERROR(__xludf.DUMMYFUNCTION("""COMPUTED_VALUE"""),"05.416.839/0001-29") -> 05.416.839/0001-29 | E23: =IFERROR(__xludf.DUMMYFUNCTION("""COMPUTED_VALUE"""),"Lutfala de Castro Bitar") -> Lutfala de Castro Bitar | F23: =IFERROR(__xludf.DUMMYFUNCTION("""COMPUTED_VALUE"""),"Presidente") -> Presidente | L23: =IFERROR(__xludf.DUMMYFUNCTION("""COMPUTED_VALUE"""),"PA") -> PA
A24: =IFERROR(__xludf.DUMMYFUNCTION("""COMPUTED_VALUE"""),"GASPARÁ") -> GASPARÁ | B24: =IFERROR(__xludf.DUMMYFUNCTION("""COMPUTED_VALUE"""),"Companhia de Gás do Pará") -> Companhia de Gás do Pará | C24: =IFERROR(__xludf.DUMMYFUNCTION("""COMPUTED_VALUE"""),"Estadual") -> Estadual | D24: =IFERROR(__xludf.DUMMYFUNCTION("""COMPUTED_VALUE"""),"08.454.441/0001-75") -> 08.454.441/0001-75 | E24: =IFERROR(__xludf.DUMMYFUNCTION("""COMPUTED_VALUE"""),"Fernando de Souza Flexa Ribeiro") -> Fernando de Souza Flexa Ribeiro | F24: =IFERROR(__xludf.DUMMYFUNCTION("""COMPUTED_VALUE"""),"Presidente") -> Presidente | H24: =IFERROR(__xludf.DUMMYFUNCTION("""COMPUTED_VALUE"""),"Ed. Quadra Corporate - Av. Visc. de Souza Franco, 05") -> Ed. Quadra Corporate - Av. Visc. de Souza Franco, 05 | I24: =IFERROR(__xludf.DUMMYFUNCTION("""COMPUTED_VALUE"""),"Umarizal") -> Umarizal | J24: =IFERROR(__xludf.DUMMYFUNCTION("""COMPUTED_VALUE"""),"66055-005") -> 66055-005 | L24: =IFERROR(__xludf.DUMMYFUNCTION("""COMPUTED_VALUE"""),"PA") -> PA
A25: =IFERROR(__xludf.DUMMYFUNCTION("""COMPUTED_VALUE"""),"CINBESA") -> CINBESA | B25: =IFERROR(__xludf.DUMMYFUNCTION("""COMPUTED_VALUE"""),"Companhia de Informática de Belém") -> Companhia de Informática de Belém | C25: =IFERROR(__xludf.DUMMYFUNCTION("""COMPUTED_VALUE"""),"Estadual") -> Estadual | D25: =IFERROR(__xludf.DUMMYFUNCTION("""COMPUTED_VALUE"""),"04.850.095/0001-93") -> 04.850.095/0001-93 | E25: =IFERROR(__xludf.DUMMYFUNCTION("""COMPUTED_VALUE"""),"Gustavo Bezerra da Costa") -> Gustavo Bezerra da Costa | F25: =IFERROR(__xludf.DUMMYFUNCTION("""COMPUTED_VALUE"""),"Diretor Presidente") -> Diretor Presidente | G25: =IFERROR(__xludf.DUMMYFUNCTION("""COMPUTED_VALUE"""),"(91) 3251-4476") -> (91) 3251-4476 | H25: =IFERROR(__xludf.DUMMYFUNCTION("""COMPUTED_VALUE"""),"Tv. Quintino Bocaiúva, 1503") -> Tv. Quintino Bocaiúva, 1503 | I25: =IFERROR(__xludf.DUMMYFUNCTION("""COMPUTED_VALUE"""),"Nazaré") -> Nazaré | J25: =IFERROR(__xludf.DUMMYFUNCTION("""COMPUTED_VALUE"""),"66035-190") -> 66035-190 | K25: =IFERROR(__xludf.DUMMYFUNCTION("""COMPUTED_VALUE"""),"Belém") -> Belém | L25: =IFERROR(__xludf.DUMMYFUNCTION("""COMPUTED_VALUE"""),"PA") -> PA
A26: =IFERROR(__xludf.DUMMYFUNCTION("""COMPUTED_VALUE"""),"CPH") -> CPH | B26: =IFERROR(__xludf.DUMMYFUNCTION("""COMPUTED_VALUE"""),"Companhia de Portos e hidrovias do Estado do Pará") -> Companhia de Portos e hidrovias do Estado do Pará | C26: =IFERROR(__xludf.DUMMYFUNCTION("""COMPUTED_VALUE"""),"Estadual") -> Estadual | D26: =IFERROR(__xludf.DUMMYFUNCTION("""COMPUTED_VALUE"""),"05.452.160/0001-95") -> 05.452.160/0001-95 | E26: =IFERROR(__xludf.DUMMYFUNCTION("""COMPUTED_VALUE"""),"Josenir Gonçalves Nascimento") -> Josenir Gonçalves Nascimento | F26: =IFERROR(__xludf.DUMMYFUNCTION("""COMPUTED_VALUE"""),"Presidente") -> Presidente | G26: =IFERROR(__xludf.DUMMYFUNCTION("""COMPUTED_VALUE"""),"(91) 3221-4102 / 4100 / 4103") -> (91) 3221-4102 / 4100 / 4103 | H26: =IFERROR(__xludf.DUMMYFUNCTION("""COMPUTED_VALUE"""),"Av. Generalíssimo Deodoro 367") -> Av. Generalíssimo Deodoro 367 | J26: =IFERROR(__xludf.DUMMYFUNCTION("""COMPUTED_VALUE"""),"66050-160") -> 66050-160 | K26: =IFERROR(__xludf.DUMMYFUNCTION("""COMPUTED_VALUE"""),"Belém") -> Belém | L26: =IFERROR(__xludf.DUMMYFUNCTION("""COMPUTED_VALUE"""),"PA") -> PA
A27: =IFERROR(__xludf.DUMMYFUNCTION("""COMPUTED_VALUE"""),"COSANPA") -> COSANPA | B27: =IFERROR(__xludf.DUMMYFUNCTION("""COMPUTED_VALUE"""),"Companhia de Saneamento do Pará") -> Companhia de Saneamento do Pará | C27: =IFERROR(__xludf.DUMMYFUNCTION("""COMPUTED_VALUE"""),"Estadual") -> Estadual | D27: =IFERROR(__xludf.DUMMYFUNCTION("""COMPUTED_VALUE"""),"04.945.341/0001-90") -> 04.945.341/0001-90 | E27: =IFERROR(__xludf.DUMMYFUNCTION("""COMPUTED_VALUE"""),"José Fernando de Mendonça Gomes Junior") -> José Fernando de Mendonça Gomes Junior | F27: =IFERROR(__xludf.DUMMYFUNCTION("""COMPUTED_VALUE"""),"Presidente") -> Presidente | G27: =IFERROR(__xludf.DUMMYFUNCTION("""COMPUTED_VALUE"""),"55(91) 3202-8534 / 8539") -> 55(91) 3202-8534 / 8539 | H27: =IFERROR(__xludf.DUMMYFUNCTION("""COMPUTED_VALUE"""),"Av. Magalhães Barata, 1201") -> Av. Magalhães Barata, 1201 | I27: =IFERROR(__xludf.DUMMYFUNCTION("""COMPUTED_VALUE"""),"São Brás") -> São Brás | K27: =IFERROR(__xludf.DUMMYFUNCTION("""COMPUTED_VALUE"""),"Belém") -> Belém | L27: =IFERROR(__xludf.DUMMYFUNCTION("""COMPUTED_VALUE"""),"PA") -> PA
A28: =IFERROR(__xludf.DUMMYFUNCTION("""COMPUTED_VALUE"""),"CGE") -> CGE | B28: =IFERROR(__xludf.DUMMYFUNCTION("""COMPUTED_VALUE"""),"Controladoria Geral do Estado do Pará") -> Controladoria Geral do Estado do Pará | C28: =IFERROR(__xludf.DUMMYFUNCTION("""COMPUTED_VALUE"""),"Estadual") -> Estadual | D28: =IFERROR(__xludf.DUMMYFUNCTION("""COMPUTED_VALUE"""),"03.269.619/0001-94") -> 03.269.619/0001-94 | E28: =IFERROR(__xludf.DUMMYFUNCTION("""COMPUTED_VALUE"""),"Marcos André Mendes Azevedo Cantuária Nobre") -> Marcos André Mendes Azevedo Cantuária Nobre | F28: =IFERROR(__xludf.DUMMYFUNCTION("""COMPUTED_VALUE"""),"Controlador Geral") -> Controlador Geral | G28: =IFERROR(__xludf.DUMMYFUNCTION("""COMPUTED_VALUE"""),"(91) 3239-6450 / 6477") -> (91) 3239-6450 / 6477 | H28: =IFERROR(__xludf.DUMMYFUNCTION("""COMPUTED_VALUE"""),"Rua Municipalidade, 1655") -> Rua Municipalidade, 1655 | I28: =IFERROR(__xludf.DUMMYFUNCTION("""COMPUTED_VALUE"""),"Umarizal") -> Umarizal | J28: =IFERROR(__xludf.DUMMYFUNCTION("""COMPUTED_VALUE"""),"66050-350") -> 66050-350 | K28: =IFERROR(__xludf.DUMMYFUNCTION("""COMPUTED_VALUE"""),"Belém") -> Belém | L28: =IFERROR(__xludf.DUMMYFUNCTION("""COMPUTED_VALUE"""),"PA") -> PA
A29: =IFERROR(__xludf.DUMMYFUNCTION("""COMPUTED_VALUE"""),"CBM") -> CBM | B29: =IFERROR(__xludf.DUMMYFUNCTION("""COMPUTED_VALUE"""),"Corpos de Bombeiros Militares") -> Corpos de Bombeiros Militares | C29: =IFERROR(__xludf.DUMMYFUNCTION("""COMPUTED_VALUE"""),"Estadual") -> Estadual | D29: =IFERROR(__xludf.DUMMYFUNCTION("""COMPUTED_VALUE"""),"34.847.236/0001-80") -> 34.847.236/0001-80 | E29: =IFERROR(__xludf.DUMMYFUNCTION("""COMPUTED_VALUE"""),"Col. QOBM Jayme de Aviz Benjó") -> Col. QOBM Jayme de Aviz Benjó | F29: =IFERROR(__xludf.DUMMYFUNCTION("""COMPUTED_VALUE"""),"comandante Geral") -> comandante Geral | G29: =IFERROR(__xludf.DUMMYFUNCTION("""COMPUTED_VALUE"""),"(91) 4006-8399") -> (91) 4006-8399 | H29: =IFERROR(__xludf.DUMMYFUNCTION("""COMPUTED_VALUE"""),"Avenida Júlio César, 3000") -> Avenida Júlio César, 3000 | I29: =IFERROR(__xludf.DUMMYFUNCTION("""COMPUTED_VALUE"""),"Val-de-cans") -> Val-de-cans | J29: =IFERROR(__xludf.DUMMYFUNCTION("""COMPUTED_VALUE"""),"68447-000") -> 68447-000 | K29: =IFERROR(__xludf.DUMMYFUNCTION("""COMPUTED_VALUE"""),"Belém") -> Belém | L29: =IFERROR(__xludf.DUMMYFUNCTION("""COMPUTED_VALUE"""),"PA") -> PA
A30: =IFERROR(__xludf.DUMMYFUNCTION("""COMPUTED_VALUE"""),"DEFPUB") -> DEFPUB | B30: =IFERROR(__xludf.DUMMYFUNCTION("""COMPUTED_VALUE"""),"Defensoria Pública do Estado do Pará") -> Defensoria Pública do Estado do Pará | C30: =IFERROR(__xludf.DUMMYFUNCTION("""COMPUTED_VALUE"""),"Estadual") -> Estadual | D30: =IFERROR(__xludf.DUMMYFUNCTION("""COMPUTED_VALUE"""),"34.639.526/0001-38") -> 34.639.526/0001-38 | E30: =IFERROR(__xludf.DUMMYFUNCTION("""COMPUTED_VALUE"""),"Mônica Palheta Furtado") -> Mônica Palheta Furtado | F30: =IFERROR(__xludf.DUMMYFUNCTION("""COMPUTED_VALUE"""),"Defensora Pública") -> Defensora Pública | H30: =IFERROR(__xludf.DUMMYFUNCTION("""COMPUTED_VALUE"""),"Rua Padre Prudêncio, n° 154") -> Rua Padre Prudêncio, n° 154 | I30: =IFERROR(__xludf.DUMMYFUNCTION("""COMPUTED_VALUE"""),"Campina") -> Campina | J30: =IFERROR(__xludf.DUMMYFUNCTION("""COMPUTED_VALUE"""),"66019-080") -> 66019-080 | K30: =IFERROR(__xludf.DUMMYFUNCTION("""COMPUTED_VALUE"""),"Belém") -> Belém | L30: =IFERROR(__xludf.DUMMYFUNCTION("""COMPUTED_VALUE"""),"PA") -> PA
A31: =IFERROR(__xludf.DUMMYFUNCTION("""COMPUTED_VALUE"""),"DETRAN") -> DETRAN | B31: =IFERROR(__xludf.DUMMYFUNCTION("""COMPUTED_VALUE"""),"Departamento de Transito do Estado do Pará") -> Departamento de Transito do Estado do Pará | C31: =IFERROR(__xludf.DUMMYFUNCTION("""COMPUTED_VALUE"""),"Estadual") -> Estadual | D31: =IFERROR(__xludf.DUMMYFUNCTION("""COMPUTED_VALUE"""),"04.822.060/0001-40") -> 04.822.060/0001-40 | E31: =IFERROR(__xludf.DUMMYFUNCTION("""COMPUTED_VALUE"""),"Renata Mirella Freitas Guimaarães de Sousa Coelho") -> Renata Mirella Freitas Guimaarães de Sousa Coelho | F31: =IFERROR(__xludf.DUMMYFUNCTION("""COMPUTED_VALUE"""),"Diretora") -> Diretora | G31: =IFERROR(__xludf.DUMMYFUNCTION("""COMPUTED_VALUE"""),"(91) 3214-6235") -> (91) 3214-6235 | H31: =IFERROR(__xludf.DUMMYFUNCTION("""COMPUTED_VALUE"""),"Rod. Augusto Montenegro, S/N") -> Rod. Augusto Montenegro, S/N | I31: =IFERROR(__xludf.DUMMYFUNCTION("""COMPUTED_VALUE"""),"Mangueirão") -> Mangueirão | J31: =IFERROR(__xludf.DUMMYFUNCTION("""COMPUTED_VALUE"""),"66640-000") -> 66640-000 | K31: =IFERROR(__xludf.DUMMYFUNCTION("""COMPUTED_VALUE"""),"Belém") -> Belém | L31: =IFERROR(__xludf.DUMMYFUNCTION("""COMPUTED_VALUE"""),"PA") -> PA
A32: =IFERROR(__xludf.DUMMYFUNCTION("""COMPUTED_VALUE"""),"EMATER") -> EMATER | B32: =IFERROR(__xludf.DUMMYFUNCTION("""COMPUTED_VALUE"""),"Empresa de Assistência Técnica e Extensão Rural") -> Empresa de Assistência Técnica e Extensão Rural | C32: =IFERROR(__xludf.DUMMYFUNCTION("""COMPUTED_VALUE"""),"Estadual") -> Estadual | D32: =IFERROR(__xludf.DUMMYFUNCTION("""COMPUTED_VALUE"""),"05.402.797/0001-77") -> 05.402.797/0001-77 | E32: =IFERROR(__xludf.DUMMYFUNCTION("""COMPUTED_VALUE"""),"Joniel VIeira de Abreu") -> Joniel VIeira de Abreu | F32: =IFERROR(__xludf.DUMMYFUNCTION("""COMPUTED_VALUE"""),"presidente") -> presidente | G32: =IFERROR(__xludf.DUMMYFUNCTION("""COMPUTED_VALUE"""),"(91) 3299 - 3413 : (91) 98887-6155") -> (91) 3299 - 3413 : (91) 98887-6155 | H32: =IFERROR(__xludf.DUMMYFUNCTION("""COMPUTED_VALUE"""),"BR 316, KM 12") -> BR 316, KM 12 | I32: =IFERROR(__xludf.DUMMYFUNCTION("""COMPUTED_VALUE"""),"Bela Vista") -> Bela Vista | K32: =IFERROR(__xludf.DUMMYFUNCTION("""COMPUTED_VALUE"""),"Marituba") -> Marituba | L32: =IFERROR(__xludf.DUMMYFUNCTION("""COMPUTED_VALUE"""),"PA") -> PA
A33: =IFERROR(__xludf.DUMMYFUNCTION("""COMPUTED_VALUE"""),"PRODEPA") -> PRODEPA | B33: =IFERROR(__xludf.DUMMYFUNCTION("""COMPUTED_VALUE"""),"Empresa de Tecnologia da Informação e comunicação do Estado do Pará") -> Empresa de Tecnologia da Informação e comunicação do Estado do Pará | C33: =IFERROR(__xludf.DUMMYFUNCTION("""COMPUTED_VALUE"""),"Estadual") -> Estadual | D33: =IFERROR(__xludf.DUMMYFUNCTION("""COMPUTED_VALUE"""),"05.059.613/0001-18") -> 05.059.613/0001-18 | E33: =IFERROR(__xludf.DUMMYFUNCTION("""COMPUTED_VALUE"""),"Carlos Edilson de Almeida Maneschy") -> Carlos Edilson de Almeida Maneschy | F33: =IFERROR(__xludf.DUMMYFUNCTION("""COMPUTED_VALUE"""),"Presidente") -> Presidente | G33: =IFERROR(__xludf.DUMMYFUNCTION("""COMPUTED_VALUE"""),"(91) 3251- 7502") -> (91) 3251- 7502 | H33: =IFERROR(__xludf.DUMMYFUNCTION("""COMPUTED_VALUE"""),"Rod. Augusto Montenegro - Centro") -> Rod. Augusto Montenegro - Centro | I33: =IFERROR(__xludf.DUMMYFUNCTION("""COMPUTED_VALUE"""),"Tenoné") -> Tenoné | J33: =IFERROR(__xludf.DUMMYFUNCTION("""COMPUTED_VALUE"""),"66820-000") -> 66820-000 | K33: =IFERROR(__xludf.DUMMYFUNCTION("""COMPUTED_VALUE"""),"Belém") -> Belém | L33: =IFERROR(__xludf.DUMMYFUNCTION("""COMPUTED_VALUE"""),"PA") -> PA
A34: =IFERROR(__xludf.DUMMYFUNCTION("""COMPUTED_VALUE"""),"EGPA") -> EGPA | B34: =IFERROR(__xludf.DUMMYFUNCTION("""COMPUTED_VALUE"""),"Escola de Governança Pública do Estado do Pará") -> Escola de Governança Pública do Estado do Pará | C34: =IFERROR(__xludf.DUMMYFUNCTION("""COMPUTED_VALUE"""),"Estadual") -> Estadual | D34: =IFERROR(__xludf.DUMMYFUNCTION("""COMPUTED_VALUE"""),"05.914.738/0001-33") -> 05.914.738/0001-33 | E34: =IFERROR(__xludf.DUMMYFUNCTION("""COMPUTED_VALUE"""),"Hélvio Moreira Arruda") -> Hélvio Moreira Arruda | F34: =IFERROR(__xludf.DUMMYFUNCTION("""COMPUTED_VALUE"""),"Diretor") -> Diretor | H34: =IFERROR(__xludf.DUMMYFUNCTION("""COMPUTED_VALUE"""),"Av. Gov. José Malcher, 900") -> Av. Gov. José Malcher, 900 | L34: =IFERROR(__xludf.DUMMYFUNCTION("""COMPUTED_VALUE"""),"PA") -> PA
A35: =IFERROR(__xludf.DUMMYFUNCTION("""COMPUTED_VALUE"""),"EGPA") -> EGPA | B35: =IFERROR(__xludf.DUMMYFUNCTION("""COMPUTED_VALUE"""),"Escola de Governo do Estado do Pará") -> Escola de Governo do Estado do Pará | C35: =IFERROR(__xludf.DUMMYFUNCTION("""COMPUTED_VALUE"""),"Estadual") -> Estadual | L35: =IFERROR(__xludf.DUMMYFUNCTION("""COMPUTED_VALUE"""),"PA") -> PA
A36: =IFERROR(__xludf.DUMMYFUNCTION("""COMPUTED_VALUE"""),"FAPESPA") -> FAPESPA | B36: =IFERROR(__xludf.DUMMYFUNCTION("""COMPUTED_VALUE"""),"Fundação Amazônia de Amparo a Estudos e Pesquisas") -> Fundação Amazônia de Amparo a Estudos e Pesquisas | C36: =IFERROR(__xludf.DUMMYFUNCTION("""COMPUTED_VALUE"""),"Estadual") -> Estadual | D36: =IFERROR(__xludf.DUMMYFUNCTION("""COMPUTED_VALUE"""),"09.025.418/0001-28") -> 09.025.418/0001-28 | E36: =IFERROR(__xludf.DUMMYFUNCTION("""COMPUTED_VALUE"""),"Marcel do Nascimento Botelho") -> Marcel do Nascimento Botelho | F36: =IFERROR(__xludf.DUMMYFUNCTION("""COMPUTED_VALUE"""),"Presidente") -> Presidente | G36: =IFERROR(__xludf.DUMMYFUNCTION("""COMPUTED_VALUE"""),"(91) 3323- 2573 / 2574") -> (91) 3323- 2573 / 2574 | H36: =IFERROR(__xludf.DUMMYFUNCTION("""COMPUTED_VALUE"""),"Tv. Nove de Janeiro, 1686") -> Tv. Nove de Janeiro, 1686 | I36: =IFERROR(__xludf.DUMMYFUNCTION("""COMPUTED_VALUE"""),"Fátima") -> Fátima | J36: =IFERROR(__xludf.DUMMYFUNCTION("""COMPUTED_VALUE"""),"66060-575") -> 66060-575 | K36: =IFERROR(__xludf.DUMMYFUNCTION("""COMPUTED_VALUE"""),"Belém") -> Belém | L36: =IFERROR(__xludf.DUMMYFUNCTION("""COMPUTED_VALUE"""),"PA") -> PA
A37: =IFERROR(__xludf.DUMMYFUNCTION("""COMPUTED_VALUE"""),"FCG") -> FCG | B37: =IFERROR(__xludf.DUMMYFUNCTION("""COMPUTED_VALUE"""),"Fundação Carlos Gomes") -> Fundação Carlos Gomes | C37: =IFERROR(__xludf.DUMMYFUNCTION("""COMPUTED_VALUE"""),"Estadual") -> Estadual | D37: =IFERROR(__xludf.DUMMYFUNCTION("""COMPUTED_VALUE"""),"14.700.157/0001-34") -> 14.700.157/0001-34 | E37: =IFERROR(__xludf.DUMMYFUNCTION("""COMPUTED_VALUE"""),"Gabriel Mariano de Aguiar Titan") -> Gabriel Mariano de Aguiar Titan | F37: =IFERROR(__xludf.DUMMYFUNCTION("""COMPUTED_VALUE"""),"Superintendente") -> Superintendente | H37: =IFERROR(__xludf.DUMMYFUNCTION("""COMPUTED_VALUE"""),"Av. Gentil Bittencourt, nº 909") -> Av. Gentil Bittencourt, nº 909 | I37: =IFERROR(__xludf.DUMMYFUNCTION("""COMPUTED_VALUE"""),"Nazaré") -> Nazaré | J37: =IFERROR(__xludf.DUMMYFUNCTION("""COMPUTED_VALUE"""),"66040-000") -> 66040-000 | K37: =IFERROR(__xludf.DUMMYFUNCTION("""COMPUTED_VALUE"""),"Belém") -> Belém | L37: =IFERROR(__xludf.DUMMYFUNCTION("""COMPUTED_VALUE"""),"PA") -> PA
A38: =IFERROR(__xludf.DUMMYFUNCTION("""COMPUTED_VALUE"""),"HEMOPA") -> HEMOPA | B38: =IFERROR(__xludf.DUMMYFUNCTION("""COMPUTED_VALUE"""),"Fundação Centro de Hemoterapia e Hematologia do Pará") -> Fundação Centro de Hemoterapia e Hematologia do Pará | C38: =IFERROR(__xludf.DUMMYFUNCTION("""COMPUTED_VALUE"""),"Estadual") -> Estadual | D38: =IFERROR(__xludf.DUMMYFUNCTION("""COMPUTED_VALUE"""),"05.837.521/0001-11") -> 05.837.521/0001-11 | E38: =IFERROR(__xludf.DUMMYFUNCTION("""COMPUTED_VALUE"""),"Paulo André Castelo Branco Bezerra Presidente") -> Paulo André Castelo Branco Bezerra Presidente | F38: =IFERROR(__xludf.DUMMYFUNCTION("""COMPUTED_VALUE"""),"Presidente") -> Presidente | L38: =IFERROR(__xludf.DUMMYFUNCTION("""COMPUTED_VALUE"""),"PA") -> PA
A39: =IFERROR(__xludf.DUMMYFUNCTION("""COMPUTED_VALUE"""),"FCP") -> FCP | B39: =IFERROR(__xludf.DUMMYFUNCTION("""COMPUTED_VALUE"""),"Fundação Cultural do Estado do Pará") -> Fundação Cultural do Estado do Pará | C39: =IFERROR(__xludf.DUMMYFUNCTION("""COMPUTED_VALUE"""),"Estadual") -> Estadual | D39: =IFERROR(__xludf.DUMMYFUNCTION("""COMPUTED_VALUE"""),"14.662.886/0001-43") -> 14.662.886/0001-43 | E39: =IFERROR(__xludf.DUMMYFUNCTION("""COMPUTED_VALUE"""),"Thiago Farias Miranda") -> Thiago Farias Miranda | F39: =IFERROR(__xludf.DUMMYFUNCTION("""COMPUTED_VALUE"""),"Presidente") -> Presidente | H39: =IFERROR(__xludf.DUMMYFUNCTION("""COMPUTED_VALUE"""),"Avenida Gentil Bittencourt, nº 650") -> Avenida Gentil Bittencourt, nº 650 | I39: =IFERROR(__xludf.DUMMYFUNCTION("""COMPUTED_VALUE"""),"Nazará") -> Nazará | J39: =IFERROR(__xludf.DUMMYFUNCTION("""COMPUTED_VALUE"""),"66.035-340") -> 66.035-340 | K39: =IFERROR(__xludf.DUMMYFUNCTION("""COMPUTED_VALUE"""),"Belém") -> Belém | L39: =IFERROR(__xludf.DUMMYFUNCTION("""COMPUTED_VALUE"""),"PA") -> PA
A40: =IFERROR(__xludf.DUMMYFUNCTION("""COMPUTED_VALUE"""),"FADEP") -> FADEP | B40: =IFERROR(__xludf.DUMMYFUNCTION("""COMPUTED_VALUE"""),"Fundação de Apoio para o Desenvolvimento da Educação Paraense") -> Fundação de Apoio para o Desenvolvimento da Educação Paraense | C40: =IFERROR(__xludf.DUMMYFUNCTION("""COMPUTED_VALUE"""),"Estadual") -> Estadual | D40: =IFERROR(__xludf.DUMMYFUNCTION("""COMPUTED_VALUE"""),"34.860.833/0001-44") -> 34.860.833/0001-44 | E40: =IFERROR(__xludf.DUMMYFUNCTION("""COMPUTED_VALUE"""),"Arnaldo Dopazo Antonio JOsé") -> Arnaldo Dopazo Antonio JOsé | F40: =IFERROR(__xludf.DUMMYFUNCTION("""COMPUTED_VALUE"""),"Presidente") -> Presidente | H40: =IFERROR(__xludf.DUMMYFUNCTION("""COMPUTED_VALUE"""),"Rod. Augusto Montenegro, Km 10, s/n") -> Rod. Augusto Montenegro, Km 10, s/n | I40: =IFERROR(__xludf.DUMMYFUNCTION("""COMPUTED_VALUE"""),"Icoaraci") -> Icoaraci | J40: =IFERROR(__xludf.DUMMYFUNCTION("""COMPUTED_VALUE"""),"66820-000") -> 66820-000 | K40: =IFERROR(__xludf.DUMMYFUNCTION("""COMPUTED_VALUE"""),"Belém") -> Belém | L40: =IFERROR(__xludf.DUMMYFUNCTION("""COMPUTED_VALUE"""),"PA") -> PA
A41: =IFERROR(__xludf.DUMMYFUNCTION("""COMPUTED_VALUE"""),"FASEPA") -> FASEPA | B41: =IFERROR(__xludf.DUMMYFUNCTION("""COMPUTED_VALUE"""),"Fundação de Atendimento Sócio Educativo do Pará") -> Fundação de Atendimento Sócio Educativo do Pará | C41: =IFERROR(__xludf.DUMMYFUNCTION("""COMPUTED_VALUE"""),"Estadual") -> Estadual | D41: =IFERROR(__xludf.DUMMYFUNCTION("""COMPUTED_VALUE"""),"84.154.186/0001-23") -> 84.154.186/0001-23 | E41: =IFERROR(__xludf.DUMMYFUNCTION("""COMPUTED_VALUE"""),"Carlos Alberto de Andrade Rodrigues Junior") -> Carlos Alberto de Andrade Rodrigues Junior | F41: =IFERROR(__xludf.DUMMYFUNCTION("""COMPUTED_VALUE"""),"Presidente") -> Presidente | G41: =IFERROR(__xludf.DUMMYFUNCTION("""COMPUTED_VALUE"""),"(91) 3210- 3308") -> (91) 3210- 3308 | H41: =IFERROR(__xludf.DUMMYFUNCTION("""COMPUTED_VALUE"""),"Rua Diogo Moia, 1.101") -> Rua Diogo Moia, 1.101 | I41: =IFERROR(__xludf.DUMMYFUNCTION("""COMPUTED_VALUE"""),"Umarizal") -> Umarizal | K41: =IFERROR(__xludf.DUMMYFUNCTION("""COMPUTED_VALUE"""),"Belém") -> Belém | L41: =IFERROR(__xludf.DUMMYFUNCTION("""COMPUTED_VALUE"""),"PA") -> PA
A42: =IFERROR(__xludf.DUMMYFUNCTION("""COMPUTED_VALUE"""),"FUNTELPA") -> FUNTELPA | B42: =IFERROR(__xludf.DUMMYFUNCTION("""COMPUTED_VALUE"""),"Fundação Paraense de Radiodifusão") -> Fundação Paraense de Radiodifusão | C42: =IFERROR(__xludf.DUMMYFUNCTION("""COMPUTED_VALUE"""),"Estadual") -> Estadual | D42: =IFERROR(__xludf.DUMMYFUNCTION("""COMPUTED_VALUE"""),"11.953.923/0001-84") -> 11.953.923/0001-84 | E42: =IFERROR(__xludf.DUMMYFUNCTION("""COMPUTED_VALUE"""),"Valdemiro Eduardo de Assis Sanova Nascimento") -> Valdemiro Eduardo de Assis Sanova Nascimento | F42: =IFERROR(__xludf.DUMMYFUNCTION("""COMPUTED_VALUE"""),"Presidente") -> Presidente | G42: =IFERROR(__xludf.DUMMYFUNCTION("""COMPUTED_VALUE"""),"(91)3202-4300") -> (91)3202-4300 | H42: =IFERROR(__xludf.DUMMYFUNCTION("""COMPUTED_VALUE"""),"Av. Gentile Bittencourt, 650") -> Av. Gentile Bittencourt, 650 | I42: =IFERROR(__xludf.DUMMYFUNCTION("""COMPUTED_VALUE"""),"Nazará") -> Nazará | J42: =IFERROR(__xludf.DUMMYFUNCTION("""COMPUTED_VALUE"""),"66.035-340") -> 66.035-340 | L42: =IFERROR(__xludf.DUMMYFUNCTION("""COMPUTED_VALUE"""),"PA") -> PA
A43: =IFERROR(__xludf.DUMMYFUNCTION("""COMPUTED_VALUE"""),"FPARAPAZ") -> FPARAPAZ | B43: =IFERROR(__xludf.DUMMYFUNCTION("""COMPUTED_VALUE"""),"Fundação Parápaz") -> Fundação Parápaz | C43: =IFERROR(__xludf.DUMMYFUNCTION("""COMPUTED_VALUE"""),"Estadual") -> Estadual | D43: =IFERROR(__xludf.DUMMYFUNCTION("""COMPUTED_VALUE"""),"21.648.632/0001-36") -> 21.648.632/0001-36 | E43: =IFERROR(__xludf.DUMMYFUNCTION("""COMPUTED_VALUE"""),"Alberto Henrique Teixeira de Barros") -> Alberto Henrique Teixeira de Barros | F43: =IFERROR(__xludf.DUMMYFUNCTION("""COMPUTED_VALUE"""),"Presidente") -> Presidente | G43: =IFERROR(__xludf.DUMMYFUNCTION("""COMPUTED_VALUE"""),"(91) 3321 -4303") -> (91) 3321 -4303 | H43: =IFERROR(__xludf.DUMMYFUNCTION("""COMPUTED_VALUE"""),"Avenida José Bonifácio, 267") -> Avenida José Bonifácio, 267 | I43: =IFERROR(__xludf.DUMMYFUNCTION("""COMPUTED_VALUE"""),"Fátima") -> Fátima | J43: =IFERROR(__xludf.DUMMYFUNCTION("""COMPUTED_VALUE"""),"66090-363") -> 66090-363 | K43: =IFERROR(__xludf.DUMMYFUNCTION("""COMPUTED_VALUE"""),"Belém") -> Belém | L43: =IFERROR(__xludf.DUMMYFUNCTION("""COMPUTED_VALUE"""),"PA") -> PA
A44: =IFERROR(__xludf.DUMMYFUNCTION("""COMPUTED_VALUE"""),"FHCGV") -> FHCGV | B44: =IFERROR(__xludf.DUMMYFUNCTION("""COMPUTED_VALUE"""),"Fundação Pública Estadual Hospital de Clínicas Gaspar Vianna") -> Fundação Pública Estadual Hospital de Clínicas Gaspar Vianna | C44: =IFERROR(__xludf.DUMMYFUNCTION("""COMPUTED_VALUE"""),"Estadual") -> Estadual | D44: =IFERROR(__xludf.DUMMYFUNCTION("""COMPUTED_VALUE"""),"22.980.973/0001-77") -> 22.980.973/0001-77 | E44: =IFERROR(__xludf.DUMMYFUNCTION("""COMPUTED_VALUE"""),"Heliosa Maria Melo e Silva Guimarães") -> Heliosa Maria Melo e Silva Guimarães | F44: =IFERROR(__xludf.DUMMYFUNCTION("""COMPUTED_VALUE"""),"Presidente") -> Presidente | G44: =IFERROR(__xludf.DUMMYFUNCTION("""COMPUTED_VALUE"""),"(91) 3110- 1201") -> (91) 3110- 1201 | H44: =IFERROR(__xludf.DUMMYFUNCTION("""COMPUTED_VALUE"""),"Tv. Alferes Costa, S/N") -> Tv. Alferes Costa, S/N | I44: =IFERROR(__xludf.DUMMYFUNCTION("""COMPUTED_VALUE"""),"Pedreira") -> Pedreira | K44: =IFERROR(__xludf.DUMMYFUNCTION("""COMPUTED_VALUE"""),"Belém") -> Belém | L44: =IFERROR(__xludf.DUMMYFUNCTION("""COMPUTED_VALUE"""),"PA") -> PA
A45: =IFERROR(__xludf.DUMMYFUNCTION("""COMPUTED_VALUE"""),"FSCMPA") -> FSCMPA | B45: =IFERROR(__xludf.DUMMYFUNCTION("""COMPUTED_VALUE"""),"Fundação Santa Casa de Misericórdia") -> Fundação Santa Casa de Misericórdia | C45: =IFERROR(__xludf.DUMMYFUNCTION("""COMPUTED_VALUE"""),"Estadual") -> Estadual | D45: =IFERROR(__xludf.DUMMYFUNCTION("""COMPUTED_VALUE"""),"04.929.345/0001-85") -> 04.929.345/0001-85 | E45: =IFERROR(__xludf.DUMMYFUNCTION("""COMPUTED_VALUE"""),"Bruno Mendes Carmona") -> Bruno Mendes Carmona | H45: =IFERROR(__xludf.DUMMYFUNCTION("""COMPUTED_VALUE"""),"Rua Oliveira Belo, 395") -> Rua Oliveira Belo, 395 | I45: =IFERROR(__xludf.DUMMYFUNCTION("""COMPUTED_VALUE"""),"Umarizal") -> Umarizal | J45: =IFERROR(__xludf.DUMMYFUNCTION("""COMPUTED_VALUE"""),"66050-380") -> 66050-380 | K45: =IFERROR(__xludf.DUMMYFUNCTION("""COMPUTED_VALUE"""),"Belém") -> Belém | L45: =IFERROR(__xludf.DUMMYFUNCTION("""COMPUTED_VALUE"""),"PA") -> PA
A46: =IFERROR(__xludf.DUMMYFUNCTION("""COMPUTED_VALUE"""),"HOL") -> HOL | B46: =IFERROR(__xludf.DUMMYFUNCTION("""COMPUTED_VALUE"""),"Hospital Ophir Loyola") -> Hospital Ophir Loyola | C46: =IFERROR(__xludf.DUMMYFUNCTION("""COMPUTED_VALUE"""),"Estadual") -> Estadual | D46: =IFERROR(__xludf.DUMMYFUNCTION("""COMPUTED_VALUE"""),"08.109.444/0001-71") -> 08.109.444/0001-71 | E46: =IFERROR(__xludf.DUMMYFUNCTION("""COMPUTED_VALUE"""),"Dr. Heraldo Francisco da Costa Pedreira") -> Dr. Heraldo Francisco da Costa Pedreira | H46: =IFERROR(__xludf.DUMMYFUNCTION("""COMPUTED_VALUE"""),"Avenida Governador Magalhães Barata, 992") -> Avenida Governador Magalhães Barata, 992 | I46: =IFERROR(__xludf.DUMMYFUNCTION("""COMPUTED_VALUE"""),"São Bráz") -> São Bráz | K46: =IFERROR(__xludf.DUMMYFUNCTION("""COMPUTED_VALUE"""),"Belém") -> Belém | L46: =IFERROR(__xludf.DUMMYFUNCTION("""COMPUTED_VALUE"""),"PA") -> PA
A47: =IFERROR(__xludf.DUMMYFUNCTION("""COMPUTED_VALUE"""),"IOEPA") -> IOEPA | B47: =IFERROR(__xludf.DUMMYFUNCTION("""COMPUTED_VALUE"""),"Imprensa Oficial do Estado do Pará") -> Imprensa Oficial do Estado do Pará | C47: =IFERROR(__xludf.DUMMYFUNCTION("""COMPUTED_VALUE"""),"Estadual") -> Estadual | D47: =IFERROR(__xludf.DUMMYFUNCTION("""COMPUTED_VALUE"""),"48.066.047/0001-84") -> 48.066.047/0001-84 | E47: =IFERROR(__xludf.DUMMYFUNCTION("""COMPUTED_VALUE"""),"Jorge Luiz Guimarães Panzera") -> Jorge Luiz Guimarães Panzera | F47: =IFERROR(__xludf.DUMMYFUNCTION("""COMPUTED_VALUE"""),"Presidente") -> Presidente
